Workbook

Sheet Tx_croissance
A1: Country Name | B1: Country Code | C1: Series Name | D1: 1995 [YR1995] | E1: 1996 [YR1996] | F1: 1997 [YR1997] | G1: 1998 [YR1998] | H1: 1999 [YR1999] | I1: 2000 [YR2000] | J1: 2001 [YR2001] | K1: 2002 [YR2002] | L1: 2003 [YR2003] | M1: 2004 [YR2004] | N1: 2005 [YR2005] | O1: 2006 [YR2006] | P1: 2007 [YR2007] | Q1: 2008 [YR2008] | R1: 2009 [YR2009] | S1: 2010 [YR2010] | T1: 2011 [YR2011] | U1: 2012 [YR2012] | V1: 2013 [YR2013] | W1: 2014 [YR2014] | X1: 2015 [YR2015] | Y1: 2016 [YR2016] | Z1: 2017 [YR2017] | AA1: 2018 [YR2018] | AB1: 2019 [YR2019] | AC1: 2020 [YR2020] | AD1: 2021 [YR2021] | AE1: 2022 [YR2022]
A2: Afghanistan | B2: AFG | C2: GDP per capita (constant 2015 US$) | D2: .. | E2: .. | F2: .. | G2: .. | H2: .. | I2: .. | J2: .. | K2: 344.22418 | L2: 347.41524 | M2: 338.7394 | N2: 363.54147 | O2: 367.48585 | P2: 410.86161 | Q2: 418.52317 | R2: 490.27284 | S2: 544.6893 | T2: 527.19734 | U2: 570.67606 | V2: 582.10398 | W2: 576.48782 | X2: 566.88113 | Y2: 564.92084 | Z2: 563.48824 | AA2: 553.97331 | AB2: 559.14096 | AC2: 529.14491 | AD2: 407.61651 | AE2: .. | AH2: =IFERROR(((AE2/D2)^(1/27)-1)*100,"NA") -> NA
A3: Albania | B3: ALB | C3: GDP per capita (constant 2015 US$) | D3: 1488.0209 | E3: 1633.552 | F3: 1464.298 | G3: 1603.6477 | H3: 1821.8731 | I3: 1960.8825 | J3: 2143.5268 | K3: 2247.4981 | L3: 2380.6446 | M3: 2522.4494 | N3: 2675.5086 | O3: 2851.3678 | P3: 3044.8966 | Q3: 3298.4789 | R3: 3432.1709 | S3: 3577.1143 | T3: 3678.0477 | U3: 3736.3401 | V3: 3780.6992 | W3: 3855.7607 | X3: 3952.8036 | Y3: 4090.3727 | Z3: 4249.82 | AA3: 4431.5556 | AB3: 4543.3877 | AC3: 4418.6609 | AD3: 4857.1119 | AE3: 5155.2909 | AH3: =IFERROR(((AE3/D3)^(1/27)-1)*100,"NA") -> 4.7096771
A4: Algeria | B4: DZA | C4: GDP per capita (constant 2015 US$) | D4: 2862.1079 | E4: 2927.3774 | F4: 2910.2392 | G4: 3012.8054 | H4: 3066.0377 | I4: 3138.23 | J4: 3188.2062 | K4: 3321.6378 | L4: 3512.899 | M4: 3612.753 | N4: 3774.0713 | O4: 3783.313 | P4: 3848.7783 | Q4: 3874.3681 | R4: 3866.2958 | S4: 3931.7201 | T4: 3969.6603 | U4: 4025.6415 | V4: 4057.7648 | W4: 4129.4225 | X4: 4197.42 | Y4: 4246.2422 | Z4: 4218.0823 | AA4: 4188.2204 | AB4: 4153.0035 | AC4: 3873.5087 | AD4: 3939.3609 | AE4: 3999.7577 | AH4: =IFERROR(((AE4/D4)^(1/27)-1)*100,"NA") -> 1.2472527
A5: American Samoa | B5: ASM | C5: GDP per capita (constant 2015 US$) | D5: .. | E5: .. | F5: .. | G5: .. | H5: .. | I5: .. | J5: .. | K5: 12804.436 | L5: 12980.722 | M5: 13105.169 | N5: 13136.48 | O5: 12690.529 | P5: 13029.616 | Q5: 12795.025 | R5: 12378.17 | S5: 12532.311 | T5: 12656.688 | U5: 12247.635 | V5: 12098.275 | W5: 12494.98 | X5: 13101.542 | Y5: 13116.431 | Z5: 12442.858 | AA5: 13049.33 | AB5: 13288.357 | AC5: 14214.646 | AD5: 14464.814 | AE5: 14969.06 | AH5: =IFERROR(((AE5/D5)^(1/27)-1)*100,"NA") -> NA
A6: Andorra | B6: AND | C6: GDP per capita (constant 2015 US$) | D6: 28051.403 | E6: 28797.867 | F6: 31149.37 | G6: 31895.996 | H6: 32966.252 | I6: 33901.193 | J6: 35722.546 | K6: 35749.946 | L6: 37250.313 | M6: 38696.513 | N6: 39307.159 | O6: 40994.467 | P6: 42724.587 | Q6: 41470.457 | R6: 40442.804 | S6: 40937.293 | T6: 41486.219 | U6: 39174.916 | V6: 37597.723 | W6: 38402.667 | X6: 38885.549 | Y6: 39886.659 | Z6: 39321.633 | AA6: 39320.111 | AB6: 39413.809 | AC6: 34394.43 | AD6: 36616.118 | AE6: 39447.538 | AH6: =IFERROR(((AE6/D6)^(1/27)-1)*100,"NA") -> 1.2707207
A7: Angola | B7: AGO | C7: GDP per capita (constant 2015 US$) | D7: 1675.7081 | E7: 1840.3541 | F7: 1909.4689 | G7: 1934.558 | H7: 1913.9989 | I7: 1909.5021 | J7: 1925.508 | K7: 2116.8517 | L7: 2106.9859 | M7: 2257.1524 | N7: 2505.655 | O7: 2696.4411 | P7: 2964.3355 | Q7: 3176.6722 | R7: 3087.8114 | S7: 3105.4497 | T7: 3094.7339 | U7: 3235.1746 | V7: 3270.9663 | W7: 3304.6812 | X7: 3217.3392 | Y7: 3023.9163 | Z7: 2914.1271 | AA7: 2777.843 | AB7: 2666.2539 | AC7: 2435.0249 | AD7: 2387.4299 | AE7: 2385.12 | AH7: =IFERROR(((AE7/D7)^(1/27)-1)*100,"NA") -> 1.3160424
A8: Antigua and Barbuda | B8: ATG | C8: GDP per capita (constant 2015 US$) | D8: 13584.273 | E8: 14190.974 | F8: 14669.016 | G8: 15076.393 | H8: 15370.828 | I8: 16055.954 | J8: 15092.469 | K8: 15053.966 | L8: 15788.74 | M8: 16516.087 | N8: 17380.986 | O8: 19341.328 | P8: 20854.062 | Q8: 20541.753 | R8: 17809.933 | S8: 16191.157 | T8: 15684.781 | U8: 15739.035 | V8: 15668.436 | W8: 15882.309 | X8: 15985.541 | Y8: 16526.436 | Z8: 16830.396 | AA8: 17901.041 | AB8: 18357.679 | AC8: 14803.77 | AD8: 15921.095 | AE8: 17335.047 | AH8: =IFERROR(((AE8/D8)^(1/27)-1)*100,"NA") -> 0.90711749
A9: Argentina | B9: ARG | C9: GDP per capita (constant 2015 US$) | D9: 9969.3316 | E9: 10388.539 | F9: 11097.382 | G9: 11391.945 | H9: 10880.206 | I9: 10672.722 | J9: 10090.653 | K9: 8895.3196 | L9: 9581.9698 | M9: 10341.643 | N9: 11141.311 | O9: 11913.959 | P9: 12857.093 | Q9: 13246.635 | R9: 12336.862 | S9: 13551.339 | T9: 14200.27 | U9: 13895.634 | V9: 14071.509 | W9: 13567.948 | X9: 13789.06 | Y9: 13360.212 | Z9: 13595.037 | AA9: 13105.397 | AB9: 12716.224 | AC9: 11346.652 | AD9: 12444.318 | AE9: 12940.738 | AH9: =IFERROR(((AE9/D9)^(1/27)-1)*100,"NA") -> 0.97085591
A10: Armenia | B10: ARM | C10: GDP per capita (constant 2015 US$) | D10: 928.0925 | E10: 989.64234 | F10: 1031.0983 | G10: 1116.9072 | H10: 1166.188 | I10: 1249.6121 | J10: 1385.0448 | K10: 1582.0576 | L10: 1815.7882 | M10: 2018.4601 | N10: 2312.9829 | O10: 2636.2566 | P10: 3019.4656 | Q10: 3250.4986 | R10: 2810.1928 | S10: 2889.5662 | T10: 3043.2628 | U10: 3278.6704 | V10: 3402.0839 | W10: 3538.5294 | X10: 3666.1418 | Y10: 3689.8301 | Z10: 3985.9167 | AA10: 4215.8994 | AB10: 4561.9678 | AC10: 4256.1312 | AD10: 4526.5975 | AE10: 5116.2058 | AH10: =IFERROR(((AE10/D10)^(1/27)-1)*100,"NA") -> 6.5264997
A11: Aruba | B11: ABW | C11: GDP per capita (constant 2015 US$) | D11: 29497.963 | E11: 28958.144 | F11: 30074.406 | G11: 29765.515 | H11: 29262.616 | I11: 30703.661 | J11: 31426.879 | K11: 30760.207 | L11: 30793.135 | M11: 32742.761 | N11: 32291.769 | O11: 32272.251 | P11: 32863.362 | Q11: 33053.767 | R11: 28836.017 | S11: 27732.214 | T11: 28398.558 | U11: 27876.206 | V11: 29447.58 | W11: 28780.631 | X11: 28419.265 | Y11: 28737.896 | Z11: 30598.649 | AA11: 31172.802 | AB11: 30317.607 | AC11: 23015.742 | AD11: 29390.381 | AE11: 32492.179 | AH11: =IFERROR(((AE11/D11)^(1/27)-1)*100,"NA") -> 0.35870917
A12: Australia | B12: AUS | C12: GDP per capita (constant 2015 US$) | D12: 39309.995 | E12: 40336.299 | F12: 41463.646 | G12: 42966.793 | H12: 44636.024 | I12: 45858.58 | J12: 46190.381 | K12: 47485.341 | L12: 48393.137 | M12: 49901.015 | N12: 50852.161 | O12: 51552.894 | P12: 52530.702 | Q12: 53335.006 | R12: 53235.924 | S12: 53581.159 | T12: 54114.726 | U12: 55261.918 | V12: 55734.574 | W12: 56341.134 | X12: 56758.869 | Y12: 57432.18 | Z12: 57804.051 | AA12: 58600.79 | AB12: 59000.735 | AC12: 58082.427 | AD12: 59225.525 | AE12: 60993.641 | AH12: =IFERROR(((AE12/D12)^(1/27)-1)*100,"NA") -> 1.6403108
A13: Austria | B13: AUT | C13: GDP per capita (constant 2015 US$) | D13: 33790.485 | E13: 34537.74 | F13: 35220.888 | G13: 36442.288 | H13: 37664.943 | I13: 38842.891 | J13: 39184.809 | K13: 39636.483 | L13: 39815.222 | M13: 40651.227 | N13: 41281.271 | O13: 42496.351 | P13: 43937.713 | Q13: 44440.056 | R13: 42655.192 | S13: 43334.509 | T13: 44451 | U13: 44549.882 | V13: 44299.378 | W13: 44245.169 | X13: 44195.818 | Y13: 44590.252 | Z13: 45281.723 | AA13: 46154.625 | AB13: 46616.359 | AC13: 43343.972 | AD13: 44984.42 | AE13: 46697.857 | AH13: =IFERROR(((AE13/D13)^(1/27)-1)*100,"NA") -> 1.205426
A14: Azerbaijan | B14: AZE | C14: GDP per capita (constant 2015 US$) | D14: 1102.4979 | E14: 1105.5872 | F14: 1158.4817 | G14: 1262.2919 | H14: 1343.8559 | I14: 1480.8087 | J14: 1614.8489 | K14: 1754.1352 | L14: 1918.611 | M14: 2077.8853 | N14: 2631.8515 | O14: 3501.1648 | P14: 4327.1136 | Q14: 4693.0771 | R14: 5023.9673 | S14: 5215.2042 | T14: 5152.8385 | U14: 5194.9209 | V14: 5426.0959 | W14: 5506.1817 | X14: 5500.5036 | Y14: 5270.7382 | Z14: 5229.7099 | AA14: 5262.3687 | AB14: 5348.4532 | AC14: 5083.5603 | AD14: 5345.4399 | AE14: 5590.0044 | AH14: =IFERROR(((AE14/D14)^(1/27)-1)*100,"NA") -> 6.1970333
A15: Bahamas, The | B15: BHS | C15: GDP per capita (constant 2015 US$) | D15: 28410.556 | E15: 29088.157 | F15: 28965.19 | G15: 29828.746 | H15: 31473.369 | I15: 32300.766 | J15: 32685.179 | K15: 33129.484 | L15: 32276.72 | M15: 32125.044 | N15: 32765.745 | O15: 33127.423 | P15: 33136.488 | Q15: 31908.932 | R15: 30139.453 | S15: 30175.639 | T15: 29984.884 | U15: 30577.734 | V15: 29426.023 | W15: 29701.458 | X15: 29724.953 | Y15: 29253.891 | Z15: 29763.505 | AA15: 30412.133 | AB15: 29988.165 | AC15: 22830.504 | AD15: 26614.19 | AE15: 30283.897 | AH15: =IFERROR(((AE15/D15)^(1/27)-1)*100,"NA") -> 0.2367812
A16: Bahrain | B16: BHR | C16: GDP per capita (constant 2015 US$) | D16: 20403.371 | E16: 20576.515 | F16: 20566.557 | G16: 20915.833 | H16: 21195.901 | I16: 21713.538 | J16: 21681.028 | K16: 21866.049 | L16: 22348.905 | M16: 22325.703 | N16: 22027.331 | O16: 21783.852 | P16: 22013.758 | Q16: 21918.005 | R16: 21157.793 | S16: 21452.922 | T16: 21906.746 | U16: 22484.855 | V16: 23012.708 | W16: 23107.957 | X16: 22795.449 | Y16: 22810.775 | Z16: 23019.256 | AA16: 23023.12 | AB16: 23414.219 | AC16: 22579.362 | AD16: 23407.196 | AE16: 24395.472 | AH16: =IFERROR(((AE16/D16)^(1/27)-1)*100,"NA") -> 0.66403743
A17: Bangladesh | B17: BGD | C17: GDP per capita (constant 2015 US$) | D17: 559.68923 | E17: 574.83582 | F17: 590.00279 | G17: 609.01356 | H17: 625.36385 | I17: 646.03776 | J17: 666.06776 | K17: 678.86751 | L17: 698.73209 | M17: 723.22784 | N17: 758.88997 | O17: 799.78147 | P17: 847.28195 | Q17: 890.29617 | R17: 927.01809 | S17: 967.56108 | T17: 1017.6277 | U17: 1070.5952 | V17: 1120.6853 | W17: 1173.893 | X17: 1236.0044 | Y17: 1307.7323 | Z17: 1376.6035 | AA17: 1460.3042 | AB17: 1557.9643 | AC17: 1593.3474 | AD17: 1684.4335 | AE17: 1784.7389 | AH17: =IFERROR(((AE17/D17)^(1/27)-1)*100,"NA") -> 4.3885534
... A23: Bermuda | B23: BMU | C23: GDP per capita (constant 2015 US$) | D23: 89518.278 | E23: 91261.151 | F23: 94878.492 | G23: 97857.323 | H23: 100602.93 | I23: 109001.59 | J23: 115619.47 | K23: 113172.12 | L23: 116268.82 | M23: 118193.15 | N23: 119396.45 | O23: 125294.96 | P23: 128757.88 | Q23: 125610.03 | R23: 117886.74 | S23: 115839.8 | T23: 112471.35 | U23: 106119.8 | V23: 105492.48 | W23: 101374.47 | X23: 102005.63 | Y23: 102407.39 | Z23: 107237.03 | AA23: 106697.74 | AB23: 107036.24 | AC23: 99745.242 | AD23: 102959.25 | AE23: 106359.97 | AH23: =IFERROR(((AE23/D23)^(1/27)-1)*100,"NA") -> 0.64051094
A24: Bhutan | B24: BTN | C24: GDP per capita (constant 2015 US$) | D24: 944.40756 | E24: 978.49497 | F24: 1013.4093 | G24: 1053.542 | H24: 1110.0673 | I24: 1115.6253 | J24: 1176.6533 | K24: 1272.6318 | L24: 1338.5086 | M24: 1385.3964 | N24: 1456.4798 | O24: 1535.4279 | P24: 1795.0718 | Q24: 1859.0704 | R24: 1961.9388 | S24: 2171.9098 | T24: 2319.5909 | U24: 2411.8964 | V24: 2436.8598 | W24: 2551.4831 | X24: 2695.6369 | Y24: 2889.4939 | Z24: 2998.4732 | AA24: 3079.144 | AB24: 3233.5979 | AC24: 2884.2087 | AD24: 2992.4393 | AE24: .. | AH24: =IFERROR(((AE24/D24)^(1/27)-1)*100,"NA") -> NA
A25: Bolivia | B25: BOL | C25: GDP per capita (constant 2015 US$) | D25: 1866.6529 | E25: 1912.0023 | F25: 1970.1681 | G25: 2031.9722 | H25: 2003.8613 | I25: 2017.3946 | J25: 2015.3775 | K25: 2029.6179 | L25: 2048.5598 | M25: 2097.2584 | N25: 2152.362 | O25: 2216.5447 | P25: 2277.5038 | Q25: 2376.0781 | R25: 2414.1299 | S25: 2471.4736 | T25: 2556.8303 | U25: 2643.6908 | V25: 2777.7205 | W25: 2882.8069 | X25: 2975.6488 | Y25: 3054.8925 | Z25: 3135.0316 | AA25: 3219.2009 | AB25: 3242.9488 | AC25: 2920.1974 | AD25: 3061.8993 | AE25: 3134.7663 | AH25: =IFERROR(((AE25/D25)^(1/27)-1)*100,"NA") -> 1.9385795
A26: Bosnia and Herzegovina | B26: BIH | C26: GDP per capita (constant 2015 US$) | D26: 784.6187 | E26: 1422.9465 | F26: 1846.1525 | G26: 2099.2434 | H26: 2279.7437 | I26: 2554.5641 | J26: 2606.7504 | K26: 2735.5353 | L26: 2851.2736 | M26: 3061.5514 | N26: 3218.5942 | O26: 3423.124 | P26: 3669.0168 | Q26: 3932.0153 | R26: 3878.4405 | S26: 3980.4423 | T26: 4091.5819 | U26: 4133.9027 | V26: 4297.4935 | W26: 4403.6739 | X26: 4654.6086 | Y26: 4865.3513 | Z26: 5082.9973 | AA26: 5339.4771 | AB26: 5558.0814 | AC26: 5459.2196 | AD26: 5947.8193 | AE26: 6263.7021 | AH26: =IFERROR(((AE26/D26)^(1/27)-1)*100,"NA") -> 7.9975228
A27: Botswana | B27: BWA | C27: GDP per capita (constant 2015 US$) | D27: 4271.4709 | E27: 4410.3889 | F27: 4667.8859 | G27: 4585.6741 | H27: 4922.3739 | I27: 4917.2321 | J27: 4831.7838 | K27: 5030.2652 | L27: 5171.5413 | M27: 5219.4145 | N27: 5360.0192 | O27: 5700.2199 | P27: 5913.0699 | Q27: 5982.662 | R27: 5031.9836 | S27: 5428.2962 | T27: 5684.3579 | U27: 5566.6818 | V27: 6067.9984 | W27: 6291.2718 | X27: 5869.7376 | Y27: 6166.2399 | Z27: 6287.8347 | AA27: 6418.7064 | AB27: 6485.5682 | AC27: 5810.8985 | AD27: 6395.1397 | AE27: 6657.5851 | AH27: =IFERROR(((AE27/D27)^(1/27)-1)*100,"NA") -> 1.6572815
A28: Brazil | B28: BRA | C28: GDP per capita (constant 2015 US$) | D28: 6524.5189 | E28: 6567.3525 | F28: 6689.1994 | G28: 6613.9832 | H28: 6551.2267 | I28: 6745.8578 | J28: 6749.8816 | K28: 6868.6959 | L28: 6865.1733 | M28: 7178.3475 | N28: 7325.9036 | O28: 7534.5425 | P28: 7909.8252 | Q28: 8231.1004 | R28: 8142.761 | S28: 8673.8984 | T28: 8935.2773 | U28: 9025.314 | V28: 9216.1323 | W28: 9183.4597 | X28: 8783.2154 | Y28: 8426.8432 | Z28: 8470.9406 | AA28: 8553.8659 | AB28: 8592.2112 | AC28: 8255.568 | AD28: 8621.7316 | AE28: 8831.1277 | AH28: =IFERROR(((AE28/D28)^(1/27)-1)*100,"NA") -> 1.1274772
A29: British Virgin Islands | B29: VGB | C29: GDP per capita (constant 2015 US$) | D29: .. | E29: .. | F29: .. | G29: .. | H29: .. | I29: .. | J29: .. | K29: .. | L29: .. | M29: .. | N29: .. | O29: .. | P29: .. | Q29: .. | R29: .. | S29: .. | T29: .. | U29: .. | V29: .. | W29: .. | X29: .. | Y29: .. | Z29: .. | AA29: .. | AB29: .. | AC29: .. | AD29: .. | AE29: .. | AH29: =IFERROR(((AE29/D29)^(1/27)-1)*100,"NA") -> NA
A30: Brunei Darussalam | B30: BRN | C30: GDP per capita (constant 2015 US$) | D30: 35515.843 | E30: 35690.985 | F30: 34377.858 | G30: 33445.121 | H30: 33739.494 | I30: 33985.815 | J30: 34219.311 | K30: 34857.393 | L30: 35202.789 | M30: 34750.574 | N30: 34290.111 | O30: 35213.218 | P30: 34714.54 | Q30: 33526.003 | R30: 32449.83 | S30: 32810.504 | T30: 33577.06 | U30: 33456.265 | V30: 32341.889 | W30: 31155.744 | X30: 30681.434 | Y30: 29601.097 | Z30: 29695.881 | AA30: 29437.865 | AB30: 30313.414 | AC30: 30401.844 | AD30: 29673.166 | AE30: 28954.064 | AH30: =IFERROR(((AE30/D30)^(1/27)-1)*100,"NA") -> -0.75369466
A31: Bulgaria | B31: BGR | C31: GDP per capita (constant 2015 US$) | D31: 4025.6458 | E31: 4257.0951 | F31: 3678.5166 | G31: 3843.4622 | H31: 3540.5561 | I31: 3721.3035 | J31: 3941.2757 | K31: 4264.2717 | L31: 4523.2862 | M31: 4854.2734 | N31: 5236.0864 | O31: 5634.9112 | P31: 6054.2325 | Q31: 6470.5897 | R31: 6294.4334 | S31: 6434.5524 | T31: 6611.3038 | U31: 6699.503 | V31: 6700.536 | W31: 6802.7103 | X31: 7078.8603 | Y31: 7344.4435 | Z31: 7601.4385 | AA31: 7862.8618 | AB31: 8237.9268 | AC31: 7958.8268 | AD31: 8638.7184 | AE31: 9550.9425 | AH31: =IFERROR(((AE31/D31)^(1/27)-1)*100,"NA") -> 3.2515765
A32: Burkina Faso | B32: BFA | C32: GDP per capita (constant 2015 US$) | D32: 355.98794 | E32: 385.2292 | F32: 399.185 | G32: 416.7417 | H32: 434.65839 | I32: 429.84737 | J32: 444.54975 | K32: 449.85393 | L32: 470.12958 | M32: 476.00998 | N32: 501.20725 | O32: 516.17677 | P32: 521.34526 | Q32: 535.58364 | R32: 535.51683 | S32: 563.92678 | T32: 583.67948 | U32: 602.78676 | V32: 618.80458 | W32: 626.62625 | X32: 632.12669 | Y32: 650.41726 | Z32: 671.2518 | AA32: 696.04457 | AB32: 714.646 | AC32: 709.05775 | AD32: 738.41866 | AE32: 732.57032 | AH32: =IFERROR(((AE32/D32)^(1/27)-1)*100,"NA") -> 2.7088643
A33: Burundi | B33: BDI | C33: GDP per capita (constant 2015 US$) | D33: 354.11618 | E33: 325.91192 | F33: 321.08969 | G33: 330.12893 | H33: 319.1358 | I33: 310.00671 | J33: 308.6452 | K33: 313.48641 | L33: 300.08615 | M33: 303.11967 | N33: 294.73877 | O33: 299.76912 | P33: 298.93666 | Q33: 300.84135 | R33: 296.84709 | S33: 297.79173 | T33: 299.01718 | U33: 301.48132 | V33: 305.29084 | W33: 307.76553 | X33: 289.35963 | Y33: 282.97597 | Z33: 277.9598 | AA33: 274.13191 | AB33: 270.13728 | AC33: 263.36099 | AD33: 264.36483 | AE33: 262.1848 | AH33: =IFERROR(((AE33/D33)^(1/27)-1)*100,"NA") -> -1.1070687
A34: Cabo Verde | B34: CPV | C34: GDP per capita (constant 2015 US$) | D34: 1268.678 | E34: 1380.3336 | F34: 1499.4465 | G34: 1650.4974 | H34: 1797.2957 | I34: 2015.3814 | J34: 2026.2792 | K34: 2099.9002 | L34: 2156.3479 | M34: 2344.5188 | N34: 2474.8249 | O34: 2639.9627 | P34: 3005.2294 | Q34: 3181.4508 | R34: 3101.3938 | S34: 3124.5721 | T34: 3208.3671 | U34: 3204.6019 | V34: 3188.5697 | W34: 3174.7053 | X34: 3169.0789 | Y34: 3267.879 | Z34: 3376.9383 | AA34: 3463.8128 | AB34: 3667.0574 | AC34: 2876.1534 | AD34: 3010.3456 | AE34: 3494.5692 | AH34: =IFERROR(((AE34/D34)^(1/27)-1)*100,"NA") -> 3.8240248
A35: Cambodia | B35: KHM | C35: GDP per capita (constant 2015 US$) | D35: 378.92238 | E35: 391.82902 | F35: 398.65296 | G35: 408.82253 | H35: 451.86145 | I35: 488.0027 | J35: 518.38429 | K35: 542.65474 | L35: 578.40936 | M35: 627.00821 | N35: 697.74676 | O35: 759.64339 | P35: 822.75409 | Q35: 863.38697 | R35: 851.20302 | S35: 888.91259 | T35: 938.01768 | U35: 992.1346 | V35: 1049.9945 | W35: 1109.3757 | X35: 1170.7428 | Y35: 1235.3234 | Z35: 1304.5494 | AA35: 1384.968 | AB35: 1465.9695 | AC35: 1404.1987 | AD35: 1429.937 | AE35: 1488.8146 | AH35: =IFERROR(((AE35/D35)^(1/27)-1)*100,"NA") -> 5.1987922
A36: Cameroon | B36: CMR | C36: GDP per capita (constant 2015 US$) | D36: 1049.7067 | E36: 1064.646 | F36: 1083.6416 | G36: 1105.2452 | H36: 1124.9005 | I36: 1137.6245 | J36: 1156.0504 | K36: 1175.8717 | L36: 1206.6105 | M36: 1256.6936 | N36: 1250.0589 | O36: 1262.8719 | P36: 1281.3925 | Q36: 1281.0198 | R36: 1277.1816 | S36: 1277.2657 | T36: 1283.567 | U36: 1305.668 | V36: 1332.86 | W36: 1366.9666 | X36: 1399.6753 | Y36: 1420.0299 | Z36: 1429.2347 | AA36: 1445.2678 | AB36: 1454.5641 | AC36: 1419.3282 | AD36: 1428.5626 | AE36: 1441.7949 | AH36: =IFERROR(((AE36/D36)^(1/27)-1)*100,"NA") -> 1.1824101
A37: Canada | B37: CAN | C37: GDP per capita (constant 2015 US$) | D37: 32612.232 | E37: 32795.665 | F37: 33861.147 | G37: 34889.671 | H37: 36393.964 | I37: 37923.486 | J37: 38185.22 | K37: 38912.21 | L37: 39257.762 | M37: 40093.807 | N37: 40989.527 | O37: 41646.415 | P37: 42098.431 | Q37: 42063.24 | R37: 40368.932 | S37: 41156.145 | T37: 42037.519 | U37: 42315.807 | V37: 42846.284 | W37: 43635.095 | X37: 43596.136 | Y37: 43536.913 | Z37: 44325.488 | AA37: 44917.484 | AB37: 45113.066 | AC37: 42366.487 | AD37: 44234.542 | AE37: 44928.589 | AH37: =IFERROR(((AE37/D37)^(1/27)-1)*100,"NA") -> 1.1936863
A38: Cayman Islands | B38: CYM | C38: GDP per capita (constant 2015 US$) | D38: .. | E38: .. | F38: .. | G38: .. | H38: .. | I38: .. | J38: .. | K38: .. | L38: .. | M38: .. | N38: .. | O38: 96176.301 | P38: 96280.247 | Q38: 93166.316 | R38: 84026.972 | S38: 79519.845 | T38: 78393.737 | U38: 77448.51 | V38: 76617.544 | W38: 76872.581 | X38: 77295.845 | Y38: 78077.434 | Z38: 78883.281 | AA38: 80597.709 | AB38: 82170.593 | AC38: 76609.769 | AD38: 78731.148 | AE38: 80946.966 | AH38: =IFERROR(((AE38/D38)^(1/27)-1)*100,"NA") -> NA
A39: Central African Republic | B39: CAF | C39: GDP per capita (constant 2015 US$) | D39: 478.34389 | E39: 447.35063 | F39: 458.13384 | G39: 466.63411 | H39: 470.16836 | I39: 445.80329 | J39: 455.33838 | K39: 461.49809 | L39: 426.15958 | M39: 442.01524 | N39: 436.10027 | O39: 447.80811 | P39: 459.74607 | Q39: 459.56246 | R39: 488.38803 | S39: 500.52928 | T39: 513.59427 | U39: 534.88356 | V39: 338.16571 | W39: 338.70038 | X39: 351.87975 | Y39: 362.21833 | Z39: 371.60313 | AA39: 378.26308 | AB39: 381.41405 | AC39: 375.21692 | AD39: 370.98037 | AE39: 364.69075 | AH39: =IFERROR(((AE39/D39)^(1/27)-1)*100,"NA") -> -0.99971073
A40: Chad | B40: TCD | C40: GDP per capita (constant 2015 US$) | D40: 399.99949 | E40: 391.17302 | F40: 399.38814 | G40: 412.84313 | H40: 396.01183 | I40: 379.35155 | J40: 409.70367 | K40: 429.42697 | L40: 473.46802 | M40: 605.23935 | N40: 682.35387 | O40: 662.88551 | P40: 661.77236 | Q40: 658.87446 | R40: 662.92325 | S40: 727.52495 | T40: 703.12322 | U40: 739.33836 | V40: 754.17181 | W40: 777.93568 | X40: 774.4116 | Y40: 703.46601 | Z40: 660.12613 | AA40: 653.34976 | AB40: 652.70322 | AC40: 622.27851 | AD40: 595.66379 | AE40: 590.30518 | AH40: =IFERROR(((AE40/D40)^(1/27)-1)*100,"NA") -> 1.4518322
A41: Channel Islands | B41: CHI | C41: GDP per capita (constant 2015 US$) | D41: .. | E41: .. | F41: .. | G41: .. | H41: .. | I41: .. | J41: .. | K41: .. | L41: .. | M41: .. | N41: .. | O41: .. | P41: .. | Q41: .. | R41: .. | S41: .. | T41: .. | U41: .. | V41: .. | W41: .. | X41: .. | Y41: .. | Z41: .. | AA41: .. | AB41: .. | AC41: .. | AD41: .. | AE41: .. | AH41: =IFERROR(((AE41/D41)^(1/27)-1)*100,"NA") -> NA
A42: Chile | B42: CHL | C42: GDP per capita (constant 2015 US$) | D42: 7277.5619 | E42: 7666.9848 | F42: 8125.9555 | G42: 8359.8749 | H42: 8238.301 | I42: 8549.0791 | J42: 8720.9101 | K42: 8902.838 | L42: 9226.1505 | M42: 9744.3224 | N42: 10212.782 | O42: 10725.055 | P42: 11169.287 | Q42: 11477.09 | R42: 11232.823 | S42: 11770.757 | T42: 12380.015 | U42: 13014.582 | V42: 13316.052 | W42: 13418.976 | X42: 13567.357 | Y42: 13642.018 | Z42: 13612.924 | AA42: 13904.115 | AB42: 13758.747 | AC42: 12738.725 | AD42: 14093.091 | AE42: 14355.606 | AH42: =IFERROR(((AE42/D42)^(1/27)-1)*100,"NA") -> 2.548012
A43: China | B43: CHN | C43: GDP per capita (constant 2015 US$) | D43: 1520.0295 | E43: 1653.4338 | F43: 1787.767 | G43: 1909.6223 | H43: 2038.2065 | I43: 2193.8969 | J43: 2359.5724 | K43: 2557.8916 | L43: 2797.1767 | M43: 3061.8332 | N43: 3390.7162 | O43: 3800.7658 | P43: 4319.0314 | Q43: 4711.6434 | R43: 5128.9041 | S43: 5647.0687 | T43: 6152.6969 | U43: 6591.6625 | V43: 7056.4231 | W43: 7532.7853 | X43: 8016.4456 | Y43: 8516.5287 | Z43: 9053.2287 | AA43: 9619.2095 | AB43: 10155.511 | AC43: 10358.17 | AD43: 11223.255 | AE43: 11560.242 | AH43: =IFERROR(((AE43/D43)^(1/27)-1)*100,"NA") -> 7.8037544
A44: Colombia | B44: COL | C44: GDP per capita (constant 2015 US$) | D44: 4170.4577 | E44: 4179.2262 | F44: 4246.1567 | G44: 4196.9203 | H44: 3953.73 | I44: 4003.9852 | J44: 4007.528 | K44: 4045.3067 | L44: 4142.0077 | M44: 4301.035 | N44: 4447.5668 | O44: 4685.0546 | P44: 4939.118 | Q44: 5042.0611 | R44: 5042.145 | S44: 5209.7325 | T44: 5511.0999 | U44: 5667.4988 | V44: 5899.7679 | W44: 6107.083 | X44: 6228.6516 | Y44: 6291.0797 | Z44: 6280.8911 | AA44: 6320.9907 | AB44: 6404.1088 | AC44: 5852.9832 | AD44: 6423.8599 | AE44: 6842.5325 | AH44: =IFERROR(((AE44/D44)^(1/27)-1)*100,"NA") -> 1.8507405
A45: Comoros | B45: COM | C45: GDP per capita (constant 2015 US$) | D45: 1135.1349 | E45: 1096.6072 | F45: 1116.5306 | G45: 1106.9033 | H45: 1105.7367 | I45: 1202.1314 | J45: 1205.5092 | K45: 1208.5899 | L45: 1210.0285 | M45: 1209.8631 | N45: 1219.9912 | O45: 1227.4829 | P45: 1212.7517 | Q45: 1235.6528 | R45: 1249.8394 | S45: 1270.3027 | T45: 1295.2044 | U45: 1307.973 | V45: 1337.3977 | W45: 1336.4897 | X45: 1322.9368 | Y45: 1337.5279 | Z45: 1360.4312 | AA45: 1383.3779 | AB45: 1381.6222 | AC45: 1352.9555 | AD45: 1355.5388 | AE45: 1362.778 | AH45: =IFERROR(((AE45/D45)^(1/27)-1)*100,"NA") -> 0.67923634
A46: Congo, Dem. Rep. | B46: COD | C46: GDP per capita (constant 2015 US$) | D46: 466.24576 | E46: 452.76306 | F46: 420.62414 | G46: 404.11548 | H46: 375.95052 | I46: 339.96945 | J46: 322.93004 | K46: 322.44005 | L46: 330.54899 | M46: 342.46 | N46: 352.32123 | O46: 359.42807 | P46: 369.84075 | Q46: 380.49491 | R46: 379.05488 | S46: 393.02745 | T46: 406.20103 | U46: 420.62937 | V46: 441.01298 | W46: 466.42495 | X46: 482.06457 | Y46: 476.8149 | Z46: 477.84789 | AA46: 489.38237 | AB46: 494.81925 | AC46: 487.43313 | AD46: 501.23909 | AE46: 528.78883 | AH46: =IFERROR(((AE46/D46)^(1/27)-1)*100,"NA") -> 0.46729697
A47: Congo, Rep. | B47: COG | C47: GDP per capita (constant 2015 US$) | D47: 2098.0068 | E47: 2130.3136 | F47: 2073.97 | G47: 2105.976 | H47: 1997.5332 | I47: 2068.3899 | J47: 2067.8201 | K47: 2112.5401 | L47: 2071.578 | M47: 2071.9894 | N47: 2153.7672 | O47: 2240.09 | P47: 2016.3153 | Q47: 2073.6197 | R47: 2223.7826 | S47: 2345.1181 | T47: 2320.3401 | U47: 2481.3018 | V47: 2405.0404 | W47: 2504.2998 | X47: 2455.3479 | Y47: 2189.169 | Z47: 2017.8598 | AA47: 1924.7243 | AB47: 1901.0615 | AC47: 1740.8323 | AD47: 1718.2357 | AE47: 1704.2724 | AH47: =IFERROR(((AE47/D47)^(1/27)-1)*100,"NA") -> -0.76685751
A48: Costa Rica | B48: CRI | C48: GDP per capita (constant 2015 US$) | D48: 6867.6377 | E48: 6801.6554 | F48: 7014.5301 | G48: 7355.1536 | H48: 7507.9654 | I48: 7646.0274 | J48: 7768.439 | K48: 7898.6331 | L48: 8109.8249 | M48: 8340.8299 | N48: 8545.7473 | O48: 9041.3868 | P48: 9647.8609 | Q48: 9966.0484 | R48: 9746.4907 | S48: 10137.582 | T48: 10453.523 | U48: 10832.757 | V48: 10975.696 | W48: 11240.712 | X48: 11529.955 | Y48: 11893.323 | Z48: 12267.162 | AA48: 12470.957 | AB48: 12662.423 | AC48: 12030.049 | AD48: 12906.997 | AE48: 13424.465 | AH48: =IFERROR(((AE48/D48)^(1/27)-1)*100,"NA") -> 2.5135083
A49: Cote d'Ivoire | B49: CIV | C49: GDP per capita (constant 2015 US$) | D49: 1711.1109 | E49: 1779.7421 | F49: 1884.722 | G49: 1900.2134 | H49: 1865.1231 | I49: 1809.9208 | J49: 1725.1559 | K49: 1636.447 | L49: 1521.8848 | M49: 1534.0767 | N49: 1514.6206 | O49: 1523.2331 | P49: 1507.0896 | Q49: 1545.8801 | R49: 1568.0211 | S49: 1640.315 | T49: 1520.3423 | U49: 1602.9109 | V49: 1739.1552 | W49: 1858.6154 | X49: 1941.5819 | Y49: 2027.834 | Z49: 2122.5026 | AA49: 2168.9134 | AB49: 2252.5433 | AC49: 2234.9095 | AD49: 2333.3531 | AE49: 2430.3069 | AH49: =IFERROR(((AE49/D49)^(1/27)-1)*100,"NA") -> 1.3080167
A50: Croatia | B50: HRV | C50: GDP per capita (constant 2015 US$) | D50: 7305.9398 | E50: 7854.7451 | F50: 8380.1159 | G50: 8573.6804 | H50: 8537.1039 | I50: 8876.6157 | J50: 9512.7084 | K50: 10060.479 | L50: 10620.804 | M50: 11061.661 | N50: 11523.298 | O50: 12105.469 | P50: 12722.604 | Q50: 12980.08 | R50: 12055.846 | S50: 11933.019 | T50: 11964.358 | U50: 11720.172 | V50: 11706.225 | W50: 11703.979 | X50: 12098.512 | Y50: 12617.306 | Z50: 13203.819 | AA50: 13698.055 | AB50: 14242.456 | AC50: 13075.347 | AD50: 15524.743 | AE50: 16610.318 | AH50: =IFERROR(((AE50/D50)^(1/27)-1)*100,"NA") -> 3.0887278
A51: Cuba | B51: CUB | C51: GDP per capita (constant 2015 US$) | D51: 3348.4766 | E51: 3598.9898 | F51: 3687.3599 | G51: 3681.3025 | H51: 3896.2981 | I51: 4113.4903 | J51: 4231.8037 | K51: 4280.2167 | L51: 4430.9845 | M51: 4675.7888 | N51: 5189.9286 | O51: 5808.6407 | P51: 6225.3545 | Q51: 6477.7779 | R51: 6567.9602 | S51: 6720.6499 | T51: 6903.9117 | U51: 7105.4043 | V51: 7292.7081 | W51: 7362.3113 | X51: 7683.7403 | Y51: 7721.7036 | Z51: 7865.3386 | AA51: 8047.941 | AB51: 8043.0142 | AC51: 7172.5179 | AD51: 7291.0378 | AE51: 7449.6829 | AH51: =IFERROR(((AE51/D51)^(1/27)-1)*100,"NA") -> 3.0060211
A52: Curacao | B52: CUW | C52: GDP per capita (constant 2015 US$) | D52: .. | E52: .. | F52: .. | G52: .. | H52: .. | I52: 21523.646 | J52: 22171.065 | K52: 22231.879 | L52: 21840.891 | M52: 21512.112 | N52: 21112.322 | O52: 20913.663 | P52: 21011.157 | Q52: 21202.43 | R52: 20952.9 | S52: 20706.437 | T52: 20518.099 | U52: 20277.511 | V52: 19921.477 | W52: 19529.529 | X52: 19361.813 | Y52: 18953.054 | Z52: 18651.48 | AA52: 18355.177 | AB52: 17980.53 | AC52: 14974.325 | AD52: 15864.765 | AE52: 17387.285 | AH52: =IFERROR(((AE52/D52)^(1/27)-1)*100,"NA") -> NA
A53: Cyprus | B53: CYP | C53: GDP per capita (constant 2015 US$) | D53: 19452.574 | E53: 19384.025 | F53: 19615.902 | G53: 20560.945 | H53: 21348.348 | I53: 22382.496 | J53: 23017.74 | K53: 23602.635 | L53: 23929.205 | M53: 24798.029 | N53: 25629.697 | O53: 26393.795 | P53: 27155.021 | Q53: 27447.363 | R53: 26181.859 | S53: 26019.879 | T53: 25466.221 | U53: 24216.637 | V53: 22682.367 | W53: 22513.879 | X53: 23408.441 | Y53: 24805.312 | Z53: 26013.949 | AA53: 27161.523 | AB53: 28360.359 | AC53: 27089.883 | AD53: 29498.709 | AE53: 30571.551 | AH53: =IFERROR(((AE53/D53)^(1/27)-1)*100,"NA") -> 1.6885059
A54: Czechia | B54: CZE | C54: GDP per capita (constant 2015 US$) | D54: 11219.15 | E54: 11711.315 | F54: 11663.174 | G54: 11632.603 | H54: 11805.672 | I54: 12312.498 | J54: 12734.922 | K54: 12959.817 | L54: 13428.1 | M54: 14070.28 | N54: 14978.413 | O54: 15948.745 | P54: 16739.179 | Q54: 17046.885 | R54: 16160.621 | S54: 16505.954 | T54: 16761.827 | U54: 16606.993 | V54: 16593.864 | W54: 16951.379 | X54: 17829.698 | Y54: 18247.012 | Z54: 19139.24 | AA54: 19689.583 | AB54: 20206.426 | AC54: 19048.087 | AD54: 20085.516 | AE54: 20237.443 | AH54: =IFERROR(((AE54/D54)^(1/27)-1)*100,"NA") -> 2.2089035
A55: Denmark | B55: DNK | C55: GDP per capita (constant 2015 US$) | D55: 43310.25 | E55: 44314.79 | F55: 45570.08 | G55: 46412.039 | H55: 47622.439 | I55: 49241.928 | J55: 49469.689 | K55: 49541.856 | L55: 49599.997 | M55: 50792.001 | N55: 51835.833 | O55: 53687.442 | P55: 53935.87 | Q55: 53345.358 | R55: 50457.232 | S55: 51173.466 | T55: 51644.464 | U55: 51567.04 | V55: 51831.798 | W55: 52404.764 | X55: 53254.856 | Y55: 54556.069 | Z55: 55735.765 | AA55: 56563.488 | AB55: 57203.028 | AC55: 55653.587 | AD55: 59205.647 | AE55: 60345.557 | AH55: =IFERROR(((AE55/D55)^(1/27)-1)*100,"NA") -> 1.2360883
A56: Djibouti | B56: DJI | C56: GDP per capita (constant 2015 US$) | D56: .. | E56: .. | F56: .. | G56: .. | H56: .. | I56: .. | J56: .. | K56: .. | L56: .. | M56: .. | N56: .. | O56: .. | P56: .. | Q56: .. | R56: .. | S56: .. | T56: .. | U56: .. | V56: 2167.2025 | W56: 2279.5776 | X56: 2409.3119 | Y56: 2538.054 | Z56: 2632.9133 | AA56: 2714.3516 | AB56: 2820.0629 | AC56: 2814.8262 | AD56: 2901.1371 | AE56: 2950.9465 | AH56: =IFERROR(((AE56/D56)^(1/27)-1)*100,"NA") -> NA
A57: Dominica | B57: DMA | C57: GDP per capita (constant 2015 US$) | D57: 5498.5212 | E57: 5672.0752 | F57: 5803.1773 | G57: 6034.6944 | H57: 6077.2192 | I57: 6251.4712 | J57: 6265.172 | K57: 6078.2717 | L57: 6447.4314 | M57: 6631.3331 | N57: 6665.106 | O57: 6968.7632 | P57: 7407.9306 | Q57: 7934.6461 | R57: 7841.2732 | S57: 7897.6903 | T57: 7881.5252 | U57: 7781.5328 | V57: 7711.446 | W57: 8013.7531 | X57: 7724.0424 | Y57: 7929.8053 | Z57: 7370.4331 | AA57: 7586.6461 | AB57: 7936.3048 | AC57: 6566.4274 | AD57: 6978.4705 | AE57: 7339.6951 | AH57: =IFERROR(((AE57/D57)^(1/27)-1)*100,"NA") -> 1.0754385
A58: Dominican Republic | B58: DOM | C58: GDP per capita (constant 2015 US$) | D58: 3318.6051 | E58: 3454.4087 | F58: 3697.7637 | G58: 3883.1335 | H58: 4050.5815 | I58: 4175.171 | J58: 4214.5738 | K58: 4340.8999 | L58: 4222.5903 | M58: 4272.0752 | N58: 4612.8087 | O58: 4971.2382 | P58: 5272.8641 | Q58: 5373.0963 | R58: 5353.5982 | S58: 5724.3073 | T58: 5827.3833 | U58: 5909.8634 | V58: 6120.9912 | W58: 6472.8491 | X58: 6838.9367 | Y58: 7209.9902 | Z58: 7461.6533 | AA58: 7894.9552 | AB58: 8205.1426 | AC58: 7571.7828 | AD58: 8410.6058 | AE58: 8732.0807 | AH58: =IFERROR(((AE58/D58)^(1/27)-1)*100,"NA") -> 3.6481517
A59: Ecuador | B59: ECU | C59: GDP per capita (constant 2015 US$) | D59: 4374.2687 | E59: 4369.321 | F59: 4477.5709 | G59: 4543.5365 | H59: 4254.1512 | I59: 4227.5525 | J59: 4322.3419 | K59: 4421.9344 | L59: 4463.5972 | M59: 4746.8072 | N59: 4912.5275 | O59: 5041.3338 | P59: 5063.9845 | Q59: 5294.8993 | R59: 5236.0537 | S59: 5331.3838 | T59: 5657.213 | U59: 5881.3812 | V59: 6078.4396 | W59: 6215.8381 | X59: 6130.5867 | Y59: 5965.6433 | Z59: 6012.8033 | AA59: 5976.2453 | AB59: 5863.9106 | AC59: 5331.9766 | AD59: 5492.4893 | AE59: 5590.5416 | AH59: =IFERROR(((AE59/D59)^(1/27)-1)*100,"NA") -> 0.91279569
A60: Egypt, Arab Rep. | B60: EGY | C60: GDP per capita (constant 2015 US$) | D60: 2122.8805 | E60: 2181.2528 | F60: 2251.9886 | G60: 2327.1015 | H60: 2416.3623 | I60: 2517.5805 | J60: 2553.5284 | K60: 2560.4574 | L60: 2587.6305 | M60: 2639.3471 | N60: 2703.2226 | O60: 2832.5482 | P60: 2974.6879 | Q60: 3125.7475 | R60: 3208.4523 | S60: 3305.8832 | T60: 3290.7618 | U60: 3288.7944 | V60: 3283.7407 | W60: 3301.2044 | X60: 3370.3824 | Y60: 3444.2683 | Z60: 3517.5879 | AA60: 3635.4206 | AB60: 3769.0358 | AC60: 3835.7842 | AD60: 3896.8429 | AE60: 4088.897 | AH60: =IFERROR(((AE60/D60)^(1/27)-1)*100,"NA") -> 2.4574934
A61: El Salvador | B61: SLV | C61: GDP per capita (constant 2015 US$) | D61: 2780.049 | E61: 2778.9457 | F61: 2843.8288 | G61: 2898.2005 | H61: 2941.4831 | I61: 2957.3719 | J61: 2968.6315 | K61: 3003.6983 | L61: 3042.8347 | M61: 3065.4188 | N61: 3146.4704 | O61: 3284.7721 | P61: 3340.0954 | Q61: 3398.5775 | R61: 3314.2985 | S61: 3373.0438 | T61: 3487.0312 | U61: 3573.7859 | V61: 3637.4227 | W61: 3686.0956 | X61: 3761.5137 | Y61: 3845.0225 | Z61: 3922.7769 | AA61: 4011.54 | AB61: 4103.8245 | AC61: 3775.5761 | AD61: 4183.2593 | AE61: 4276.9552 | AH61: =IFERROR(((AE61/D61)^(1/27)-1)*100,"NA") -> 1.6082502
A62: Equatorial Guinea | B62: GNQ | C62: GDP per capita (constant 2015 US$) | D62: 628.88025 | E62: 1008.3284 | F62: 2424.8285 | G62: 2886.1531 | H62: 3486.799 | I62: 3941.6635 | J62: 6132.8473 | K62: 6987.9427 | L62: 7604.4807 | M62: 10028.354 | N62: 11188.449 | O62: 11508.926 | P62: 12660.906 | Q62: 14222.549 | R62: 13740.84 | S62: 11933.311 | T62: 12155.819 | U62: 12625.296 | V62: 11614.003 | W62: 11200.811 | X62: 9788.9838 | Y62: 8594.4502 | Z62: 7818.0536 | AA62: 7079.6505 | AB62: 6472.0709 | AC62: 5995.9058 | AD62: 5870.4014 | AE62: 5945.2017 | AH62: =IFERROR(((AE62/D62)^(1/27)-1)*100,"NA") -> 8.6759093
A63: Eritrea | B63: ERI | C63: GDP per capita (constant 2015 US$) | D63: 757.35852 | E63: 788.42813 | F63: 840.57702 | G63: 843.98884 | H63: 832.02249 | I63: 793.62056 | J63: 838.89891 | K63: 835.11 | L63: 780.46814 | M63: 760.34879 | N63: 761.03178 | O63: 741.00074 | P63: 739.73934 | Q63: 649.69446 | R63: 657.78646 | S63: 658.58627 | T63: 702.39663 | U63: .. | V63: .. | W63: .. | X63: .. | Y63: .. | Z63: .. | AA63: .. | AB63: .. | AC63: .. | AD63: .. | AE63: .. | AH63: =IFERROR(((AE63/D63)^(1/27)-1)*100,"NA") -> NA
A64: Estonia | B64: EST | C64: GDP per capita (constant 2015 US$) | D64: 7137.5308 | E64: 7601.669 | F64: 8692.2964 | G64: 9157.0648 | H64: 9091.3332 | I64: 9960.139 | J64: 10625.579 | K64: 11417.168 | L64: 12362.248 | M64: 13282.546 | N64: 14631.387 | O64: 16155.207 | P64: 17459.098 | Q64: 16607.568 | R64: 14205.395 | S64: 14585.839 | T64: 15692.789 | U64: 16257.472 | V64: 16553.383 | W64: 17096.645 | X64: 17402.038 | Y64: 17945.945 | Z64: 18962.41 | AA64: 19611.611 | AB64: 20269.575 | AC64: 20118.105 | AD64: 21707.241 | AE64: 21143.291 | AH64: =IFERROR(((AE64/D64)^(1/27)-1)*100,"NA") -> 4.1040386
A65: Eswatini | B65: SWZ | C65: GDP per capita (constant 2015 US$) | D65: 2264.4025 | E65: 2303.0643 | F65: 2333.4272 | G65: 2359.8339 | H65: 2397.9505 | I65: 2411.4449 | J65: 2411.3739 | K65: 2494.4475 | L65: 2571.6881 | M65: 2647.4632 | N65: 2790.2508 | O65: 2941.3968 | P65: 3054.0824 | Q65: 3062.615 | R65: 3096.2961 | S65: 3199.0535 | T65: 3254.8134 | U65: 3411.7194 | V65: 3521.6693 | W65: 3530.3609 | X65: 3583.3113 | Y65: 3594.1671 | Z65: 3638.7688 | AA65: 3696.3599 | AB65: 3766.063 | AC65: 3672.6533 | AD65: 4025.4109 | AE65: 4012.9545 | AH65: =IFERROR(((AE65/D65)^(1/27)-1)*100,"NA") -> 2.1419387
A66: Ethiopia | B66: ETH | C66: GDP per capita (constant 2015 US$) | D66: 241.78179 | E66: 263.25588 | F66: 263.1444 | G66: 246.38728 | H66: 251.37772 | I66: 258.87053 | J66: 272.28855 | K66: 268.4236 | L66: 255.10027 | M66: 281.52033 | N66: 305.97935 | O66: 329.67928 | P66: 357.11793 | Q66: 384.57266 | R66: 406.85693 | S66: 445.18234 | T66: 481.03786 | U66: 508.06571 | V66: 546.59284 | W66: 586.57361 | X66: 630.31262 | Y66: 671.29058 | Z66: 715.74873 | AA66: 744.36752 | AB66: 785.48497 | AC66: 811.25554 | AD66: 834.99129 | AE66: 857.31549 | AH66: =IFERROR(((AE66/D66)^(1/27)-1)*100,"NA") -> 4.7996644
A67: Faroe Islands | B67: FRO | C67: GDP per capita (constant 2015 US$) | D67: .. | E67: .. | F67: .. | G67: .. | H67: .. | I67: .. | J67: .. | K67: .. | L67: .. | M67: .. | N67: .. | O67: .. | P67: .. | Q67: 44678.67 | R67: 42740.254 | S67: 42510.347 | T67: 44108.58 | U67: 47197.674 | V67: 49933.35 | W67: 52595.025 | X67: 52726.687 | Y67: 52762.429 | Z67: 53822.91 | AA67: 54506.387 | AB67: 56099.969 | AC67: 54248.55 | AD67: 56856.685 | AE67: 59699.201 | AH67: =IFERROR(((AE67/D67)^(1/27)-1)*100,"NA") -> NA
A68: Fiji | B68: FJI | C68: GDP per capita (constant 2015 US$) | D68: 3786.0786 | E68: 3946.4305 | F68: 3821.0692 | G68: 3826.1601 | H68: 4114.9607 | I68: 4000.8544 | J68: 4038.1332 | K68: 4125.3264 | L68: 4125.7297 | M68: 4302.3476 | N68: 4291.7155 | O68: 4330.8272 | P68: 4257.5145 | Q68: 4272.3066 | R68: 4191.3473 | S68: 4297.139 | T68: 4397.903 | U68: 4446.7342 | V68: 4645.0465 | W68: 4894.0436 | X68: 5105.1896 | Y68: 5223.376 | Z68: 5499.1223 | AA68: 5708.911 | AB68: 5679.0519 | AC68: 4701.3315 | AD68: 4451.6026 | AE68: 5313.0285 | AH68: =IFERROR(((AE68/D68)^(1/27)-1)*100,"NA") -> 1.2628377
A69: Finland | B69: FIN | C69: GDP per capita (constant 2015 US$) | D69: 29912.898 | E69: 30908.3 | F69: 32768.378 | G69: 34464.991 | H69: 35891.006 | I69: 37884.391 | J69: 38784.773 | K69: 39351.39 | L69: 40044.305 | M69: 41522.175 | N69: 42530.62 | O69: 44074.031 | P69: 46212.641 | Q69: 46358.62 | R69: 42412.098 | S69: 43563.572 | T69: 44466.818 | U69: 43637.249 | V69: 43044.997 | W69: 42710.921 | X69: 42801.908 | Y69: 43878.967 | Z69: 45173.629 | AA69: 45627.92 | AB69: 46135.881 | AC69: 44984.734 | AD69: 46315.063 | AE69: 46929.144 | AH69: =IFERROR(((AE69/D69)^(1/27)-1)*100,"NA") -> 1.6819478
A70: France | B70: FRA | C70: GDP per capita (constant 2015 US$) | D70: 29745.129 | E70: 30057.966 | F70: 30650.744 | G70: 31633.148 | H70: 32546.934 | I70: 33592.467 | J70: 34009.862 | K70: 34146.306 | L70: 34183.663 | M70: 34893.53 | N70: 35208.856 | O70: 35821.872 | P70: 36464.959 | Q70: 36354.659 | R70: 35129.362 | S70: 35638.122 | T70: 36244.187 | U70: 36182.151 | V70: 36203.191 | W70: 36378.619 | X70: 36652.922 | Y70: 36956.796 | Z70: 37694.083 | AA70: 38259.698 | AB70: 38832.024 | AC70: 35806.618 | AD70: 38002.194 | AE70: 38816.479 | AH70: =IFERROR(((AE70/D70)^(1/27)-1)*100,"NA") -> 0.99072552
A71: French Polynesia | B71: PYF | C71: GDP per capita (constant 2015 US$) | D71: 22034.328 | E71: 21538.691 | F71: 21166.025 | G71: 21191.941 | H71: 21247.987 | I71: 21578.6 | J71: 21157.335 | K71: 20999.774 | L71: 21117.523 | M71: 21006.62 | N71: 20766.379 | O71: 20658.378 | P71: 20763.089 | Q71: 20588.347 | R71: 19596.683 | S71: 19012.053 | T71: 18353.402 | U71: 18099.48 | V71: 18080.308 | W71: 18072.114 | X71: 18252.514 | Y71: 18573.385 | Z71: 19260.62 | AA71: 19471.39 | AB71: 19856.259 | AC71: 18321.528 | AD71: 18575.386 | AE71: 19262.613 | AH71: =IFERROR(((AE71/D71)^(1/27)-1)*100,"NA") -> -0.49667181
A72: Gabon | B72: GAB | C72: GDP per capita (constant 2015 US$) | D72: 8524.4192 | E72: 8613.5806 | F72: 8882.4029 | G72: 8963.205 | H72: 7959.0648 | I72: 7611.8357 | J72: 7574.1149 | K72: 7357.5667 | L72: 7322.6061 | M72: 7171.6835 | N72: 7155.3655 | O72: 6750.0508 | P72: 6937.4851 | Q72: 6497.4812 | R72: 6295.1991 | S72: 6514.7312 | T72: 6735.0829 | U72: 6840.9486 | V72: 6977.7703 | W72: 7039.6821 | X72: 7090.4546 | Y72: 7038.5773 | Z72: 6893.3843 | AA72: 6786.8903 | AB72: 6893.3231 | AC72: 6619.6886 | AD72: 6581.2274 | AE72: 6637.0661 | AH72: =IFERROR(((AE72/D72)^(1/27)-1)*100,"NA") -> -0.92262439
A73: Gambia, The | B73: GMB | C73: GDP per capita (constant 2015 US$) | D73: 620.49308 | E73: 615.9839 | F73: 627.55635 | G73: 630.75295 | H73: 651.74919 | I73: 667.96538 | J73: 686.68769 | K73: 645.70173 | L73: 670.66094 | M73: 697.47245 | N73: 661.32191 | O73: 638.07695 | P73: 637.531 | Q73: 656.70391 | R73: 679.00361 | S73: 697.16257 | T73: 620.94822 | U73: 633.58272 | V73: 632.19715 | W73: 605.03369 | X73: 611.67122 | Y73: 606.3162 | Z73: 618.48077 | AA73: 645.93819 | AB73: 668.63512 | AC73: 655.57612 | AD73: 666.47109 | AE73: 678.36172 | AH73: =IFERROR(((AE73/D73)^(1/27)-1)*100,"NA") -> 0.33079111
A74: Georgia | B74: GEO | C74: GDP per capita (constant 2015 US$) | D74: 1033.0041 | E74: 1191.159 | F74: 1359.3676 | G74: 1436.6853 | H74: 1508.6286 | I74: 1566.5313 | J74: 1667.4771 | K74: 1774.6036 | L74: 1984.2076 | M74: 2112.2222 | N74: 2329.5277 | O74: 2563.4956 | P74: 2901.0504 | Q74: 2980.2544 | R74: 2897.0773 | S74: 3100.1647 | T74: 3355.1636 | U74: 3596.8528 | V74: 3738.1328 | W74: 3902.3311 | X74: 4014.1117 | Y74: 4128.3092 | Z74: 4327.6475 | AA74: 4539.0035 | AB74: 4773.335 | AC74: 4447.5819 | AD74: 4931.7324 | AE74: 5438.6042 | AH74: =IFERROR(((AE74/D74)^(1/27)-1)*100,"NA") -> 6.3452211
A75: Germany | B75: DEU | C75: GDP per capita (constant 2015 US$) | D75: 31628.16 | E75: 31790.867 | F75: 32313.297 | G75: 32959.074 | H75: 33559.399 | I75: 34490.076 | J75: 35011.068 | K75: 34883.058 | L75: 34619.664 | M75: 35034.081 | N75: 35310.47 | O75: 36699.447 | P75: 37842.358 | Q75: 38278.313 | R75: 36190.393 | S75: 37760.914 | T75: 39977.342 | U75: 40069.354 | V75: 40135.016 | W75: 40851.162 | X75: 41103.256 | Y75: 41682.032 | Z75: 42639.554 | AA75: 42928.741 | AB75: 43292.684 | AC75: 41601.973 | AD75: 42900.023 | AE75: 43361.177 | AH75: =IFERROR(((AE75/D75)^(1/27)-1)*100,"NA") -> 1.1754347
A76: Ghana | B76: GHA | C76: GDP per capita (constant 2015 US$) | D76: 931.18043 | E76: 951.9228 | F76: 968.84604 | G76: 990.17503 | H76: 1008.8337 | I76: 1020.1622 | J76: 1033.1214 | K76: 1050.344 | L76: 1075.3719 | M76: 1105.6856 | N76: 1140.1864 | O76: 1181.559 | P76: 1201.2108 | Q76: 1277.823 | R76: 1306.1851 | S76: 1374.985 | T76: 1530.3593 | U76: 1631.9194 | V76: 1708.828 | W76: 1715.824 | X76: 1711.2713 | Y76: 1728.0971 | Z76: 1827.2739 | AA76: 1899.8084 | AB76: 1981.6138 | AC76: 1951.0645 | AD76: 2009.3591 | AE76: 2031.4283 | AH76: =IFERROR(((AE76/D76)^(1/27)-1)*100,"NA") -> 2.9311798
A77: Gibraltar | B77: GIB | C77: GDP per capita (constant 2015 US$) | D77: .. | E77: .. | F77: .. | G77: .. | H77: .. | I77: .. | J77: .. | K77: .. | L77: .. | M77: .. | N77: .. | O77: .. | P77: .. | Q77: .. | R77: .. | S77: .. | T77: .. | U77: .. | V77: .. | W77: .. | X77: .. | Y77: .. | Z77: .. | AA77: .. | AB77: .. | AC77: .. | AD77: .. | AE77: .. | AH77: =IFERROR(((AE77/D77)^(1/27)-1)*100,"NA") -> NA
A78: Greece | B78: GRC | C78: GDP per capita (constant 2015 US$) | D78: 15946.755 | E78: 16331.047 | F78: 16979.403 | G78: 17543.238 | H78: 18013.063 | I78: 18642.721 | J78: 19312.303 | K78: 19996.465 | L78: 21104.741 | M78: 22118.06 | N78: 22185.425 | O78: 23369.15 | P78: 24072.792 | Q78: 23928.502 | R78: 22839.249 | S78: 21560.353 | T78: 19400.808 | U78: 18123.671 | V78: 17796.258 | W78: 18000.418 | X78: 18083.878 | Y78: 18070.781 | Z78: 18304.308 | AA78: 18647.496 | AB78: 19017.996 | AC78: 17283.246 | AD78: 18960.891 | AE78: 20287.725 | AH78: =IFERROR(((AE78/D78)^(1/27)-1)*100,"NA") -> 0.89569373
A79: Greenland | B79: GRL | C79: GDP per capita (constant 2015 US$) | D79: 26416.517 | E79: 26772.614 | F79: 27117.373 | G79: 29169.047 | H79: 29570.962 | I79: 31614.619 | J79: 31930.595 | K79: 31475.821 | L79: 32779.882 | M79: 34953.949 | N79: 36681.806 | O79: 38829.536 | P79: 39896.875 | Q79: 42527.667 | R79: 42899.744 | S79: 43198.032 | T79: 42994.879 | U79: 43655.7 | V79: 43338.384 | W79: 45545.143 | X79: 44536.355 | Y79: 46561.783 | Z79: 46597.945 | AA79: 47012.986 | AB79: 48170.79 | AC79: 48139.583 | AD79: 48514.527 | AE79: .. | AH79: =IFERROR(((AE79/D79)^(1/27)-1)*100,"NA") -> NA
A80: Grenada | B80: GRD | C80: GDP per capita (constant 2015 US$) | D80: 5017.0166 | E80: 5200.4032 | F80: 5424.8551 | G80: 6025.303 | H80: 6403.3861 | I80: 6678.3074 | J80: 6512.5924 | K80: 6718.09 | L80: 7319.4655 | M80: 7220.5477 | N80: 8124.4129 | O80: 7748.2332 | P80: 8168.451 | Q80: 8190.6476 | R80: 7596.9027 | S80: 7505.7132 | T80: 7505.2652 | U80: 7354.9736 | V80: 7461.4007 | W80: 7939.5021 | X80: 8379.6218 | Y80: 8621.5389 | Z80: 8933.1082 | AA80: 9252.554 | AB80: 9247.8984 | AC80: 7915.1387 | AD80: 8223.1867 | AE80: 8688.5478 | AH80: =IFERROR(((AE80/D80)^(1/27)-1)*100,"NA") -> 2.0547903
A81: Guam | B81: GUM | C81: GDP per capita (constant 2015 US$) | D81: .. | E81: .. | F81: .. | G81: .. | H81: .. | I81: .. | J81: .. | K81: 29531.101 | L81: 29640.893 | M81: 31446.572 | N81: 32507.517 | O81: 31273.577 | P81: 31481.052 | Q81: 32128.972 | R81: 32298.348 | S81: 32964.245 | T81: 32841.672 | U81: 33392.685 | V81: 33822.593 | W81: 34328.563 | X81: 34522.378 | Y81: 34509.601 | Z81: 34763.081 | AA81: 34472.959 | AB81: 35378.956 | AC81: 31236.08 | AD81: 31325.396 | AE81: .. | AH81: =IFERROR(((AE81/D81)^(1/27)-1)*100,"NA") -> NA
A82: Guatemala | B82: GTM | C82: GDP per capita (constant 2015 US$) | D82: 2965.886 | E82: 2981.115 | F82: 3038.7076 | G82: 3115.9713 | H82: 3160.0733 | I82: 3195.3881 | J82: 3192.3024 | K82: 3239.5608 | L82: 3250.8348 | M82: 3282.3146 | N82: 3320.1576 | O82: 3427.6716 | P82: 3573.5926 | Q82: 3620.8234 | R82: 3570.2958 | S82: 3606.4235 | T82: 3688.8589 | U82: 3731.6685 | V82: 3802.1464 | W82: 3903.052 | X82: 3994.6291 | Y82: 4034.1506 | Z82: 4091.26 | AA82: 4163.4763 | AB82: 4263.7084 | AC82: 4124.1435 | AD82: 4388.7241 | AE82: 4504.1292 | AH82: =IFERROR(((AE82/D82)^(1/27)-1)*100,"NA") -> 1.5595124
A83: Guinea | B83: GIN | C83: GDP per capita (constant 2015 US$) | D83: 571.98275 | E83: 580.80007 | F83: 598.45611 | G83: 608.64402 | H83: 617.7514 | I83: 620.90446 | J83: 635.33183 | K83: 657.85676 | L83: 651.30526 | M83: 652.50422 | N83: 658.89438 | O83: 653.11938 | P83: 681.82818 | Q83: 693.11411 | R83: 668.81474 | S83: 683.98458 | T83: 704.73732 | U83: 728.36844 | V83: 738.84059 | W83: 747.36341 | X83: 756.42559 | Y83: 816.84708 | Z83: 878.17927 | AA83: 910.65264 | AB83: 937.70313 | AC83: 959.43197 | AD83: 972.77903 | AE83: 994.437 | AH83: =IFERROR(((AE83/D83)^(1/27)-1)*100,"NA") -> 2.0695234
A84: Guinea-Bissau | B84: GNB | C84: GDP per capita (constant 2015 US$) | D84: 682.22752 | E84: 745.75817 | F84: 779.31108 | G84: 550.09004 | H84: 545.41205 | I84: 563.62431 | J84: 563.8086 | K84: 545.96682 | L84: 536.56102 | M84: 538.54252 | N84: 548.20737 | O84: 547.23217 | P84: 550.8765 | Q84: 554.06349 | R84: 558.19208 | S84: 569.01763 | T84: 599.0452 | U84: 573.2172 | V84: 576.17989 | W84: 566.53558 | X84: 585.95701 | Y84: 607.16634 | Z84: 627.61694 | AA84: 620.77103 | AB84: 633.72575 | AC84: 604.59515 | AD84: 613.89811 | AE84: 621.85223 | AH84: =IFERROR(((AE84/D84)^(1/27)-1)*100,"NA") -> -0.34259965
A85: Guyana | B85: GUY | C85: GDP per capita (constant 2015 US$) | D85: 3342.1721 | E85: 3599.0482 | F85: 3813.1947 | G85: 3741.8046 | H85: 3845.8741 | I85: 3788.2414 | J85: 3870.7298 | K85: 3911.9244 | L85: 3885.9707 | M85: 3947.4383 | N85: 3874.0681 | O85: 4079.9999 | P85: 4384.0739 | Q85: 4475.0494 | R85: 4654.5152 | S85: 4868.6945 | T85: 5147.1608 | U85: 5420.6648 | V85: 5592.7372 | W85: 5659.0818 | X85: 5668.4298 | Y85: 5852.8117 | Z85: 6038.2534 | AA85: 6127.6791 | AB85: 6348.6837 | AC85: 9126.7914 | AD85: 10857.32 | AE85: 17646.216 | AH85: =IFERROR(((AE85/D85)^(1/27)-1)*100,"NA") -> 6.3564436
A86: Haiti | B86: HTI | C86: GDP per capita (constant 2015 US$) | D86: 1291.0774 | E86: 1319.7469 | F86: 1330.6837 | G86: 1335.1363 | H86: 1346.5905 | I86: 1333.7272 | J86: 1305.4978 | K86: 1296.4107 | L86: 1318.5941 | M86: 1279.5466 | N86: 1297.086 | O86: 1298.0349 | P86: 1336.8323 | Q86: 1350.2335 | R86: 1406.935 | S86: 1312.2849 | T86: 1363.7488 | U86: 1349.6892 | V86: 1387.1112 | W86: 1406.4122 | X86: 1405.7148 | Y86: 1411.1431 | Z86: 1426.6337 | AA86: 1430.8188 | AB86: 1387.5149 | AC86: 1324.2833 | AD86: 1284.4779 | AE86: 1247.8924 | AH86: =IFERROR(((AE86/D86)^(1/27)-1)*100,"NA") -> -0.12592441
A87: Honduras | B87: HND | C87: GDP per capita (constant 2015 US$) | D87: 1722.533 | E87: 1706.689 | F87: 1736.4791 | G87: 1751.9384 | H87: 1693.7231 | I87: 1768.2539 | J87: 1768.29 | K87: 1787.0989 | L87: 1821.1504 | M87: 1887.0853 | N87: 1953.3261 | O87: 2033.0711 | P87: 2110.0473 | Q87: 2151.2016 | R87: 2054.3841 | S87: 2087.2523 | T87: 2124.1875 | U87: 2169.1563 | V87: 2187.8334 | W87: 2213.4405 | X87: 2257.2253 | Y87: 2303.8785 | Z87: 2373.7916 | AA87: 2423.2761 | AB87: 2446.1081 | AC87: 2190.9744 | AD87: 2428.0319 | AE87: 2487.7056 | AH87: =IFERROR(((AE87/D87)^(1/27)-1)*100,"NA") -> 1.3706602
A88: Hong Kong SAR, China | B88: HKG | C88: GDP per capita (constant 2015 US$) | D88: 25620.028 | E88: 25551.388 | F88: 26631.81 | G88: 24856.797 | H88: 25237.662 | I88: 26933.25 | J88: 26885.425 | K88: 27210.068 | L88: 28097.097 | M88: 30304.29 | N88: 32401.355 | O88: 34457.996 | P88: 36371.639 | Q88: 36924.017 | R88: 35938.557 | S88: 38089.987 | T88: 39656.313 | U88: 39887.813 | V88: 40959.971 | W88: 41796.841 | X88: 42432.162 | Y88: 43087.541 | Z88: 44380.802 | AA88: 45280.487 | AB88: 44195.262 | AC88: 41451.287 | AD88: 44525.593 | AE88: 43369.714 | AH88: =IFERROR(((AE88/D88)^(1/27)-1)*100,"NA") -> 1.9687099
A89: Hungary | B89: HUN | C89: GDP per capita (constant 2015 US$) | D89: 7675.5782 | E89: 7695.1105 | F89: 7952.9831 | G89: 8282.3989 | H89: 8560.9691 | I89: 8967.6963 | J89: 9354.4808 | K89: 9825.9432 | L89: 10255.61 | M89: 10792.737 | N89: 11278.616 | O89: 11741.948 | P89: 11792.771 | Q89: 11932.038 | R89: 11162.056 | S89: 11307.716 | T89: 11551.499 | U89: 11466.142 | V89: 11705.009 | W89: 12233.299 | X89: 12717.039 | Y89: 13035.353 | Z89: 13628.404 | AA89: 14377.424 | AB89: 15083.599 | AC89: 14430.477 | AD89: 15517.049 | AE89: 16336.241 | AH89: =IFERROR(((AE89/D89)^(1/27)-1)*100,"NA") -> 2.8370638
A90: Iceland | B90: ISL | C90: GDP per capita (constant 2015 US$) | D90: 34188.351 | E90: 35557.277 | F90: 37302.668 | G90: 39622.607 | H90: 40725.886 | I90: 42174.665 | J90: 43288.076 | K90: 43143.461 | L90: 43763.776 | M90: 46766.017 | N90: 48850.766 | O90: 50731.691 | P90: 53646.369 | Q90: 53821.471 | R90: 49527.399 | S90: 48193.701 | T90: 48933.546 | U90: 49191.574 | V90: 50946.816 | W90: 51233.244 | X90: 52951.682 | Y90: 55513.642 | Z90: 56501.458 | AA90: 57697.804 | AB90: 57493.42 | AC90: 52486.039 | AD90: 53960.103 | AE90: 56429.3 | AH90: =IFERROR(((AE90/D90)^(1/27)-1)*100,"NA") -> 1.8732687
A91: India | B91: IND | C91: GDP per capita (constant 2015 US$) | D91: 618.13929 | E91: 651.95836 | F91: 665.46611 | G91: 693.4085 | H91: 740.91623 | I91: 755.48229 | J91: 777.73366 | K91: 793.10096 | L91: 840.81804 | M91: 892.3821 | N91: 947.76344 | O91: 1008.6671 | P91: 1070.1315 | Q91: 1087.583 | R91: 1156.8807 | S91: 1238.0147 | T91: 1285.283 | U91: 1337.4761 | V91: 1404.5453 | W91: 1490.0285 | X91: 1590.1743 | Y91: 1701.1842 | Z91: 1795.9118 | AA91: 1891.1384 | AB91: 1944.3148 | AC91: 1813.5346 | AD91: 1961.9609 | AE91: 2089.7344 | AH91: =IFERROR(((AE91/D91)^(1/27)-1)*100,"NA") -> 4.6147131
A92: Indonesia | B92: IDN | C92: GDP per capita (constant 2015 US$) | D92: 1922.3521 | E92: 2039.363 | F92: 2101.2541 | G92: 1797.0839 | H92: 1784.3336 | I92: 1845.2278 | J92: 1885.6798 | K92: 1943.6449 | L92: 2009.4898 | M92: 2083.8825 | N92: 2174.9152 | O92: 2264.9357 | P92: 2377.255 | Q92: 2487.6113 | R92: 2569.8742 | S92: 2695.8682 | T92: 2826.4804 | U92: 2959.5145 | V92: 3086.3231 | W92: 3203.4843 | X92: 3322.5817 | Y92: 3453.0494 | Z92: 3591.78 | AA92: 3741.3053 | AB92: 3892.4217 | AC92: 3780.1216 | AD92: 3892.9624 | AE92: 4073.6105 | AH92: =IFERROR(((AE92/D92)^(1/27)-1)*100,"NA") -> 2.8204505
A93: Iran, Islamic Rep. | B93: IRN | C93: GDP per capita (constant 2015 US$) | D93: 3564.6618 | E93: 3741.5814 | F93: 3738.5673 | G93: 3757.3431 | H93: 3772.3559 | I93: 3927.7092 | J93: 3953.4797 | K93: 4231.4789 | L93: 4554.5939 | M93: 4675.9408 | N93: 4748.0303 | O93: 4908.96 | P93: 5232.7035 | Q93: 5174.3548 | R93: 5155.8572 | S93: 5378.7177 | T93: 5450.9382 | U93: 5180.086 | V93: 5027.4847 | W93: 5178.9007 | X93: 4990.9368 | Y93: 5332.101 | Z93: 5401.4559 | AA93: 5233.2821 | AB93: 5017.1172 | AC93: 5141.0848 | AD93: 5344.958 | AE93: 5507.5334 | AH93: =IFERROR(((AE93/D93)^(1/27)-1)*100,"NA") -> 1.624339
... A95: Ireland | B95: IRL | C95: GDP per capita (constant 2015 US$) | D95: 28192.775 | E95: 30034.698 | F95: 33012.334 | G95: 35533.652 | H95: 38835.041 | I95: 41924.293 | J95: 43451.373 | K95: 45245.809 | L95: 45856.35 | M95: 48081.968 | N95: 49746.056 | O95: 50838.077 | P95: 52012.045 | Q95: 48677.217 | R95: 45729.903 | S95: 46246.845 | T95: 46635.345 | U95: 46377.922 | V95: 46676.258 | W95: 50427.33 | X95: 62179.264 | Y95: 62566.798 | Z95: 67652.02 | AA95: 72478.838 | AB95: 75281.922 | AC95: 79441.709 | AD95: 90589.197 | AE95: 97316.878 | AH95: =IFERROR(((AE95/D95)^(1/27)-1)*100,"NA") -> 4.6954457
A96: Isle of Man | B96: IMN | C96: GDP per capita (constant 2015 US$) | D96: 30828.305 | E96: 32959.001 | F96: 35394.2 | G96: 39663.501 | H96: 44529.061 | I96: 46334.341 | J96: 48301.993 | K96: 50774.996 | L96: 53299.433 | M96: 55545.052 | N96: 58275.577 | O96: 62126.782 | P96: 66068.194 | Q96: 68547.373 | R96: 69212.003 | S96: 70785.768 | T96: 71754.664 | U96: 77006.494 | V96: 80380.899 | W96: 84774.418 | X96: 84753.457 | Y96: 90801.104 | Z96: 93232.584 | AA96: 95074.375 | AB96: 95137.276 | AC96: 86614.116 | AD96: .. | AE96: .. | AH96: =IFERROR(((AE96/D96)^(1/27)-1)*100,"NA") -> NA
A97: Israel | B97: ISR | C97: GDP per capita (constant 2015 US$) | D97: 25872.23 | E97: 26698.232 | F97: 27026.481 | G97: 27502.574 | H97: 27704.022 | I97: 29321.325 | J97: 28733.941 | K97: 28128.846 | L97: 28010.607 | M97: 28836.513 | N97: 29503.901 | O97: 30605.156 | P97: 31880.345 | Q97: 32337.198 | R97: 31852.267 | S97: 33048.555 | T97: 34247.623 | U97: 34491.16 | V97: 35348.307 | W97: 36035.258 | X97: 36206.522 | Y97: 37109.022 | Z97: 37953.04 | AA97: 38744.16 | AB97: 39591.369 | AC97: 38176.754 | AD97: 40772.97 | AE97: 42710.778 | AH97: =IFERROR(((AE97/D97)^(1/27)-1)*100,"NA") -> 1.8739386
A98: Italy | B98: ITA | C98: GDP per capita (constant 2015 US$) | D98: 29265.089 | E98: 29627.487 | F98: 30153.775 | G98: 30690.912 | H98: 31184.616 | I98: 32350.904 | J98: 32963.671 | K98: 32998.203 | L98: 32897.391 | M98: 33150.476 | N98: 33257.77 | O98: 33751.7 | P98: 34081.09 | Q98: 33530.36 | R98: 31615.271 | S98: 32058.174 | T98: 32229.457 | U98: 31184.558 | V98: 30257.627 | W98: 29979.919 | X98: 30242.386 | Y98: 30685.646 | Z98: 31244.227 | AA98: 31593.48 | AB98: 32114.3 | AC98: 29375.037 | AD98: 31981.681 | AE98: 33281.337 | AH98: =IFERROR(((AE98/D98)^(1/27)-1)*100,"NA") -> 0.47743788
A99: Jamaica | B99: JAM | C99: GDP per capita (constant 2015 US$) | D99: 5209.8159 | E99: 5155.5643 | F99: 5052.7606 | G99: 4893.4066 | H99: 4907.1467 | I99: 4920.0702 | J99: 4961.1719 | K99: 5035.6352 | L99: 5195.086 | M99: 5238.1738 | N99: 5259.6442 | O99: 5386.3778 | P99: 5440.1249 | Q99: 5375.7616 | R99: 5121.3385 | S99: 5025.4935 | T99: 5089.6052 | U99: 5033.3586 | V99: 5035.1286 | W99: 5049.0804 | X99: 5077.551 | Y99: 5132.2268 | Z99: 5172.9161 | AA99: 5264.1965 | AB99: 5307.5104 | AC99: 4769.6936 | AD99: 4976.3597 | AE99: 5236.7903 | AH99: =IFERROR(((AE99/D99)^(1/27)-1)*100,"NA") -> 0.019128631
A100: Japan | B100: JPN | C100: GDP per capita (constant 2015 US$) | D100: 30171.164 | E100: 31046.17 | F100: 31276.193 | G100: 30795.089 | H100: 30636.266 | I100: 31430.631 | J100: 31476.052 | K100: 31416.124 | L100: 31830.218 | M100: 32515.116 | N100: 33098.547 | O100: 33531.519 | P100: 33990.036 | Q100: 33557.645 | R100: 31651.084 | S100: 32942.202 | T100: 33011.134 | U100: 33518.445 | V100: 34239.886 | W100: 34386.906 | X100: 34960.639 | Y100: 35242.199 | Z100: 35861.973 | AA100: 36138.529 | AB100: 36043.784 | AC100: 34603.265 | AD100: 35507.579 | AE100: 36032.394 | AH100: =IFERROR(((AE100/D100)^(1/27)-1)*100,"NA") -> 0.65969145
A101: Jordan | B101: JOR | C101: GDP per capita (constant 2015 US$) | D101: 3521.0523 | E101: 3477.1697 | F101: 3497.3613 | G101: 3520.3537 | H101: 3561.4753 | I101: 3635.2922 | J101: 3747.4649 | K101: 3879.8837 | L101: 3951.041 | M101: 4183.8511 | N101: 4408.2703 | O101: 4453.6538 | P101: 4521.6532 | Q101: 4731.6128 | R101: 4861.127 | S101: 4865.4698 | T101: 4872.9966 | U101: 4920.8652 | V101: 4732.3872 | W101: 4348.2367 | X101: 4064.253 | Y101: 3949.6108 | Z101: 3947.9717 | AA101: 3929.6872 | AB101: 3909.25 | AC101: 3784.7625 | AD101: 3845.857 | AE101: 3891.2122 | AH101: =IFERROR(((AE101/D101)^(1/27)-1)*100,"NA") -> 0.37091151
A102: Kazakhstan | B102: KAZ | C102: GDP per capita (constant 2015 US$) | D102: 3700.7539 | E102: 3776.0834 | F102: 3901.3384 | G102: 3893.9381 | H102: 4037.4532 | I102: 4446.4519 | J102: 5055.3131 | K102: 5550.5048 | L102: 6046.3271 | M102: 6580.8841 | N102: 7155.3426 | O102: 7837.628 | P102: 8438.1034 | Q102: 8554.8223 | R102: 8487.5436 | S102: 8979.3309 | T102: 9506.7326 | U102: 9823.6924 | V102: 10264.297 | W102: 10539.043 | X102: 10510.77 | Y102: 10476.346 | Z102: 10758.519 | AA102: 11053.36 | AB102: 11402.758 | AC102: 10974.245 | AD102: 11298.356 | AE102: 11290.898 | AH102: =IFERROR(((AE102/D102)^(1/27)-1)*100,"NA") -> 4.2178617
A103: Kenya | B103: KEN | C103: GDP per capita (constant 2015 US$) | D103: 1225.1439 | E103: 1241.8785 | F103: 1214.8476 | G103: 1221.5243 | H103: 1215.1639 | I103: 1187.3258 | J103: 1195.4438 | K103: 1166.0653 | L103: 1165.1661 | M103: 1188.5707 | N103: 1221.8593 | O103: 1262.8147 | P103: 1309.8956 | Q103: 1274.4047 | R103: 1278.1409 | S103: 1342.7687 | T103: 1374.5442 | U103: 1401.4908 | V103: 1420.0787 | W103: 1457.5431 | X103: 1496.6536 | Y103: 1525.7436 | Z103: 1550.2035 | AA103: 1604.8029 | AB103: 1653.829 | AC103: 1616.5024 | AD103: 1705.7404 | AE103: 1754.5855 | AH103: =IFERROR(((AE103/D103)^(1/27)-1)*100,"NA") -> 1.3391629
A104: Kiribati | B104: KIR | C104: GDP per capita (constant 2015 US$) | D104: 1397.1191 | E104: 1397.6257 | F104: 1396.0431 | G104: 1461.6337 | H104: 1414.6801 | I104: 1477.0887 | J104: 1427.9574 | K104: 1452.0631 | L104: 1451.3216 | M104: 1399.1577 | N104: 1439.4183 | O104: 1411.1228 | P104: 1412.8056 | Q104: 1357.0736 | R104: 1341.7696 | S104: 1302.1802 | T104: 1302.5061 | U104: 1347.9713 | V104: 1383.0897 | W104: 1348.0122 | X104: 1459.144 | Y104: 1430.0371 | Z104: 1410.6883 | AA104: 1459.794 | AB104: 1405.4695 | AC104: 1357.8891 | AD104: 1437.2877 | AE104: 1433.5163 | AH104: =IFERROR(((AE104/D104)^(1/27)-1)*100,"NA") -> 0.095297413
A105: Korea, Dem. People's Rep. | B105: PRK | C105: GDP per capita (constant 2015 US$) | D105: .. | E105: .. | F105: .. | G105: .. | H105: .. | I105: .. | J105: .. | K105: .. | L105: .. | M105: .. | N105: .. | O105: .. | P105: .. | Q105: .. | R105: .. | S105: .. | T105: .. | U105: .. | V105: .. | W105: .. | X105: .. | Y105: .. | Z105: .. | AA105: .. | AB105: .. | AC105: .. | AD105: .. | AE105: .. | AH105: =IFERROR(((AE105/D105)^(1/27)-1)*100,"NA") -> NA
A106: Korea, Rep. | B106: KOR | C106: GDP per capita (constant 2015 US$) | D106: 13411.112 | E106: 14332.137 | F106: 15074.488 | G106: 14198.386 | H106: 15714.412 | I106: 16995.559 | J106: 17684.05 | K106: 18940.384 | L106: 19435.493 | M106: 20364.76 | N106: 21197.199 | O106: 22196.208 | P106: 23365.14 | Q106: 23887.06 | R106: 23952.813 | S106: 25455.617 | T106: 26191.644 | U106: 26680.275 | V106: 27399.616 | W106: 28100.01 | X106: 28737.439 | Y106: 29467.124 | Z106: 30312.889 | AA106: 31059.267 | AB106: 31645.95 | AC106: 31378.158 | AD106: 32786.692 | AE106: 33719.386 | AH106: =IFERROR(((AE106/D106)^(1/27)-1)*100,"NA") -> 3.4737481
...

Sheet DONNEES
B1: tx croiss | C1: loggdp95 | D1: INV | E1: tx_pop | F1: GOVeff | G1: ESP VIE | H1: POLSTAB | I1: SCOLPRIM | J1: SCOLSEC | K1: SCOLTER | L1: CONTRCORR | M1: RegQual | N1: RuLaw | O1: VoiceAcc | P1: GDP 1995 | Q1: tx_rev_gdp | R1: tx_ipc (%toltx) | S1: profit tx | T1: tx_ipc(%rev) | U1: debt | V1: VAT_gdp | W1: trade_tx_gdp | X1: tx_ipc_gdp | Y1: tx95_rev_gdp | Z1: inv95 | AA1: GNQ | AB1: FMR | AC1: CUS_EX_RT
A2: Afghanistan | B2: =Tx_croissance!AH2 -> NA | C2: =IFERROR(LN(P2),"NA") -> NA | D2: 12.221166 | E2: 3.4954979 | F2: -1.5282862 | G2: 59.095889 | H2: -2.4809625 | I2: 115.7132 | J2: 100.72019 | K2: 29.139934 | L2: -1.4200903 | M2: -1.4936953 | N2: -1.7212338 | O2: -1.3154747 | P2: NA | Q2: 7.8005405 | R2: 28.969577 | S2: 0 | T2: 3.8070328 | U2: NA | V2: ='VATtax et trade tax et ipc '!AI2 -> 2.401943 | W2: {='VATtax et trade tax et ipc '!AK2:AK218} -> 3.0990709 | X2: ='VATtax et trade tax et ipc '!AM2 -> 2.4633253 | AA2: 0 | AB2: 1 | AC2: 38.77887
A3: Albania | B3: =Tx_croissance!AH3 -> 4.7096771 | C3: =IFERROR(LN(P3),"NA") -> 7.3052022 | D3: 28.234992 | E3: -0.51387055 | F3: -0.30570641 | G3: 76.962704 | H3: -0.07743383 | I3: 87.204486 | J3: 39.967874 | K3: 5.6691786 | L3: -0.6724434 | M3: 0.020878915 | N3: -0.53877781 | O3: 0.034698074 | P3: 1488.0209 | Q3: 16.430994 | R3: 19.034249 | S3: 13.1 | T3: 13.141789 | U3: 66.809868 | V3: ='VATtax et trade tax et ipc '!AI3 -> 13.416597 | W3: 0.91035615 | X3: ='VATtax et trade tax et ipc '!AM3 -> 3.7756395 | Y3: 13.600788 | Z3: 21.278513 | AA3: 0 | AB3: 1 | AC3: 9.4345675
A4: Algeria | B4: =Tx_croissance!AH4 -> 1.2472527 | C4: =IFERROR(LN(P4),"NA") -> 7.9593136 | D4: 30.722778 | E4: 1.694848 | F4: -0.57214574 | G4: 72.826667 | H4: -1.2189323 | I4: 107.48072 | J4: 22.097866 | K4: 5.4010473 | L4: -0.64930455 | M4: -0.96427201 | N4: -0.84774298 | O4: -0.97832619 | P4: 2862.1079 | Q4: NA | R4: #DIV/0! | S4: 7.6266667 | T4: #DIV/0! | U4: NA | V4: ='VATtax et trade tax et ipc '!AI4 -> NA | W4: NA | X4: ='VATtax et trade tax et ipc '!AM4 -> NA | Z4: 29.136944 | AA4: 0 | AB4: 1 | AC4: NA
A5: American Samoa | B5: =Tx_croissance!AH5 -> NA | C5: =IFERROR(LN(P5),"NA") -> NA | D5: NA | E5: -0.59425675 | F5: 0.45066375 | G5: NA | H5: 0.99981607 | I5: 107.93092 | J5: 86.952467 | K5: 38.056991 | L5: 0.88248917 | M5: 0.26575818 | N5: 1.1612325 | O5: 0.91652832 | P5: NA | Q5: NA | R5: #DIV/0! | S5: #DIV/0! | T5: #DIV/0! | U5: NA | V5: ='VATtax et trade tax et ipc '!AI5 -> NA | W5: NA | X5: ='VATtax et trade tax et ipc '!AM5 -> NA | AA5: 0 | AB5: 0 | AC5: NA
A6: Andorra | B6: =Tx_croissance!AH6 -> 1.2707207 | C6: =IFERROR(LN(P6),"NA") -> 10.241794 | D6: NA | E6: 0.95837133 | F6: 1.572452 | G6: NA | H6: 1.3621018 | I6: 89.527079 | J6: 89.524159 | K6: 13.653441 | L6: 1.252925 | M6: 1.3059024 | N6: 1.3283595 | O6: 1.3110088 | P6: 28051.403 | Q6: NA | R6: #DIV/0! | S6: #DIV/0! | T6: #DIV/0! | U6: NA | V6: ='VATtax et trade tax et ipc '!AI6 -> NA | W6: NA | X6: ='VATtax et trade tax et ipc '!AM6 -> NA | AA6: 0 | AB6: 0 | AC6: NA
A7: Angola | B7: =Tx_croissance!AH7 -> 1.3160424 | C7: =IFERROR(LN(P7),"NA") -> 7.4239911 | D7: 26.839838 | E7: 3.4720108 | F7: -1.0962019 | G7: 54.111889 | H7: -0.76937486 | I7: 110.11878 | J7: 90.954865 | K7: 49.593525 | L7: -1.2330975 | M7: -1.0589671 | N7: -1.2683666 | O7: -1.1383518 | P7: 1675.7081 | Q7: 16.951172 | R7: 75.134266 | S7: 23.92 | T7: 40.214544 | U7: NA | V7: ='VATtax et trade tax et ipc '!AI7 -> 1.1549995 | W7: 0.70915725 | X7: ='VATtax et trade tax et ipc '!AM7 -> 7.7522472 | AA7: 0 | AB7: 1 | AC7: 6.4242978
A8: Antigua and Barbuda | B8: =Tx_croissance!AH8 -> 0.90711749 | C8: =IFERROR(LN(P8),"NA") -> 9.516668 | D8: NA | E8: 1.1964416 | F8: 1.2284783 | G8: 76.391519 | H8: 0.86728527 | I8: 114.70298 | J8: 98.955017 | K8: 74.241269 | L8: 0.80119645 | M8: 0.54966119 | N8: 0.71992285 | O8: 0.55544067 | P8: 13584.273 | Q8: NA | R8: #DIV/0! | S8: 27.873333 | T8: #DIV/0! | U8: NA | V8: ='VATtax et trade tax et ipc '!AI8 -> NA | W8: NA | X8: ='VATtax et trade tax et ipc '!AM8 -> NA | AA8: 0 | AB8: 0 | AC8: NA
A9: Argentina | B9: =Tx_croissance!AH9 -> 0.97085591 | C9: =IFERROR(LN(P9),"NA") -> 9.2072688 | D9: 16.526854 | E9: 1.0467921 | F9: 0.309166 | G9: 75.272593 | H9: -0.062694981 | I9: 99.739047 | J9: 89.30783 | K9: 41.944904 | L9: -0.34692161 | M9: -0.52550969 | N9: -0.51334566 | O9: 0.40665429 | P9: 9969.3316 | Q9: 10.465761 | R9: 21.450258 | S9: 2.72 | T9: 13.771817 | U9: NA | V9: ='VATtax et trade tax et ipc '!AI9 -> 3.9050876 | W9: 1.5709463 | X9: ='VATtax et trade tax et ipc '!AM9 -> 1.3523403 | Y9: 8.0543577 | Z9: 17.937746 | AA9: 0 | AB9: 0 | AC9: 6.1704262
A10: Armenia | B10: =Tx_croissance!AH10 -> 6.5264997 | C10: =IFERROR(LN(P10),"NA") -> 6.8331314 | D10: 24.927534 | E10: -0.69069393 | F10: -0.07553162 | G10: 72.329667 | H10: -0.27584209 | I10: NA | J10: NA | K10: NA | L10: -0.55545039 | M10: 0.15242438 | N10: -0.35538289 | O10: -0.47553955 | P10: 928.0925 | Q10: 18.749481 | R10: 32.915449 | S10: 16.62 | T10: 27.466847 | U10: 57.836665 | V10: ='VATtax et trade tax et ipc '!AI10 -> 12.528264 | W10: 1.3716237 | X10: ='VATtax et trade tax et ipc '!AM10 -> 9.0651098 | Z10: 16.153955 | AA10: 0 | AB10: 1 | AC10: 5.3095739
A11: Aruba | B11: =Tx_croissance!AH11 -> 0.35870917 | C11: =IFERROR(LN(P11),"NA") -> 10.292076 | D11: NA | E11: 1.2643374 | F11: -0.22971242 | G11: 74.586444 | H11: 1.2768626 | I11: 115.11915 | J11: 113.40096 | K11: NA | L11: 1.1393865 | M11: 1.0875311 | N11: 1.1622112 | O11: 1.1683587 | P11: 29497.963 | Q11: NA | R11: #DIV/0! | S11: #DIV/0! | T11: #DIV/0! | U11: NA | V11: ='VATtax et trade tax et ipc '!AI11 -> NA | W11: NA | X11: ='VATtax et trade tax et ipc '!AM11 -> NA | AA11: 0 | AB11: 0 | AC11: NA
A12: Australia | B12: =Tx_croissance!AH12 -> 1.6403108 | C12: =IFERROR(LN(P12),"NA") -> 10.579234 | D12: 25.514464 | E12: 1.3528714 | F12: 1.1339919 | G12: 81.006775 | H12: 0.98132158 | I12: 102.78112 | J12: 146.69508 | K12: 101.18495 | L12: 1.8690129 | M12: 1.7265004 | N12: 1.7302952 | O12: 1.3990897 | P12: 39309.995 | Q12: 21.895615 | R12: 72.064757 | S12: 26.266667 | T12: 64.892736 | U12: 35.458215 | V12: ='VATtax et trade tax et ipc '!AI12 -> 5.4911305 | W12: 0.67024513 | X12: ='VATtax et trade tax et ipc '!AM12 -> 16.434395 | Y12: 21.159594 | Z12: 25.095292 | AA12: 0 | AB12: 0 | AC12: 2.8204189
A13: Austria | B13: =Tx_croissance!AH13 -> 1.205426 | C13: =IFERROR(LN(P13),"NA") -> 10.427935 | D13: 23.921077 | E13: 0.46585597 | F13: 1.6610913 | G13: 79.828726 | H13: 1.0967106 | I13: 101.698 | J13: 100.66312 | K13: 73.446607 | L13: 1.6486806 | M13: 1.4838394 | N13: 1.8280325 | O13: 1.3867748 | P13: 33790.485 | Q13: 22.430875 | R13: 46.996991 | S13: 16.86 | T13: 27.53463 | U13: 80.368534 | V13: ='VATtax et trade tax et ipc '!AI13 -> 11.745178 | W13: -0.0027464446 | X13: ='VATtax et trade tax et ipc '!AM13 -> 11.93604 | Y13: 24.600106 | Z13: 25.299058 | AA13: 0 | AB13: 0 | AC13: 0.0098863037
A14: Azerbaijan | B14: =Tx_croissance!AH14 -> 6.1970333 | C14: =IFERROR(LN(P14),"NA") -> 7.0053337 | D14: 26.805767 | E14: 1.0320249 | F14: 1.6619661 | G14: 68.094741 | H14: -0.74111291 | I14: 98.485199 | J14: 84.919172 | K14: 25.63076 | L14: -1.0847096 | M14: -0.47731127 | N14: -0.82028031 | O14: -1.3069318 | P14: 1102.4979 | Q14: 14.193999 | R14: 36.101595 | S14: 13.4 | T14: 15.683281 | U14: 11.25391 | V14: ='VATtax et trade tax et ipc '!AI14 -> 8.2392438 | W14: 1.4743464 | X14: ='VATtax et trade tax et ipc '!AM14 -> 6.0267988 | Y14: 17.954073 | Z14: 15.643453 | AA14: 0 | AB14: 1 | AC14: 7.5939685
A15: Bahamas, The | B15: =Tx_croissance!AH15 -> 0.2367812 | C15: =IFERROR(LN(P15),"NA") -> 10.254516 | D15: 26.505855 | E15: 1.1876735 | F15: -0.55437021 | G15: 72.391037 | H15: 0.94337777 | I15: 96.945866 | J15: 29.503661 | K15: 3.1290701 | L15: 1.2644203 | M15: 0.58671984 | N15: 0.75484677 | O15: 0.98894457 | P15: 28410.556 | Q15: 12.933436 | R15: #DIV/0! | S15: 0 | T15: #DIV/0! | U15: 42.184055 | V15: ='VATtax et trade tax et ipc '!AI15 -> 5.7376246 | W15: 5.172775 | X15: ='VATtax et trade tax et ipc '!AM15 -> NA | Y15: 17.346165 | Z15: 25.438612 | AA15: 0 | AB15: 0 | AC15: 35.734648
A16: Bahrain | B16: =Tx_croissance!AH16 -> 0.66403743 | C16: =IFERROR(LN(P16),"NA") -> 9.9234554 | D16: 23.467916 | E16: 3.2461176 | F16: 0.91198128 | G16: 77.508111 | H16: -0.45629006 | I16: 102.61714 | J16: 155.73887 | K16: 67.336749 | L16: 0.20715693 | M16: 0.68849758 | N16: 0.42452549 | O16: -1.0894483 | P16: 20403.371 | Q16: 4.8338218 | R16: 27.34312 | S16: 0 | T16: 4.3790231 | U16: 23.769771 | V16: ='VATtax et trade tax et ipc '!AI16 -> 0.31447793 | W16: 0.63554918 | X16: ='VATtax et trade tax et ipc '!AM16 -> 0.43292226 | Y16: 4.796763 | Z16: 17.327454 | AA16: 0 | AB16: 0 | AC16: 41.223081
A17: Bangladesh | B17: =Tx_croissance!AH17 -> 4.3885534 | C17: =IFERROR(LN(P17),"NA") -> 6.3273817 | D17: 26.658804 | E17: 1.4017432 | F17: 0.45139074 | G17: 67.719222 | H17: -1.1891145 | I17: 103.30039 | J17: 39.306518 | K17: 8.4604723 | L17: -1.0820966 | M17: -0.93982781 | N17: -0.82140678 | O17: -0.48791288 | P17: 559.68923 | Q17: 7.5968699 | R17: 25.449192 | S17: 31.071429 | T17: 20.232594 | U17: 31.510096 | V17: ='VATtax et trade tax et ipc '!AI17 -> 4.0092421 | W17: 1.8015978 | X17: ='VATtax et trade tax et ipc '!AM17 -> 2.5116353 | Z17: 19.119796 | AA17: 0 | AB17: 1 | AC17: 28.821819
A18: Barbados | B18: =Tx_croissance!AH18 -> 0.57238029 | C18: =IFERROR(LN(P18),"NA") -> 9.5623417 | D18: 16.778978 | E18: 0.26202587 | F18: -0.75506117 | G18: 75.431556 | H18: 1.0822522 | I18: 67.930978 | J18: 24.278902 | K18: 3.9475652 | L18: 1.4049004 | M18: 0.75509913 | N18: 0.98860834 | O18: 1.1252438 | P18: 14219.104 | Q18: 25.246765 | R18: 34.357319 | S18: 19.622222 | T18: 31.820108 | U18: 99.753458 | V18: ='VATtax et trade tax et ipc '!AI18 -> 13.164133 | W18: 2.5135495 | X18: ='VATtax et trade tax et ipc '!AM18 -> 9.2873308 | Z18: 11.661808 | AA18: 0 | AB18: 0 | AC18: 9.1156998
A19: Belarus | B19: =Tx_croissance!AH19 -> 4.507885 | C19: =IFERROR(LN(P19),"NA") -> 7.542472 | D19: 27.849921 | E19: -0.36706017 | F19: 1.1357789 | G19: 70.638432 | H19: 0.078517446 | I19: 105.78866 | J19: 55.475698 | K19: 12.775785 | L19: -0.43211972 | M19: -1.1852769 | N19: -1.0220175 | O19: -1.4641737 | P19: 1886.4877 | Q19: 17.44036 | R19: 11.051499 | S19: 15.88 | T19: 6.1935302 | U19: 21.037599 | V19: ='VATtax et trade tax et ipc '!AI19 -> 8.0357778 | W19: 3.1923354 | X19: ='VATtax et trade tax et ipc '!AM19 -> 0.85928337 | Y19: 19.887647 | Z19: 24.697907 | AA19: 0 | AB19: 0 | AC19: 9.603561
A20: Belgium | B20: =Tx_croissance!AH20 -> 1.2814957 | C20: =IFERROR(LN(P20),"NA") -> 10.352328 | D20: 22.601563 | E20: 0.5153448 | F20: -0.83133648 | G20: 79.565086 | H20: 0.7702138 | I20: 101.35388 | J20: 92.131931 | K20: 55.878957 | L20: 1.437862 | M20: 1.2696099 | N20: 1.3549161 | O20: 1.3580424 | P20: 31329.892 | Q20: 25.085864 | R20: 57.613329 | S20: 8.5 | T20: 35.425657 | U20: 106.0602 | V20: ='VATtax et trade tax et ipc '!AI20 -> 10.118285 | W20: NA | X20: ='VATtax et trade tax et ipc '!AM20 -> 13.953597 | Y20: 25.622419 | Z20: 21.231741 | AA20: 0 | AB20: 0 | AC20: NA
A21: Belize | B21: =Tx_croissance!AH21 -> 0.81824313 | C21: =IFERROR(LN(P21),"NA") -> 8.5109323 | D21: 17.747519 | E21: 2.5506879 | F21: 1.5396026 | G21: 71.090037 | H21: 0.21959279 | I21: 96.8926 | J21: 90.5701 | K21: 40.954326 | L21: -0.15975439 | M21: -0.28267077 | N21: -0.39967279 | O21: 0.65727731 | P21: 4968.7932 | Q21: 16.427327 | R21: 27.729823 | S21: 24.7 | T21: 23.391049 | U21: 59.624879 | V21: ='VATtax et trade tax et ipc '!AI21 -> 6.3035175 | W21: 4.6893769 | X21: ='VATtax et trade tax et ipc '!AM21 -> 4.6216683 | Y21: 14.243196 | Z21: 19.561072 | AA21: 0 | AB21: 0 | AC21: 43.637766
A22: Benin | B22: =Tx_croissance!AH22 -> 1.6630842 | C22: =IFERROR(LN(P22),"NA") -> 6.6900349 | D22: 19.800557 | E22: 2.9029332 | F22: -0.2037761 | G22: 57.924815 | H22: 0.25150338 | I22: NA | J22: 83.060659 | K22: 14.33432 | L22: -0.54896374 | M22: -0.45623376 | N22: -0.50650971 | O22: 0.18884809 | P22: 804.35033 | Q22: 12.269847 | R22: #DIV/0! | S22: 15.426667 | T22: #DIV/0! | U22: NA | V22: ='VATtax et trade tax et ipc '!AI22 -> NA | W22: NA | X22: ='VATtax et trade tax et ipc '!AM22 -> NA | Z22: 17.564867 | AA22: 0 | AB22: 1 | AC22: NA
A23: Bermuda | B23: =Tx_croissance!AH23 -> 0.64051094 | C23: =IFERROR(LN(P23),"NA") -> 11.402198 | D23: 12.636803 | E23: 0.24499 | F23: -0.50903461 | G23: 79.759667 | H23: 0.8931456 | I23: 93.126175 | J23: 84.573198 | K23: 35.584385 | L23: 1.2607275 | M23: 1.2075273 | N23: 0.90820859 | O23: 1.0565776 | P23: 89518.278 | Q23: NA | R23: #DIV/0! | S23: #DIV/0! | T23: #DIV/0! | U23: NA | V23: ='VATtax et trade tax et ipc '!AI23 -> NA | W23: NA | X23: ='VATtax et trade tax et ipc '!AM23 -> NA | AA23: 0 | AB23: 0 | AC23: NA
A24: Bhutan | B24: =Tx_croissance!AH24 -> NA | C24: =IFERROR(LN(P24),"NA") -> 6.8505578 | D24: 50.534339 | E24: 1.4506695 | F24: 1.1320169 | G24: 66.759296 | H24: 0.89031048 | I24: 100.13653 | J24: 98.674237 | K24: 71.284453 | L24: 1.0714155 | M24: -0.63584256 | N24: 0.33951693 | O24: -0.47107942 | P24: 944.40756 | Q24: 9.2555309 | R24: 53.832345 | S24: 33.42 | T24: 18.025831 | U24: 69.061865 | V24: ='VATtax et trade tax et ipc '!AI24 -> 4.9238723 | W24: 0.79130598 | X24: ='VATtax et trade tax et ipc '!AM24 -> 6.2481379 | Y24: 6.898255 | Z24: 42.317708 | AA24: 0 | AB24: 1 | AC24: 3.2686868
A25: Bolivia | B25: =Tx_croissance!AH25 -> 1.9385795 | C25: =IFERROR(LN(P25),"NA") -> 7.5319022 | D25: 17.404931 | E25: 1.6535913 | F25: 0.4656296 | G25: 64.634926 | H25: -0.45960037 | I25: 115.03735 | J25: 78.156679 | K25: 21.133021 | L25: -0.68099136 | M25: -0.71039483 | N25: -0.90665773 | O25: -0.014136566 | P25: 1866.6529 | Q25: 11.206035 | R25: 11.104858 | S25: 0 | T25: 6.683974 | U25: 54.801788 | V25: ='VATtax et trade tax et ipc '!AI25 -> 4.4863966 | W25: 0.37027745 | X25: ='VATtax et trade tax et ipc '!AM25 -> 0.70856584 | Y25: 9.7223295 | Z25: 15.533527 | AA25: 0 | AB25: 1 | AC25: 7.1759694
A26: Bosnia and Herzegovina | B26: =Tx_croissance!AH26 -> 7.9975228 | C26: =IFERROR(LN(P26),"NA") -> 6.6651979 | D26: 24.760237 | E26: -0.54094737 | F26: -0.51303612 | G26: 75.672074 | H26: -0.45036886 | I26: 104.79967 | J26: 88.698727 | K26: 33.22389 | L26: -0.42206778 | M26: -0.2956734 | N26: -0.36336778 | O26: -0.075485842 | P26: 784.6187 | Q26: 19.921778 | R26: 12.128134 | S26: 11.166667 | T26: 6.2870854 | U26: 47.350149 | V26: ='VATtax et trade tax et ipc '!AI26 -> 21.712007 | W26: 0.54791374 | X26: ='VATtax et trade tax et ipc '!AM26 -> 3.3420054 | Z26: 12.268473 | AA26: 0 | AB26: 1 | AC26: 3.4175339
A27: Botswana | B27: =Tx_croissance!AH27 -> 1.6572815 | C27: =IFERROR(LN(P27),"NA") -> 8.3597135 | D27: 26.430882 | E27: 1.9973979 | F27: -0.78058553 | G27: 57.751111 | H27: 1.0226195 | I27: NA | J27: 76.921761 | K27: NA | L27: 0.85730213 | M27: 0.66657609 | N27: 0.52307551 | O27: 0.53779007 | P27: 4271.4709 | Q27: 24.13014 | R27: 41.685927 | S27: 19.213333 | T27: 26.27628 | U27: 15.464161 | V27: ='VATtax et trade tax et ipc '!AI27 -> 5.947078 | W27: 11.65696 | X27: ='VATtax et trade tax et ipc '!AM27 -> 12.011415 | Y27: 16.765796 | Z27: 26.977627 | AA27: 0 | AB27: 0 | AC27: 39.280682
A28: Brazil | B28: =Tx_croissance!AH28 -> 1.1274772 | C28: =IFERROR(LN(P28),"NA") -> 8.7833225 | D28: 18.155147 | E28: 1.0386144 | F28: 0.4347906 | G28: 72.110111 | H28: -0.22298419 | I28: 114.16318 | J28: 102.71184 | K28: 41.292828 | L28: -0.18316958 | M28: 0.037600805 | N28: -0.22986735 | O28: 0.41737558 | P28: 6524.5189 | Q28: 13.975226 | R28: 51.190242 | S28: 22.342857 | T28: 25.028306 | U28: 74.247132 | V28: ='VATtax et trade tax et ipc '!AI28 -> 9.4143723 | W28: 0.99148007 | X28: ='VATtax et trade tax et ipc '!AM28 -> 11.983306 | Z28: 20.286298 | AA28: 0 | AB28: 0 | AC28: 4.3004342
A29: British Virgin Islands | B29: =Tx_croissance!AH29 -> NA | C29: =IFERROR(LN(P29),"NA") -> NA | D29: NA | E29: 2.1274138 | F29: -0.220761 | G29: 74.936481 | H29: NA | I29: 99.755564 | J29: 107.51422 | K29: 55.078339 | L29: NA | M29: NA | N29: NA | O29: NA | P29: NA | Q29: NA | R29: #DIV/0! | S29: #DIV/0! | T29: #DIV/0! | U29: NA | V29: ='VATtax et trade tax et ipc '!AI29 -> NA | W29: NA | X29: ='VATtax et trade tax et ipc '!AM29 -> NA | AA29: 0 | AB29: 0 | AC29: NA
A30: Brunei Darussalam | B30: =Tx_croissance!AH30 -> -0.75369466 | C30: =IFERROR(LN(P30),"NA") -> 10.477734 | D30: 26.477194 | E30: 1.5374863 | F30: 0.96167488 | G30: 74.443963 | H30: 1.1823548 | I30: 102.4183 | J30: 87.681696 | K30: 20.312394 | L30: 0.60866668 | M30: 0.95820407 | N30: 0.58958852 | O30: -0.79594648 | P30: 35515.843 | Q30: NA | R30: #DIV/0! | S30: 11.507143 | T30: #DIV/0! | U30: NA | V30: ='VATtax et trade tax et ipc '!AI30 -> NA | W30: NA | X30: ='VATtax et trade tax et ipc '!AM30 -> NA | Z30: 36.661699 | AA30: 0 | AB30: 0 | AC30: NA
A31: Bulgaria | B31: =Tx_croissance!AH31 -> 3.2515765 | C31: =IFERROR(LN(P31),"NA") -> 8.3004406 | D31: 19.762658 | E31: -0.95353456 | F31: -0.021032884 | G31: 72.952647 | H31: 0.28493553 | I31: 94.839586 | J31: 62.908112 | K31: 10.062492 | L31: -0.21097233 | M31: 0.52859139 | N31: -0.12190507 | O31: 0.45300526 | P31: 4025.6458 | Q31: 19.401704 | R31: 28.876291 | S31: 5.1933333 | T31: 15.908964 | U31: 35.144067 | V31: ='VATtax et trade tax et ipc '!AI31 -> 13.424183 | W31: 0.18066 | X31: ='VATtax et trade tax et ipc '!AM31 -> 5.219091 | Y31: 11.156664 | Z31: 16.668561 | AA31: 0 | AB31: 0 | AC31: 2.9037661
A32: Burkina Faso | B32: =Tx_croissance!AH32 -> 2.7088643 | C32: =IFERROR(LN(P32),"NA") -> 5.8748969 | D32: 18.681561 | E32: 2.891211 | F32: -0.71028564 | G32: 54.921556 | H32: -0.52705767 | I32: 102.91694 | J32: 73.603632 | K32: 15.048078 | L32: -0.19425634 | M32: -0.32293118 | N32: -0.51396338 | O32: -0.27706748 | P32: 355.98794 | Q32: 12.702878 | R32: 26.265196 | S32: 16.62 | T32: 18.570685 | U32: 55.43971 | V32: ='VATtax et trade tax et ipc '!AI32 -> 8.5054231 | W32: 2.460246 | X32: ='VATtax et trade tax et ipc '!AM32 -> 4.3564671 | Z32: 22.479807 | AA32: 0 | AB32: 1 | AC32: 15.793083
A33: Burundi | B33: =Tx_croissance!AH33 -> -1.1070687 | C33: =IFERROR(LN(P33),"NA") -> 5.8696251 | D33: 11.193935 | E33: 2.9860086 | F33: -1.3055631 | G33: 54.540593 | H33: -1.7116444 | I33: 72.826495 | J33: 13.562921 | K33: 2.1412545 | L33: -1.1802308 | M33: -1.0978512 | N33: -1.2744365 | O33: -1.1844699 | P33: 354.11618 | Q33: NA | R33: 24.565344 | S33: 25.62 | T33: 17.219889 | U33: 144.22053 | V33: ='VATtax et trade tax et ipc '!AI33 -> 0.82351818 | W33: 0.44399098 | X33: ='VATtax et trade tax et ipc '!AM33 -> 0.41593262 | Y33: 16.678207 | Z33: 6.4429994 | AA33: 0 | AB33: 1 | AC33: 18.121549
A34: Cabo Verde | B34: =Tx_croissance!AH34 -> 3.8240248 | C34: =IFERROR(LN(P34),"NA") -> 7.1457307 | D34: NA | E34: 1.392329 | F34: 0.015781369 | G34: 72.108037 | H34: 0.86119937 | I34: 99.134542 | J34: 106.40359 | K34: 68.096208 | L34: 0.85061409 | M34: -0.14638214 | N34: 0.49301043 | O34: 0.86588946 | P34: 1268.678 | Q34: 17.988903 | R34: 30.578555 | S34: 19.373333 | T34: 18.595747 | U34: NA | V34: ='VATtax et trade tax et ipc '!AI34 -> 10.288915 | W34: 4.1933458 | X34: ='VATtax et trade tax et ipc '!AM34 -> 6.3904353 | AA34: 0 | AB34: 1 | AC34: 19.578392
A35: Cambodia | B35: =Tx_croissance!AH35 -> 5.1987922 | C35: =IFERROR(LN(P35),"NA") -> 5.9373314 | D35: 18.689547 | E35: 1.6256615 | F35: -0.78932999 | G35: 64.998222 | H35: -0.32878124 | I35: 102.53375 | J35: 98.211111 | K35: 50.570209 | L35: -1.1679486 | M35: -0.4676546 | N35: -1.0834278 | O35: -1.0185148 | P35: 378.92238 | Q35: 12.198874 | R35: 19.10624 | S35: 19.32 | T35: 13.93106 | U35: NA | V35: ='VATtax et trade tax et ipc '!AI35 -> 9.8419962 | W35: 2.995123 | X35: ='VATtax et trade tax et ipc '!AM35 -> 3.9723906 | Z35: 13.916833 | AA35: 0 | AB35: 1 | AC35: 20.012259
A36: Cameroon | B36: =Tx_croissance!AH36 -> 1.1824101 | C36: =IFERROR(LN(P36),"NA") -> 6.956266 | D36: 18.571178 | E36: 2.771044 | F36: -0.88050299 | G36: 56.344259 | H36: -0.81236008 | I36: NA | J36: NA | K36: NA | L36: -1.1602667 | M36: -0.8756812 | N36: -1.1248985 | O36: -1.0582847 | P36: 1049.7067 | Q36: 10.269042 | R36: 29.234389 | S36: 31.766667 | T36: 22.38712 | U36: 90.182967 | V36: ='VATtax et trade tax et ipc '!AI36 -> 6.8490888 | W36: 2.322554 | X36: ='VATtax et trade tax et ipc '!AM36 -> 4.1975948 | Y36: 7.183669 | Z36: 17.333571 | AA36: 0 | AB36: 1 | AC36: 17.959751
A37: Canada | B37: =Tx_croissance!AH37 -> 1.1936863 | C37: =IFERROR(LN(P37),"NA") -> 10.392443 | D37: 22.067825 | E37: 1.0515855 | F37: 1.7686003 | G37: 80.547309 | H37: 1.050072 | I37: 101.98573 | J37: 94.32557 | K37: 61.490332 | L37: 1.8909337 | M37: 1.6459304 | N37: 1.7256276 | O37: 1.4662967 | P37: 32612.232 | Q37: 13.205866 | R37: 76.329888 | S37: 10.906667 | T37: 53.395992 | U37: 57.577369 | V37: ='VATtax et trade tax et ipc '!AI37 -> 2.7428267 | W37: 0.24116831 | X37: ='VATtax et trade tax et ipc '!AM37 -> 9.9209642 | Y37: 13.287062 | Z37: 18.3473 | AA37: 0 | AB37: 0 | AC37: NA
A38: Cayman Islands | B38: =Tx_croissance!AH38 -> NA | C38: =IFERROR(LN(P38),"NA") -> NA | D38: NA | E38: 2.7944841 | F38: 1.3340247 | G38: 82.190244 | H38: 1.116959 | I38: 103.89109 | J38: 77.333903 | K38: 29.060357 | L38: 0.9968462 | M38: 1.1143373 | N38: 0.97377473 | O38: 0.79565808 | P38: NA | Q38: NA | R38: #DIV/0! | S38: #DIV/0! | T38: #DIV/0! | U38: NA | V38: ='VATtax et trade tax et ipc '!AI38 -> NA | W38: NA | X38: ='VATtax et trade tax et ipc '!AM38 -> NA | AA38: 0 | AB38: 0 | AC38: NA
A39: Central African Republic | B39: =Tx_croissance!AH39 -> -0.99971073 | C39: =IFERROR(LN(P39),"NA") -> 6.1703299 | D39: 12.95163 | E39: 1.9988948 | F39: -1.5470561 | G39: 49.143667 | H39: -1.8363351 | I39: 78.425447 | J39: 46.217832 | K39: 7.670532 | L39: -1.1691322 | M39: -1.2455818 | N39: -1.5203608 | O39: -1.1112256 | P39: 478.34389 | Q39: 7.4168613 | R39: 22.577926 | S39: 0 | T39: 11.379809 | U39: NA | V39: ='VATtax et trade tax et ipc '!AI39 -> 5.1847997 | W39: 2.7669079 | X39: ='VATtax et trade tax et ipc '!AM39 -> 2.3348734 | Z39: 13.053912 | AA39: 0 | AB39: 1 | AC39: 25.002107
A40: Chad | B40: =Tx_croissance!AH40 -> 1.4518322 | C40: =IFERROR(LN(P40),"NA") -> 5.9914633 | D40: 25.112545 | E40: 3.5316887 | F40: -1.3283807 | G40: 49.56537 | H40: -1.4087013 | I40: 102.10665 | J40: 39.452959 | K40: 9.6269121 | L40: -1.4089354 | M40: -1.1191018 | N40: -1.3720946 | O40: -1.3026839 | P40: 399.99949 | Q40: NA | R40: #DIV/0! | S40: 31.3 | T40: #DIV/0! | U40: NA | V40: ='VATtax et trade tax et ipc '!AI40 -> NA | W40: NA | X40: ='VATtax et trade tax et ipc '!AM40 -> NA | Z40: 14.357197 | AA40: 0 | AB40: 1 | AC40: NA
A41: Channel Islands | B41: =Tx_croissance!AH41 -> NA | C41: =IFERROR(LN(P41),"NA") -> NA | D41: NA | E41: 0.71573516 | F41: 1.0032518 | G41: 80.382519 | H41: NA | I41: 93.56225 | J41: 39.913814 | K41: 5.3561082 | L41: NA | M41: NA | N41: NA | O41: NA | Q41: NA | R41: #DIV/0! | S41: #DIV/0! | T41: #DIV/0! | U41: NA | V41: ='VATtax et trade tax et ipc '!AI41 -> NA | W41: NA | X41: ='VATtax et trade tax et ipc '!AM41 -> NA | AA41: 0 | AB41: 0 | AC41: NA
A42: Chile | B42: =Tx_croissance!AH42 -> 2.548012 | C42: =IFERROR(LN(P42),"NA") -> 8.8925512 | D42: 24.151439 | E42: 1.1490237 | F42: 0.16483272 | G42: 78.096704 | H42: 0.45257032 | I42: 100.21441 | J42: 43.993693 | K42: 6.9048595 | L42: 1.2765119 | M42: 1.3410719 | N42: 1.1240322 | O42: 1.0187498 | P42: 7277.5619 | Q42: 17.267806 | R42: 34.623007 | S42: 20.926667 | T42: 27.744198 | U42: 13.879093 | V42: ='VATtax et trade tax et ipc '!AI42 -> 9.4472125 | W42: 0.34229696 | X42: ='VATtax et trade tax et ipc '!AM42 -> 6.3054997 | Y42: 15.100754 | Z42: 25.750479 | AA42: 0 | AB42: 0 | AC42: 2.174154
A43: China | B43: =Tx_croissance!AH43 -> 7.8037544 | C43: =IFERROR(LN(P43),"NA") -> 7.326485 | D43: 39.149926 | E43: 0.60584619 | F43: -0.14735298 | G43: 74.66763 | H43: -0.44223798 | I43: 118.87128 | J43: 90.810651 | K43: 39.58527 | L43: -0.36800981 | M43: -0.30139017 | N43: -0.41876498 | O43: -1.585438 | P43: 1520.0295 | Q43: 9.3939525 | R43: 31.816323 | S43: 10.328571 | T43: 22.364507 | U43: NA | V43: ='VATtax et trade tax et ipc '!AI43 -> 7.8198475 | W43: 0.46575801 | X43: ='VATtax et trade tax et ipc '!AM43 -> 4.1425574 | Z43: 32.340969 | AA43: 0 | AB43: 0 | AC43: 4.5444463
A44: Colombia | B44: =Tx_croissance!AH44 -> 1.8507405 | C44: =IFERROR(LN(P44),"NA") -> 8.3357811 | D44: 20.241807 | E44: 1.3752278 | F44: -1.5955256 | G44: 73.696704 | H44: -1.4401395 | I44: 101.31864 | J44: 48.692416 | K44: 5.6211945 | L44: -0.33412937 | M44: 0.16580784 | N44: -0.47267379 | O44: -0.11648015 | P44: 4170.4577 | Q44: 13.866987 | R44: 38.714822 | S44: 19.96 | T44: 21.832053 | U44: 58.838247 | V44: ='VATtax et trade tax et ipc '!AI44 -> 9.2435084 | W44: 0.72767808 | X44: ='VATtax et trade tax et ipc '!AM44 -> 7.4433927 | Z44: 22.396165 | AA44: 0 | AB44: 0 | AC44: 4.939355
A45: Comoros | B45: =Tx_croissance!AH45 -> 0.67923634 | C45: =IFERROR(LN(P45),"NA") -> 7.0345068 | D45: 15.834981 | E45: 2.0337449 | F45: -1.655485 | G45: 60.854037 | H45: -0.27499165 | I45: 108.02459 | J45: 79.114567 | K45: 12.535652 | L45: -0.857356 | M45: -1.2677857 | N45: -1.0391197 | O45: -0.48531915 | P45: 1135.1349 | Q45: NA | R45: #DIV/0! | S45: 31.5 | T45: #DIV/0! | U45: NA | V45: ='VATtax et trade tax et ipc '!AI45 -> NA | W45: NA | X45: ='VATtax et trade tax et ipc '!AM45 -> NA | Z45: 17.116421 | AA45: 0 | AB45: 1 | AC45: NA
A46: Congo, Dem. Rep. | B46: =Tx_croissance!AH46 -> 0.46729697 | C46: =IFERROR(LN(P46),"NA") -> 6.1447129 | D46: 15.714788 | E46: 3.1044315 | F46: -1.2024508 | G46: 55.174519 | H46: -2.1516318 | I46: 109.68691 | J46: 93.568459 | K46: 48.267352 | L46: -1.4495876 | M46: -1.5190175 | N46: -1.6963502 | O46: -1.4343621 | P46: 466.24576 | Q46: 8.2127363 | R46: #DIV/0! | S46: 44.38 | T46: #DIV/0! | U46: 209.57291 | V46: ='VATtax et trade tax et ipc '!AI46 -> NA | W46: NA | X46: ='VATtax et trade tax et ipc '!AM46 -> NA | Z46: 9.6536063 | AA46: 0 | AB46: 1 | AC46: NA
A47: Congo, Rep. | B47: =Tx_croissance!AH47 -> -0.76685751 | C47: =IFERROR(LN(P47),"NA") -> 7.648743 | D47: 34.97185 | E47: 2.875113 | F47: -0.32221309 | G47: 58.835074 | H47: -0.67157251 | I47: 102.23934 | J47: 92.254179 | K47: 49.526065 | L47: -1.1947403 | M47: -1.2518737 | N47: -1.2059673 | O47: -1.1353801 | P47: 2098.0068 | Q47: 8.1402567 | R47: 36.13854 | S47: 1.2333333 | T47: 9.5538659 | U47: 42.854813 | V47: ='VATtax et trade tax et ipc '!AI47 -> 4.0723337 | W47: 1.6156457 | X47: ='VATtax et trade tax et ipc '!AM47 -> 3.858738 | Z47: 34.300346 | AA47: 0 | AB47: 1 | AC47: 17.729974
A48: Costa Rica | B48: =Tx_croissance!AH48 -> 2.5135083 | C48: =IFERROR(LN(P48),"NA") -> 8.8345755 | D48: 19.484288 | E48: 1.4118084 | F48: 0.27578656 | G48: 78.340222 | H48: 0.67705354 | I48: 148.0991 | J48: 107.88845 | K48: 19.283002 | L48: 0.56095784 | M48: 0.573025 | N48: 0.50043687 | O48: 1.0532039 | P48: 6867.6377 | Q48: 13.070253 | R48: 26.191495 | S48: 19.22 | T48: 14.900219 | U48: 36.404018 | V48: ='VATtax et trade tax et ipc '!AI48 -> 7.5611045 | W48: 1.1445494 | X48: ='VATtax et trade tax et ipc '!AM48 -> 3.6775853 | Y48: 12.245038 | Z48: 19.791517 | AA48: 0 | AB48: 0 | AC48: 6.5183947
A49: Cote d'Ivoire | B49: =Tx_croissance!AH49 -> 1.3080167 | C49: =IFERROR(LN(P49),"NA") -> 7.4448981 | D49: 18.682953 | E49: 2.5467415 | F49: -0.8863061 | G49: 54.350074 | H49: -1.2378577 | I49: 101.50555 | J49: 93.930294 | K49: 31.052102 | L49: -0.77235409 | M49: -0.6173169 | N49: -1.0136226 | O49: -0.77897928 | P49: 1711.1109 | Q49: 11.284122 | R49: 24.00189 | S49: 9.2266667 | T49: 21.06863 | U49: 171.06544 | V49: ='VATtax et trade tax et ipc '!AI49 -> 3.8336937 | W49: 4.3561805 | X49: ='VATtax et trade tax et ipc '!AM49 -> 2.8785341 | Y49: 18.819075 | Z49: 13.686123 | AA49: 0 | AB49: 1 | AC49: 25.830103
A50: Croatia | B50: =Tx_croissance!AH50 -> 3.0887278 | C50: =IFERROR(LN(P50),"NA") -> 8.896443 | D50: 21.456078 | E50: -0.6706277 | F50: 0.46999867 | G50: 75.610831 | H50: 0.55476515 | I50: 99.534515 | J50: 96.522404 | K50: 51.422263 | L50: 0.035110513 | M50: 0.33765799 | N50: 0.081630565 | O50: 0.46350858 | P50: 7305.9398 | Q50: 20.832934 | R50: 14.524366 | S50: 0 | T50: 7.6764105 | U50: 64.935983 | V50: ='VATtax et trade tax et ipc '!AI50 -> 16.609942 | W50: 0.67552121 | X50: ='VATtax et trade tax et ipc '!AM50 -> 2.8075053 | Y50: 22.624935 | Z50: 14.270808 | AA50: 0 | AB50: 0 | AC50: 4.8252169
A51: Cuba | B51: =Tx_croissance!AH51 -> 3.0060211 | C51: =IFERROR(LN(P51),"NA") -> 8.1162608 | D51: 9.7640578 | E51: 0.10504728 | F51: -0.32861936 | G51: 76.810889 | H51: 0.42467795 | I51: 101.7262 | J51: 97.732342 | K51: 50.902378 | L51: 0.18608777 | M51: -1.4367847 | N51: -0.74579874 | O51: -1.601457 | P51: 3348.4766 | Q51: NA | R51: #DIV/0! | S51: #DIV/0! | T51: #DIV/0! | U51: NA | V51: ='VATtax et trade tax et ipc '!AI51 -> NA | W51: NA | X51: ='VATtax et trade tax et ipc '!AM51 -> NA | Z51: 7.7540244 | AA51: 0 | AB51: 0 | AC51: NA
A52: Curacao | B52: =Tx_croissance!AH52 -> NA | C52: =IFERROR(LN(P52),"NA") -> NA | D52: 27.893034 | E52: 0.13010668 | F52: 1.1519389 | G52: 74.986319 | H52: NA | I52: 103.66583 | J52: 102.06228 | K52: 63.694101 | L52: NA | M52: NA | N52: NA | O52: NA | P52: NA | Q52: NA | R52: #DIV/0! | S52: #DIV/0! | T52: #DIV/0! | U52: NA | V52: ='VATtax et trade tax et ipc '!AI52 -> NA | W52: NA | X52: ='VATtax et trade tax et ipc '!AM52 -> NA | AA52: 0 | AB52: 0 | AC52: NA
A53: Cyprus | B53: =Tx_croissance!AH53 -> 1.6885059 | C53: =IFERROR(LN(P53),"NA") -> 9.8757347 | D53: 20.487527 | E53: 1.4050361 | F53: 0.90859837 | G53: 78.854889 | H53: 0.47913135 | I53: 47.798264 | J53: 29.626817 | K53: 1.8603227 | L53: 0.91918927 | M53: 1.1257742 | N53: 0.93126447 | O53: 1.0111689 | P53: 19452.574 | Q53: 25.646917 | R53: 39.49577 | S53: 8.7833333 | T53: 25.392069 | U53: NA | V53: ='VATtax et trade tax et ipc '!AI53 -> 14.960181 | W53: 0.49656062 | X53: ='VATtax et trade tax et ipc '!AM53 -> 11.159525 | Y53: 31.498138 | Z53: 25.202284 | AA53: 0 | AB53: 0 | AC53: 2.577003
A54: Czechia | B54: =Tx_croissance!AH54 -> 2.2089035 | C54: =IFERROR(LN(P54),"NA") -> 9.3253774 | D54: 28.431805 | E54: 0.11512529 | F54: 1.9949622 | G54: 76.670181 | H54: 0.94670984 | I54: 105.74502 | J54: 105.67304 | K54: NA | L54: 0.44749745 | M54: 1.1313956 | N54: 0.95421066 | O54: 0.97204656 | P54: 11219.15 | Q54: 14.848987 | R54: 34.821609 | S54: 5.6 | T54: 15.823995 | U54: NA | V54: ='VATtax et trade tax et ipc '!AI54 -> 8.9775468 | W54: 0.32758997 | X54: ='VATtax et trade tax et ipc '!AM54 -> 4.9918554 | Y54: 16.238177 | Z54: 33.791767 | AA54: 0 | AB54: 0 | AC54: 3.9064034
A55: Denmark | B55: =Tx_croissance!AH55 -> 1.2360883 | C55: =IFERROR(LN(P55),"NA") -> 10.676145 | D55: 20.807552 | E55: 0.44864494 | F55: -0.90152479 | G55: 78.642475 | H55: 1.0694791 | I55: 100.27588 | J55: 125.42091 | K55: 72.282714 | L55: 2.3091208 | M55: 1.7534289 | N55: 1.8998708 | O55: 1.5698435 | P55: 43310.25 | Q55: 31.200162 | R55: 49.441769 | S55: 20.84 | T55: 41.262037 | U55: NA | V55: ='VATtax et trade tax et ipc '!AI55 -> 14.397136 | W55: 0.020085722 | X55: ='VATtax et trade tax et ipc '!AM55 -> 16.243639 | Y55: 31.660832 | Z55: 19.47485 | AA55: 0 | AB55: 0 | AC55: NA
A56: Djibouti | B56: =Tx_croissance!AH56 -> NA | C56: =IFERROR(LN(P56),"NA") -> NA | D56: 28.454183 | E56: 2.0947494 | F56: 0.40929534 | G56: 59.432037 | H56: -0.31838734 | I56: 108.05088 | J56: 73.378682 | K56: 50.165856 | L56: -0.61709194 | M56: -0.74347208 | N56: -0.88744256 | O56: -1.2020427 | P56: NA | Q56: NA | R56: #DIV/0! | S56: 17.7 | T56: #DIV/0! | U56: NA | V56: ='VATtax et trade tax et ipc '!AI56 -> NA | W56: NA | X56: ='VATtax et trade tax et ipc '!AM56 -> NA | AA56: 0 | AB56: 1 | AC56: NA
A57: Dominica | B57: =Tx_croissance!AH57 -> 1.0754385 | C57: =IFERROR(LN(P57),"NA") -> 8.6122345 | D57: #DIV/0! | E57: 0.17813656 | F57: -0.44736436 | G57: 71.468444 | H57: 0.94390525 | I57: 109.11003 | J57: 78.364137 | K57: 32.154689 | L57: 0.70861388 | M57: 0.50996859 | N57: 0.72506797 | O57: 0.96337551 | P57: 5498.5212 | Q57: NA | R57: #DIV/0! | S57: 25.033333 | T57: #DIV/0! | U57: NA | V57: ='VATtax et trade tax et ipc '!AI57 -> NA | W57: NA | X57: ='VATtax et trade tax et ipc '!AM57 -> NA | AA57: 0 | AB57: 0 | AC57: NA
A58: Dominican Republic | B58: =Tx_croissance!AH58 -> 3.6481517 | C58: =IFERROR(LN(P58),"NA") -> 8.1072998 | D58: 24.265603 | E58: 1.3362856 | F58: -0.58510371 | G58: 71.328667 | H58: 0.014918256 | I58: 107.37751 | J58: 81.132175 | K58: 39.267264 | L58: -0.7387363 | M58: -0.12278644 | N58: -0.53806778 | O58: 0.14612332 | P58: 3318.6051 | Q58: 12.043337 | R58: 25.442367 | S58: 24.44 | T58: 22.066066 | U58: 18.31574 | V58: ='VATtax et trade tax et ipc '!AI58 -> 7.1732966 | W58: 1.2330208 | X58: ='VATtax et trade tax et ipc '!AM58 -> 3.5359233 | Y58: 10.574625 | Z58: 17.887759 | AA58: 0 | AB58: 0 | AC58: 16.881373
A59: Ecuador | B59: =Tx_croissance!AH59 -> 0.91279569 | C59: =IFERROR(LN(P59),"NA") -> 8.3834946 | D59: 21.96807 | E59: 1.6479159 | F59: -0.44090902 | G59: 74.508 | H59: -0.47472041 | I59: 93.368002 | J59: 76.212646 | K59: 30.415806 | L59: -0.67541854 | M59: -0.83403023 | N59: -0.80790999 | O59: -0.14760672 | P59: 4374.2687 | Q59: 13.864763 | R59: 29.298167 | S59: 17.546667 | T59: 13.777381 | U59: NA | V59: ='VATtax et trade tax et ipc '!AI59 -> 11.344058 | W59: 3.9043972 | X59: ='VATtax et trade tax et ipc '!AM59 -> 6.5308069 | Z59: 17.332777 | AA59: 0 | AB59: 0 | AC59: 9.8528386
A60: Egypt, Arab Rep. | B60: =Tx_croissance!AH60 -> 2.4574934 | C60: =IFERROR(LN(P60),"NA") -> 7.6605292 | D60: 17.730117 | E60: 2.0352523 | F60: -0.33409228 | G60: 69.248037 | H60: -0.93657244 | I60: 82.167818 | J60: 43.060837 | K60: 2.4875277 | L60: -0.59553921 | M60: -0.48225339 | N60: -0.27321078 | O60: -1.1527549 | P60: 2122.8805 | Q60: 16.734145 | R60: 42.978164 | S60: 14.66 | T60: 24.185943 | U60: 85.788534 | V60: ='VATtax et trade tax et ipc '!AI60 -> 2.781791 | W60: 0.61105856 | X60: ='VATtax et trade tax et ipc '!AM60 -> 3.0492563 | Y60: 17.623039 | Z60: 22.559412 | AA60: 0 | AB60: 1 | AC60: 12.299519
A61: El Salvador | B61: =Tx_croissance!AH61 -> 1.6082502 | C61: =IFERROR(LN(P61),"NA") -> 7.9302238 | D61: 17.08528 | E61: 0.38237677 | F61: -1.1869838 | G61: 70.621556 | H61: -0.035005995 | I61: 103.62418 | J61: 118.67588 | K61: 72.715111 | L61: -0.50819305 | M61: -0.0023381095 | N61: -0.71723534 | O61: 0.038960988 | P61: 2780.049 | Q61: 15.316406 | R61: 34.031949 | S61: 17.673333 | T61: 23.930538 | U61: 51.457213 | V61: ='VATtax et trade tax et ipc '!AI61 -> 9.3995602 | W61: 1.0412718 | X61: ='VATtax et trade tax et ipc '!AM61 -> 5.8650945 | Z61: 19.06244 | AA61: 0 | AB61: 1 | AC61: 6.921411
A62: Equatorial Guinea | B62: =Tx_croissance!AH62 -> 8.6759093 | C62: =IFERROR(LN(P62),"NA") -> 6.4439409 | D62: 29.523013 | E62: 4.0427114 | F62: -1.4157672 | G62: 56.783222 | H62: -0.041000558 | I62: 99.644168 | J62: 105.02829 | K62: 64.098501 | L62: -1.3824276 | M62: -1.5454005 | N62: -1.2063315 | O62: -1.799226 | P62: 628.88025 | Q62: 8.1671311 | R62: 83.282977 | S62: 29.313333 | T62: 28.098451 | U62: NA | V62: ='VATtax et trade tax et ipc '!AI62 -> 1.2428859 | W62: 0.32792287 | X62: ='VATtax et trade tax et ipc '!AM62 -> 10.531205 | AA62: 1 | AB62: 0 | AC62: 2.2639987
A63: Eritrea | B63: =Tx_croissance!AH63 -> NA | C63: =IFERROR(LN(P63),"NA") -> 6.6298368 | D63: 22.735535 | E63: 2.1065473 | F63: 1.0003968 | G63: 61.219222 | H63: -0.79042519 | I63: 77.763464 | J63: 25.114743 | K63: 4.6314978 | L63: -0.6144971 | M63: -1.9223328 | N63: -1.2769998 | O63: -2.0053498 | P63: 757.35852 | Q63: NA | R63: #DIV/0! | S63: 8.9133333 | T63: #DIV/0! | U63: NA | V63: ='VATtax et trade tax et ipc '!AI63 -> NA | W63: NA | X63: ='VATtax et trade tax et ipc '!AM63 -> NA | Z63: 22.536696 | AA63: 0 | AB63: 1 | AC63: NA
A64: Estonia | B64: =Tx_croissance!AH64 -> 4.1040386 | C64: =IFERROR(LN(P64),"NA") -> 8.8731222 | D64: 28.255587 | E64: -0.2889711 | F64: -0.59565084 | G64: 73.910253 | H64: 0.69658133 | I64: 99.710039 | J64: 126.94173 | K64: 88.13377 | L64: 1.1015892 | M64: 1.4187434 | N64: 1.0843323 | O64: 1.110768 | P64: 7137.5308 | Q64: 20.631679 | R64: 37.67078 | S64: 8.58 | T64: 21.582107 | U64: 9.8158812 | V64: ='VATtax et trade tax et ipc '!AI64 -> 12.48258 | W64: 0.0085888398 | X64: ='VATtax et trade tax et ipc '!AM64 -> 7.1400819 | Y64: 22.839017 | Z64: 26.50461 | AA64: 0 | AB64: 0 | AC64: 0.095370707
A65: Eswatini | B65: =Tx_croissance!AH65 -> 2.1419387 | C65: =IFERROR(LN(P65),"NA") -> 7.7250662 | D65: 15.681986 | E65: 0.82528422 | F65: -0.73807247 | G65: 50.293 | H65: -0.21351668 | I65: 100.21374 | J65: 81.683897 | K65: 23.522345 | L65: -0.18138266 | M65: -0.37513071 | N65: -0.5411738 | O65: -1.353334 | P65: 2264.4025 | Q65: NA | R65: #DIV/0! | S65: 27.166667 | T65: #DIV/0! | U65: NA | V65: ='VATtax et trade tax et ipc '!AI65 -> NA | W65: NA | X65: ='VATtax et trade tax et ipc '!AM65 -> NA | Z65: 15.416124 | AA65: 0 | AB65: 1 | AC65: NA
A66: Ethiopia | B66: =Tx_croissance!AH66 -> 4.7996644 | C66: =IFERROR(LN(P66),"NA") -> 5.4880356 | D66: 34.306804 | E66: 2.8454349 | F66: -0.19123877 | G66: 57.358667 | H66: -1.4995537 | I66: 103.16721 | J66: 105.87896 | K66: 57.225261 | L66: -0.62644812 | M66: -1.0535743 | N66: -0.69931825 | O66: -1.2083181 | P66: 241.78179 | Q66: 8.3288776 | R66: 26.830445 | S66: 25.726667 | T66: 17.616707 | U66: 48.034526 | V66: ='VATtax et trade tax et ipc '!AI66 -> 2.1040664 | W66: 1.7302257 | X66: ='VATtax et trade tax et ipc '!AM66 -> 1.5365523 | Y66: 8.4295215 | AA66: 0 | AB66: 1 | AC66: 36.989643
A67: Faroe Islands | B67: =Tx_croissance!AH67 -> NA | C67: =IFERROR(LN(P67),"NA") -> NA | D67: NA | E67: 0.66009323 | F67: 2.0322501 | G67: 80.243631 | H67: NA | I67: NA | J67: NA | K67: NA | L67: NA | M67: NA | N67: NA | O67: NA | P67: NA | Q67: NA | R67: #DIV/0! | S67: #DIV/0! | T67: #DIV/0! | U67: NA | V67: ='VATtax et trade tax et ipc '!AI67 -> NA | W67: NA | X67: ='VATtax et trade tax et ipc '!AM67 -> NA | AA67: 0 | AB67: 0 | AC67: NA
A68: Fiji | B68: =Tx_croissance!AH68 -> 1.2628377 | C68: =IFERROR(LN(P68),"NA") -> 8.2390861 | D68: 19.650594 | E68: 0.57815735 | F68: 1.445647 | G68: 66.953444 | H68: 0.3903347 | I68: 98.398497 | J68: 86.345623 | K68: NA | L68: 0.33546736 | M68: -0.28374308 | N68: -0.16318604 | O68: -0.27599282 | P68: 3786.0786 | Q68: 22.050249 | R68: 31.89293 | S68: 25.353333 | T68: 27.810763 | U68: NA | V68: ='VATtax et trade tax et ipc '!AI68 -> 11.9188 | W68: 5.4103898 | X68: ='VATtax et trade tax et ipc '!AM68 -> 7.5930787 | Y68: 22.206142 | Z68: 14.191715 | AA68: 0 | AB68: 0 | AC68: 17.824778
A69: Finland | B69: =Tx_croissance!AH69 -> 1.6819478 | C69: =IFERROR(LN(P69),"NA") -> 10.306045 | D69: 22.616007 | E69: 0.31409725 | F69: 1.0381168 | G69: 79.512195 | H69: 1.3199659 | I69: NA | J69: 48.596689 | K69: 10.353533 | L69: 2.2534375 | M69: 1.7731424 | N69: 1.9727722 | O69: 1.5572778 | P69: 29912.898 | Q69: 21.99518 | R69: 32.622648 | S69: 14.653333 | T69: 18.049381 | U69: NA | V69: ='VATtax et trade tax et ipc '!AI69 -> 13.677888 | W69: 0.0022031661 | X69: ='VATtax et trade tax et ipc '!AM69 -> 6.5911387 | Y69: 20.702392 | Z69: 19.278734 | AA69: 0 | AB69: 0 | AC69: 0.020862846
A70: France | B70: =Tx_croissance!AH70 -> 0.99072552 | C70: =IFERROR(LN(P70),"NA") -> 10.300421 | D70: 21.985984 | E70: 0.4857548 | F70: -0.74452242 | G70: 80.777778 | H70: 0.43774331 | I70: 102.23154 | J70: 106.5197 | K70: 59.605974 | L70: 1.3294836 | M70: 1.1579756 | N70: 1.3902328 | O70: 1.2115316 | P70: 29745.129 | Q70: 20.924243 | R70: 46.371919 | S70: 4.3733333 | T70: 24.423645 | U70: 81.098107 | V70: ='VATtax et trade tax et ipc '!AI70 -> 10.017845 | W70: -0.0024789065 | X70: ='VATtax et trade tax et ipc '!AM70 -> 10.592644 | Y70: 19.463207 | Z70: 20.074072 | AA70: 0 | AB70: 0 | AC70: -0.0091773942
A71: French Polynesia | B71: =Tx_croissance!AH71 -> -0.49667181 | C71: =IFERROR(LN(P71),"NA") -> 10.000357 | D71: 21.363173 | E71: 1.0590948 | F71: -0.69177871 | G71: 80.385259 | H71: NA | I71: 102.33267 | J71: 96.808918 | K71: 49.050262 | L71: NA | M71: NA | N71: NA | O71: NA | P71: 22034.328 | Q71: NA | R71: #DIV/0! | S71: #DIV/0! | T71: #DIV/0! | U71: NA | V71: ='VATtax et trade tax et ipc '!AI71 -> NA | W71: NA | X71: ='VATtax et trade tax et ipc '!AM71 -> NA | AA71: 0 | AB71: 0 | AC71: NA
A72: Gabon | B72: =Tx_croissance!AH72 -> -0.92262439 | C72: =IFERROR(LN(P72),"NA") -> 9.0506902 | D72: 25.053418 | E72: 2.7906659 | F72: 0.16349906 | G72: 63.299519 | H72: 0.17963687 | I72: 90.08746 | J72: 50.975727 | K72: 13.060013 | L72: -0.84980754 | M72: -0.45658322 | N72: -0.55036713 | O72: -0.81904158 | P72: 8524.4192 | Q72: 12.787819 | R72: 43.236028 | S72: 19 | T72: 25.407508 | U72: NA | V72: ='VATtax et trade tax et ipc '!AI72 -> 3.4388341 | W72: 4.9747319 | X72: ='VATtax et trade tax et ipc '!AM72 -> 7.5982255 | Z72: 22.676955 | AA72: 0 | AB72: 0 | AC72: NA
A73: Gambia, The | B73: =Tx_croissance!AH73 -> 0.33079111 | C73: =IFERROR(LN(P73),"NA") -> 6.4305145 | D73: 15.067814 | E73: 2.8866333 | F73: 1.5525249 | G73: 59.767148 | H73: 0.13681671 | I73: 126.64258 | J73: 114.57733 | K73: NA | L73: -0.53877541 | M73: -0.55705204 | N73: -0.40955681 | O73: -0.8345459 | P73: 620.49308 | Q73: NA | R73: #DIV/0! | S73: 7.32 | T73: #DIV/0! | U73: NA | V73: ='VATtax et trade tax et ipc '!AI73 -> NA | W73: NA | X73: ='VATtax et trade tax et ipc '!AM73 -> NA | Z73: 6.9037034 | AA73: 0 | AB73: 1 | AC73: NA
A74: Georgia | B74: =Tx_croissance!AH74 -> 6.3452211 | C74: =IFERROR(LN(P74),"NA") -> 6.9402264 | D74: 22.692401 | E74: -0.94427716 | F74: -0.15913847 | G74: 71.375815 | H74: -0.74428282 | I74: 79.540316 | J74: 30.705296 | K74: 6.7434458 | L74: 0.036486576 | M74: 0.31753404 | N74: -0.26453999 | O74: -0.049925862 | P74: 1033.0041 | Q74: 18.01439 | R74: 34.258639 | S74: 12.96 | T74: 27.089519 | U74: 41.564241 | V74: ='VATtax et trade tax et ipc '!AI74 -> 12.529337 | W74: 0.31263581 | X74: ='VATtax et trade tax et ipc '!AM74 -> 8.2897838 | Y74: 5.414843 | Z74: 4.0329027 | AA74: 0 | AB74: 1 | AC74: 3.9153152
A75: Germany | B75: =Tx_croissance!AH75 -> 1.1754347 | C75: =IFERROR(LN(P75),"NA") -> 10.361803 | D75: 20.907196 | E75: 0.10200962 | F75: 0.48878065 | G75: 79.384589 | H75: 0.84488096 | I75: 76.365644 | J75: 47.910783 | K75: 1.80151 | L75: 1.819941 | M75: 1.5723677 | N75: 1.6427566 | O75: 1.3841685 | P75: 31628.16 | Q75: 10.859416 | R75: 42.069456 | S75: 22.06 | T75: 16.181487 | U75: NA | V75: ='VATtax et trade tax et ipc '!AI75 -> 6.3613953 | W75: NA | X75: ='VATtax et trade tax et ipc '!AM75 -> 4.6653677 | Y75: 11.476135 | Z75: 23.53904 | AA75: 0 | AB75: 0 | AC75: NA
A76: Ghana | B76: =Tx_croissance!AH76 -> 2.9311798 | C76: =IFERROR(LN(P76),"NA") -> 6.8364531 | D76: 20.641248 | E76: 2.4114687 | F76: 0.8732969 | G76: 60.705111 | H76: -0.011870024 | I76: NA | J76: NA | K76: 2.346855 | L76: -0.15635264 | M76: -0.14210584 | N76: -0.023500415 | O76: 0.36027119 | P76: 931.18043 | Q76: 13.880277 | R76: 37.937576 | S76: 18.046667 | T76: 28.236562 | U76: NA | V76: ='VATtax et trade tax et ipc '!AI76 -> 4.7763616 | W76: 1.9223913 | X76: ='VATtax et trade tax et ipc '!AM76 -> 5.2634084 | Z76: 21.130849 | AA76: 0 | AB76: 1 | AC76: 18.134927
A77: Gibraltar | B77: =Tx_croissance!AH77 -> NA | C77: =IFERROR(LN(P77),"NA") -> NA | D77: NA | E77: 0.64138244 | F77: 0.23098738 | G77: 80.75763 | H77: NA | I77: 65.889502 | J77: NA | K77: 4.4648415 | L77: NA | M77: NA | N77: NA | O77: NA | P77: NA | Q77: NA | R77: #DIV/0! | S77: #DIV/0! | T77: #DIV/0! | U77: NA | V77: ='VATtax et trade tax et ipc '!AI77 -> NA | W77: NA | X77: ='VATtax et trade tax et ipc '!AM77 -> NA | AA77: 0 | AB77: 0 | AC77: NA
A78: Greece | B78: =Tx_croissance!AH78 -> 0.89569373 | C78: =IFERROR(LN(P78),"NA") -> 9.6770106 | D78: 18.045836 | E78: -0.029336927 | F78: 0.25520895 | G78: 79.752213 | H78: 0.2120385 | I78: 99.990347 | J78: 101.49036 | K78: 92.304361 | L78: 0.14105122 | M78: 0.61488925 | N78: 0.54491671 | O78: 0.89586102 | P78: 15946.755 | Q78: 18.842004 | R78: 35.065953 | S78: 17.54 | T78: 18.763887 | U78: 155.28242 | V78: ='VATtax et trade tax et ipc '!AI78 -> 13.096301 | W78: 0.004852945 | X78: ='VATtax et trade tax et ipc '!AM78 -> 7.7698136 | Y78: 18.580841 | Z78: 19.957069 | AA78: 0 | AB78: 0 | AC78: 0.024105719
A79: Greenland | B79: =Tx_croissance!AH79 -> NA | C79: =IFERROR(LN(P79),"NA") -> 10.181745 | D79: 30.682903 | E79: 0.073939724 | F79: -0.68765001 | G79: 69.251834 | H79: 1.8508105 | I79: 104.8579 | J79: 105.83005 | K79: 86.549924 | L79: 1.1431822 | M79: 1.3415428 | N79: 1.7039508 | O79: 1.2764135 | P79: 26416.517 | Q79: NA | R79: #DIV/0! | S79: #DIV/0! | T79: #DIV/0! | U79: NA | V79: ='VATtax et trade tax et ipc '!AI79 -> NA | W79: NA | X79: ='VATtax et trade tax et ipc '!AM79 -> NA | AA79: 0 | AB79: 0 | AC79: NA
A80: Grenada | B80: =Tx_croissance!AH80 -> 2.0547903 | C80: =IFERROR(LN(P80),"NA") -> 8.5205907 | D80: NA | E80: 0.69783832 | F80: -1.0567448 | G80: 73.981407 | H80: 0.74639604 | I80: NA | J80: #DIV/0! | K80: NA | L80: 0.56273271 | M80: 0.24337385 | N80: 0.28669531 | O80: 0.73017115 | P80: 5017.0166 | Q80: NA | R80: #DIV/0! | S80: 27.366667 | T80: #DIV/0! | U80: NA | V80: ='VATtax et trade tax et ipc '!AI80 -> NA | W80: NA | X80: ='VATtax et trade tax et ipc '!AM80 -> NA | AA80: 0 | AB80: 0 | AC80: NA
A81: Guam | B81: =Tx_croissance!AH81 -> NA | C81: =IFERROR(LN(P81),"NA") -> NA | D81: NA | E81: 0.535817 | F81: -1.3404591 | G81: 76.117407 | H81: 0.69201342 | I81: 104.13896 | J81: 43.3335 | K81: 16.7692 | L81: 0.96791237 | M81: 0.45352506 | N81: 1.1569212 | O81: 0.89764647 | P81: NA | Q81: NA | R81: #DIV/0! | S81: #DIV/0! | T81: #DIV/0! | U81: NA | V81: ='VATtax et trade tax et ipc '!AI81 -> NA | W81: NA | X81: ='VATtax et trade tax et ipc '!AM81 -> NA | AA81: 0 | AB81: 0 | AC81: NA
A82: Guatemala | B82: =Tx_croissance!AH82 -> 1.5595124 | C82: =IFERROR(LN(P82),"NA") -> 7.9949311 | D82: 16.218015 | E82: 1.9561309 | F82: -0.20936456 | G82: 69.648222 | H82: -0.68649309 | I82: NA | J82: NA | K82: NA | L82: -0.78526526 | M82: -0.28400344 | N82: -1.0538754 | O82: -0.31990631 | P82: 2965.886 | Q82: 10.143023 | R82: 29.724293 | S82: 24.126667 | T82: 27.525875 | U82: 19.303343 | V82: ='VATtax et trade tax et ipc '!AI82 -> 6.093166 | W82: 0.73815269 | X82: ='VATtax et trade tax et ipc '!AM82 -> 3.3392862 | Y82: 7.7147312 | Z82: 14.514737 | AA82: 0 | AB82: 1 | AC82: 9.3026845
A83: Guinea | B83: =Tx_croissance!AH83 -> 2.0695234 | C83: =IFERROR(LN(P83),"NA") -> 6.3491088 | D83: 21.111725 | E83: 2.3081741 | F83: -1.6829757 | G83: 55.562444 | H83: -1.1997753 | I83: 96.715202 | J83: 91.148396 | K83: 10.433304 | L83: -1.037583 | M83: -0.98261785 | N83: -1.3315533 | O83: -1.0518733 | P83: 571.98275 | Q83: 11.275722 | R83: #DIV/0! | S83: 0 | T83: #DIV/0! | U83: NA | V83: ='VATtax et trade tax et ipc '!AI83 -> NA | W83: NA | X83: ='VATtax et trade tax et ipc '!AM83 -> NA | Z83: 20.288935 | AA83: 0 | AB83: 1 | AC83: NA
A84: Guinea-Bissau | B84: =Tx_croissance!AH84 -> -0.34259965 | C84: =IFERROR(LN(P84),"NA") -> 6.5253632 | D84: 12.83267 | E84: 2.3527073 | F84: -0.68317619 | G84: 54.608778 | H84: -0.68166121 | I84: 103.85102 | J84: 95.491665 | K84: 65.235176 | L84: -1.2803746 | M84: -1.1555221 | N84: -1.3899013 | O84: -0.75619671 | P84: 682.22752 | Q84: 9.8924538 | R84: 27.228272 | S84: 15.553333 | T84: 16.240138 | U84: NA | V84: ='VATtax et trade tax et ipc '!AI84 -> 7.0254755 | W84: 5.3992392 | X84: ='VATtax et trade tax et ipc '!AM84 -> 4.8062079 | Z84: 22.301055 | AA84: 0 | AB84: 1 | AC84: 17.51676
A85: Guyana | B85: =Tx_croissance!AH85 -> 6.3564436 | C85: =IFERROR(LN(P85),"NA") -> 8.1143762 | D85: 26.721013 | E85: 0.27140171 | F85: 1.6478141 | G85: 66.108926 | H85: -0.33741067 | I85: 97.583381 | J85: 61.990224 | K85: 17.226058 | L85: -0.44520107 | M85: -0.47998277 | N85: -0.47173478 | O85: 0.18441443 | P85: 3342.1721 | Q85: NA | R85: #DIV/0! | S85: 24.013333 | T85: #DIV/0! | U85: NA | V85: ='VATtax et trade tax et ipc '!AI85 -> NA | W85: NA | X85: ='VATtax et trade tax et ipc '!AM85 -> NA | Z85: 33.228683 | AA85: 1 | AB85: 0 | AC85: NA
A86: Haiti | B86: =Tx_croissance!AH86 -> -0.12592441 | C86: =IFERROR(LN(P86),"NA") -> 7.1632323 | D86: 15.055078 | E86: 1.5595145 | F86: 0.67679935 | G86: 60.143852 | H86: -1.0381614 | I86: 96.768619 | J86: 95.919323 | K86: 51.536307 | L86: -1.300208 | M86: -1.1064803 | N86: -1.3385116 | O86: -0.83740829 | P86: 1291.0774 | Q86: NA | R86: #DIV/0! | S86: 23.593333 | T86: #DIV/0! | U86: NA | V86: ='VATtax et trade tax et ipc '!AI86 -> NA | W86: NA | X86: ='VATtax et trade tax et ipc '!AM86 -> NA | AA86: 0 | AB86: 1 | AC86: NA
A87: Honduras | B87: =Tx_croissance!AH87 -> 1.3706602 | C87: =IFERROR(LN(P87),"NA") -> 7.4515512 | D87: 24.777162 | E87: 2.1885205 | F87: 1.6741392 | G87: 70.202148 | H87: -0.43839652 | I87: 106.57146 | J87: NA | K87: NA | L87: -0.88766629 | M87: -0.42820618 | N87: -0.97633993 | O87: -0.37299338 | P87: 1722.533 | Q87: 13.096955 | R87: 30.032758 | S87: 28.1 | T87: 20.160134 | U87: NA | V87: ='VATtax et trade tax et ipc '!AI87 -> 9.5192155 | W87: 0.84730634 | X87: ='VATtax et trade tax et ipc '!AM87 -> 4.6517992 | Z87: 26.353788 | AA87: 0 | AB87: 1 | AC87: 6.2269799
A88: Hong Kong SAR, China | B88: =Tx_croissance!AH88 -> 1.9687099 | C88: =IFERROR(LN(P88),"NA") -> 10.15113 | D88: 23.148365 | E88: 0.70188367 | F88: 0.0039457695 | G88: 82.568654 | H88: 0.83243214 | I88: 100.4754 | J88: 99.91036 | K88: 50.179962 | L88: 1.6807445 | M88: 1.8940356 | N88: 1.4703808 | O88: 0.34154597 | P88: 25620.028 | Q88: NA | R88: #DIV/0! | S88: 17.793333 | T88: #DIV/0! | U88: NA | V88: ='VATtax et trade tax et ipc '!AI88 -> NA | W88: NA | X88: ='VATtax et trade tax et ipc '!AM88 -> NA | Z88: 30.210651 | AA88: 0 | AB88: 0 | AC88: NA
A89: Hungary | B89: =Tx_croissance!AH89 -> 2.8370638 | C89: =IFERROR(LN(P89),"NA") -> 8.9457989 | D89: 23.425676 | E89: -0.2503823 | F89: -0.22497772 | G89: 73.506748 | H89: 0.82948793 | I89: 110.16395 | J89: 74.046388 | K89: 24.225921 | L89: 0.35057179 | M89: 0.88654685 | N89: 0.68975366 | O89: 0.796225 | P89: 7675.5782 | Q89: 22.340994 | R89: 32.089971 | S89: 10.166667 | T89: 18.017893 | U89: 78.361064 | V89: ='VATtax et trade tax et ipc '!AI89 -> 13.618645 | W89: 0.33540372 | X89: ='VATtax et trade tax et ipc '!AM89 -> 6.5424893 | Y89: 23.167205 | Z89: 21.775734 | AA89: 0 | AB89: 0 | AC89: 4.3794326
A90: Iceland | B90: =Tx_croissance!AH90 -> 1.8732687 | C90: =IFERROR(LN(P90),"NA") -> 10.43964 | D90: 21.681847 | E90: 1.2923329 | F90: -0.56699724 | G90: 81.352529 | H90: 1.3631096 | I90: NA | J90: NA | K90: NA | L90: 1.9586453 | M90: 1.3437094 | N90: 1.735136 | O90: 1.4330363 | P90: 34188.351 | Q90: 22.969981 | R90: 37.131331 | S90: 8.4466667 | T90: 26.225921 | U90: 92.782377 | V90: ='VATtax et trade tax et ipc '!AI90 -> 12.253587 | W90: 0.24965063 | X90: ='VATtax et trade tax et ipc '!AM90 -> 9.1961187 | Y90: 22.513347 | Z90: 17.529239 | AA90: 0 | AB90: 0 | AC90: 1.2674733
A91: India | B91: =Tx_croissance!AH91 -> 4.6147131 | C91: =IFERROR(LN(P91),"NA") -> 6.4267138 | D91: 29.74482 | E91: 1.4462762 | F91: -1.4213022 | G91: 66.027333 | H91: -1.0658786 | I91: 99.430768 | J91: 60.205391 | K91: 18.161983 | L91: -0.38835074 | M91: -0.32485067 | N91: 0.045935208 | O91: 0.37524204 | P91: 618.13929 | Q91: 9.7636015 | R91: 44.835296 | S91: 22.971429 | T91: 36.828698 | U91: 53.512241 | V91: ='VATtax et trade tax et ipc '!AI91 -> 2.8323156 | W91: 1.1207294 | X91: ='VATtax et trade tax et ipc '!AM91 -> 3.9932093 | Y91: 9.2268247 | Z91: 25.136923 | AA91: 0 | AB91: 1 | AC91: 19.077239
A92: Indonesia | B92: =Tx_croissance!AH92 -> 2.8204505 | C92: =IFERROR(LN(P92),"NA") -> 7.5613048 | D92: 27.772533 | E92: 1.2355696 | F92: 1.494555 | G92: 67.941 | H92: -0.98053223 | I92: 101.60119 | J92: 114.88386 | K92: 54.229289 | L92: -0.70245254 | M92: -0.23295907 | N92: -0.54905375 | O92: -0.079320336 | P92: 1922.3521 | Q92: 14.532821 | R92: 51.252552 | S92: 19.357143 | T92: 39.842548 | U92: 34.920794 | V92: ='VATtax et trade tax et ipc '!AI92 -> 4.804385 | W92: 0.3995512 | X92: ='VATtax et trade tax et ipc '!AM92 -> 5.2330342 | Y92: 14.964772 | Z92: 28.429811 | AA92: 0 | AB92: 1 | AC92: 3.1057583
A93: Iran, Islamic Rep. | B93: =Tx_croissance!AH93 -> 1.624339 | C93: =IFERROR(LN(P93),"NA") -> 8.1788245 | D93: 28.653878 | E93: 1.3909528 | F93: 1.2022989 | G93: 72.355481 | H93: -1.1007145 | I93: 107.56842 | J93: 82.445783 | K93: 40.429958 | L93: -0.70151612 | M93: -1.4566258 | N93: -0.87047863 | O93: -1.3769386 | P93: 3564.6618 | Q93: 6.5538781 | R93: 49.472269 | S93: 17.993333 | T93: 13.530197 | U93: NA | V93: ='VATtax et trade tax et ipc '!AI93 -> 0.11004703 | W93: 0.1925528 | X93: ='VATtax et trade tax et ipc '!AM93 -> 0.42137896 | Y93: 6.2207987 | Z93: 24.688894 | AA93: 0 | AB93: 0 | AC93: 23.026203
A94: Iraq | B94: =Tx_croissance!AH94 -> 3.0045836 | C94: =IFERROR(LN(P94),"NA") -> 7.5753684 | D94: 11.004403 | E94: 2.8119372 | F94: 0.5067354 | G94: 67.284593 | H94: -2.2921575 | I94: NA | J94: NA | K94: NA | L94: -1.3835704 | M94: -1.3557346 | N94: -1.6661777 | O94: -1.2648438 | P94: 1949.5783 | Q94: 1.7215676 | R94: 60.22102 | S94: 14.746667 | T94: 3.173684 | U94: 30.042303 | V94: ='VATtax et trade tax et ipc '!AI94 -> 0.27055042 | W94: 0.63816572 | X94: ='VATtax et trade tax et ipc '!AM94 -> 1.6997815 | Z94: 1.7305324 | AA94: 0 | AB94: 1 | AC94: 19.838724
A95: Ireland | B95: =Tx_croissance!AH95 -> 4.6954457 | C95: =IFERROR(LN(P95),"NA") -> 10.246821 | D95: 25.681157 | E95: 1.272479 | F95: 0.26083724 | G95: 79.448475 | H95: 1.1109462 | I95: 98.910753 | J95: 111.34198 | K95: 64.544133 | L95: 1.5795461 | M95: 1.6534127 | N95: 1.5919355 | O95: 1.3634469 | P95: 28192.775 | Q95: 23.881351 | R95: 51.887712 | S95: 12.146667 | T95: 39.201244 | U95: 66.024981 | V95: ='VATtax et trade tax et ipc '!AI95 -> 8.9271272 | W95: NA | X95: ='VATtax et trade tax et ipc '!AM95 -> 10.630055 | Y95: 26.526589 | Z95: 18.071546 | AA95: 1 | AB95: 0 | AC95: NA
A96: Isle of Man | B96: =Tx_croissance!AH96 -> NA | C96: =IFERROR(LN(P96),"NA") -> 10.336189 | D96: NA | E96: 0.6177622 | F96: 1.4353898 | G96: 77.707926 | H96: NA | I96: 97.21721 | J96: 96.115533 | K96: 55.130496 | L96: NA | M96: NA | N96: NA | O96: NA | P96: 30828.305 | Q96: NA | R96: #DIV/0! | S96: #DIV/0! | T96: #DIV/0! | U96: NA | V96: ='VATtax et trade tax et ipc '!AI96 -> NA | W96: NA | X96: ='VATtax et trade tax et ipc '!AM96 -> NA | AA96: 0 | AB96: 0 | AC96: NA
A97: Israel | B97: =Tx_croissance!AH97 -> 1.8739386 | C97: =IFERROR(LN(P97),"NA") -> 10.160925 | D97: 23.336774 | E97: 2.0396873 | F97: 1.2760356 | G97: 80.684282 | H97: -1.1629256 | I97: 102.42372 | J97: 98.866626 | K97: 59.835404 | L97: 0.90841895 | M97: 1.1301461 | N97: 0.96391927 | O97: 0.67271118 | P97: 25872.23 | Q97: 23.883956 | R97: 46.470887 | S97: 21.32 | T97: 31.488092 | U97: 95.175588 | V97: ='VATtax et trade tax et ipc '!AI97 -> 10.785749 | W97: 0.23948948 | X97: ='VATtax et trade tax et ipc '!AM97 -> 10.418939 | Y97: 25.874731 | Z97: 28.022519 | AA97: 0 | AB97: 0 | AC97: 1.0660076
A98: Italy | B98: =Tx_croissance!AH98 -> 0.47743788 | C98: =IFERROR(LN(P98),"NA") -> 10.284151 | D98: 19.552438 | E98: 0.12938239 | F98: 0.10161594 | G98: 81.268473 | H98: 0.52665461 | I98: 95.088382 | J98: 85.414653 | K98: 19.918339 | L98: 0.32330809 | M98: 0.80421722 | N98: 0.4739961 | O98: 1.0257972 | P98: 29265.089 | Q98: 22.113555 | R98: 54.112014 | S98: 23.06 | T98: 33.358059 | U98: NA | V98: ='VATtax et trade tax et ipc '!AI98 -> 9.0529046 | W98: NA | X98: ='VATtax et trade tax et ipc '!AM98 -> 12.877966 | Y98: 24.363031 | Z98: 19.3726 | AA98: 0 | AB98: 0 | AC98: NA
A99: Jamaica | B99: =Tx_croissance!AH99 -> 0.019128631 | C99: =IFERROR(LN(P99),"NA") -> 8.5582998 | D99: 23.565395 | E99: 0.46216427 | F99: -0.42825464 | G99: 71.690815 | H99: 0.0032678802 | I99: NA | J99: 76.981012 | K99: 33.8039 | L99: -0.21275593 | M99: 0.16943875 | N99: -0.30908842 | O99: 0.57895816 | P99: 5209.8159 | Q99: 23.565549 | R99: 41.726414 | S99: 22.76 | T99: 36.845434 | U99: 112.99913 | V99: ='VATtax et trade tax et ipc '!AI99 -> 11.138618 | W99: 2.5754469 | X99: ='VATtax et trade tax et ipc '!AM99 -> 8.8365627 | Y99: 21.74404 | Z99: 24.917369 | AA99: 0 | AB99: 0 | AC99: 9.8696031
A100: Japan | B100: =Tx_croissance!AH100 -> 0.65969145 | C100: =IFERROR(LN(P100),"NA") -> 10.314642 | D100: 26.177652 | E100: -0.0015127666 | F100: -0.52603105 | G100: 82.456305 | H100: 1.0416451 | I100: 103.51471 | J100: 103.20988 | K100: 57.458382 | L100: 1.3820045 | M100: 1.1234965 | N100: 1.3754992 | O100: 1.0143582 | P100: 30171.164 | Q100: 11.90016 | R100: #DIV/0! | S100: 25.928571 | T100: #DIV/0! | U100: 145.3796 | V100: ='VATtax et trade tax et ipc '!AI100 -> NA | W100: NA | X100: ='VATtax et trade tax et ipc '!AM100 -> NA | Z100: 30.60586 | AA100: 0 | AB100: 0 | AC100: NA
...

Sheet VATtax et trade tax et ipc 
A1: Series Name | B1: Series Code | C1: Country Name | D1: Country Code | E1: 1995 [YR1995] | F1: 1996 [YR1996] | G1: 1997 [YR1997] | H1: 1998 [YR1998] | I1: 1999 [YR1999] | J1: 2000 [YR2000] | K1: 2001 [YR2001] | L1: 2002 [YR2002] | M1: 2003 [YR2003] | N1: 2004 [YR2004] | O1: 2005 [YR2005] | P1: 2006 [YR2006] | Q1: 2007 [YR2007] | R1: 2008 [YR2008] | S1: 2009 [YR2009] | T1: 2010 [YR2010] | U1: 2011 [YR2011] | V1: 2012 [YR2012] | W1: 2013 [YR2013] | X1: 2014 [YR2014] | Y1: 2015 [YR2015] | Z1: 2016 [YR2016] | AA1: 2017 [YR2017] | AB1: 2018 [YR2018] | AC1: 2019 [YR2019] | AD1: 2020 [YR2020] | AE1: 2021 [YR2021] | AF1: 2022 [YR2022] | AG1: moyenne | AI1: VAT(lcu) / Gdp (lcu) = Vat/gdp | AK1: trade_tx_gdp = taxe sur le commerce international (%GDP) | AM1: incprofitcap_tx = tax on income profit and capital gain LCU / GDP LCU
A2: Taxes on goods and services (current LCU) | B2: GC.TAX.GSRV.CN | C2: Afghanistan | D2: AFG | E2: .. | F2: .. | G2: .. | H2: .. | I2: .. | J2: .. | K2: .. | L2: .. | M2: .. | N2: .. | O2: .. | P2: 5.9529439e+09 | Q2: 6.7020366e+09 | R2: 8.0706949e+09 | S2: 1.3497092e+10 | T2: 1.8435006e+10 | U2: 2.0918999e+10 | V2: 2.1452208e+10 | W2: 19386490829 | X2: 1.7309901e+10 | Y2: 1.7608166e+10 | Z2: 4.4737123e+10 | AA2: 5.3188617e+10 | AB2: .. | AC2: .. | AD2: .. | AE2: .. | AF2: .. | AG2: =IFERROR(AVERAGE(E2:AF2),"NA") -> 2.060494e+10 | AI2: =IFERROR(AG2*100/AG222,"NA") -> 2.401943 | AK2: =IFERROR(AG443*100/AG222,"NA") -> 3.0990709 | AM2: =IFERROR(AG664*100/AG222,"NA") -> 2.4633253
A3: Taxes on goods and services (current LCU) | B3: GC.TAX.GSRV.CN | C3: Albania | D3: ALB | E3: 18850000000 | F3: 15948958000 | G3: 18926363000 | H3: 35385497000 | I3: .. | J3: .. | K3: .. | L3: 64835600000 | M3: 76255180000 | N3: 89353960000 | O3: .. | P3: .. | Q3: .. | R3: .. | S3: .. | T3: .. | U3: 175055100000 | V3: 173505580000 | W3: 166375460000 | X3: 195997780000 | Y3: 200012910000 | Z3: 208378160000 | AA3: 218755890000 | AB3: 226077000000 | AC3: 220257210000 | AD3: 208303130000 | AE3: 251058420000 | AF3: .. | AG3: =IFERROR(AVERAGE(E3:AF3),"NA") -> 1.4240734e+11 | AI3: =IFERROR(AG3*100/AG223,"NA") -> 13.416597 | AK3: =IFERROR(AG444*100/AG223,"NA") -> 0.91035615 | AM3: =IFERROR(AG665*100/AG223,"NA") -> 3.7756395
A4: Taxes on goods and services (current LCU) | B4: GC.TAX.GSRV.CN | C4: Algeria | D4: DZA | E4: .. | F4: .. | G4: .. | H4: .. | I4: .. | J4: .. | K4: .. | L4: .. | M4: .. | N4: .. | O4: .. | P4: .. | Q4: .. | R4: .. | S4: .. | T4: .. | U4: .. | V4: .. | W4: .. | X4: .. | Y4: .. | Z4: .. | AA4: .. | AB4: .. | AC4: .. | AD4: .. | AE4: .. | AF4: .. | AG4: =IFERROR(AVERAGE(E4:AF4),"NA") -> NA | AI4: =IFERROR(AG4*100/AG224,"NA") -> NA | AK4: =IFERROR(AG445*100/AG224,"NA") -> NA | AM4: =IFERROR(AG666*100/AG224,"NA") -> NA
A5: Taxes on goods and services (current LCU) | B5: GC.TAX.GSRV.CN | C5: American Samoa | D5: ASM | E5: .. | F5: .. | G5: .. | H5: .. | I5: .. | J5: .. | K5: .. | L5: .. | M5: .. | N5: .. | O5: .. | P5: .. | Q5: .. | R5: .. | S5: .. | T5: .. | U5: .. | V5: .. | W5: .. | X5: .. | Y5: .. | Z5: .. | AA5: .. | AB5: .. | AC5: .. | AD5: .. | AE5: .. | AF5: .. | AG5: =IFERROR(AVERAGE(E5:AF5),"NA") -> NA | AI5: =IFERROR(AG5*100/AG225,"NA") -> NA | AK5: =IFERROR(AG446*100/AG225,"NA") -> NA | AM5: =IFERROR(AG667*100/AG225,"NA") -> NA
A6: Taxes on goods and services (current LCU) | B6: GC.TAX.GSRV.CN | C6: Andorra | D6: AND | E6: .. | F6: .. | G6: .. | H6: .. | I6: .. | J6: .. | K6: .. | L6: .. | M6: .. | N6: .. | O6: .. | P6: .. | Q6: .. | R6: .. | S6: .. | T6: .. | U6: .. | V6: .. | W6: .. | X6: .. | Y6: .. | Z6: .. | AA6: .. | AB6: .. | AC6: .. | AD6: .. | AE6: .. | AF6: .. | AG6: =IFERROR(AVERAGE(E6:AF6),"NA") -> NA | AI6: =IFERROR(AG6*100/AG226,"NA") -> NA | AK6: =IFERROR(AG447*100/AG226,"NA") -> NA | AM6: =IFERROR(AG668*100/AG226,"NA") -> NA
A7: Taxes on goods and services (current LCU) | B7: GC.TAX.GSRV.CN | C7: Angola | D7: AGO | E7: .. | F7: .. | G7: .. | H7: .. | I7: 3.2635839e+08 | J7: 1495978615 | K7: 17300349784 | L7: 12670999806 | M7: 30463029879 | N7: 41894421449 | O7: 51456380174 | P7: 68937892658 | Q7: 92906282322 | R7: 137367000000 | S7: 149494000000 | T7: 162085000000 | U7: 170041000000 | V7: 165995000000 | W7: 202397000000 | X7: 228895697526 | Y7: 176561786757 | Z7: 209778948579 | AA7: 246820082710 | AB7: 273026007438 | AC7: 3.5989858e+11 | AD7: .. | AE7: .. | AF7: .. | AG7: =IFERROR(AVERAGE(E7:AF7),"NA") -> 1.3332437e+11 | AI7: =IFERROR(AG7*100/AG227,"NA") -> 1.1549995 | AK7: =IFERROR(AG448*100/AG227,"NA") -> 0.70915725 | AM7: =IFERROR(AG669*100/AG227,"NA") -> 7.7522472
A8: Taxes on goods and services (current LCU) | B8: GC.TAX.GSRV.CN | C8: Antigua and Barbuda | D8: ATG | E8: .. | F8: .. | G8: .. | H8: .. | I8: .. | J8: .. | K8: .. | L8: .. | M8: .. | N8: .. | O8: .. | P8: .. | Q8: .. | R8: .. | S8: .. | T8: .. | U8: .. | V8: .. | W8: .. | X8: .. | Y8: .. | Z8: .. | AA8: .. | AB8: .. | AC8: .. | AD8: .. | AE8: .. | AF8: .. | AG8: =IFERROR(AVERAGE(E8:AF8),"NA") -> NA | AI8: =IFERROR(AG8*100/AG228,"NA") -> NA | AK8: =IFERROR(AG449*100/AG228,"NA") -> NA | AM8: =IFERROR(AG670*100/AG228,"NA") -> NA
A9: Taxes on goods and services (current LCU) | B9: GC.TAX.GSRV.CN | C9: Argentina | D9: ARG | E9: 13203700000 | F9: 13931400000 | G9: 16227200000 | H9: 17185200000 | I9: 16728900000 | J9: 17674300000 | K9: 16224000000 | L9: 16481800000 | M9: 2.2164551e+10 | N9: 3.0264212e+10 | O9: 36184400000 | P9: 44376700000 | Q9: 54722400000 | R9: 69210800000 | S9: 76968800000 | T9: 101267600000 | U9: 130577600000 | V9: 165330200000 | W9: 210696000000 | X9: 282293400000 | Y9: 369418100000 | Z9: 478910200000 | AA9: 624789300000 | AB9: 871333500000 | AC9: 1.2081107e+12 | AD9: 1.5030353e+12 | AE9: 2.6026779e+12 | AF9: .. | AG9: =IFERROR(AVERAGE(E9:AF9),"NA") -> 3.3370326e+11 | AI9: =IFERROR(AG9*100/AG229,"NA") -> 3.9050876 | AK9: =IFERROR(AG450*100/AG229,"NA") -> 1.5709463 | AM9: =IFERROR(AG671*100/AG229,"NA") -> 1.3523403
A10: Taxes on goods and services (current LCU) | B10: GC.TAX.GSRV.CN | C10: Armenia | D10: ARM | E10: .. | F10: .. | G10: .. | H10: .. | I10: .. | J10: .. | K10: .. | L10: .. | M10: .. | N10: 113048383600 | O10: 1.4457726e+11 | P10: 163233826600 | Q10: 2.8672424e+11 | R10: 361177594616 | S10: 293121813614 | T10: 346424420350 | U10: 364465369127 | V10: 415937000000 | W10: 453982449672 | X10: 532789401680 | Y10: 472922401444 | Z10: 450833122380 | AA10: 488914300373 | AB10: 547181002880 | AC10: 757077840956 | AD10: 719724611359 | AE10: 867184153472 | AF10: .. | AG10: =IFERROR(AVERAGE(E10:AF10),"NA") -> 4.321844e+11 | AI10: =IFERROR(AG10*100/AG230,"NA") -> 12.528264 | AK10: =IFERROR(AG451*100/AG230,"NA") -> 1.3716237 | AM10: =IFERROR(AG672*100/AG230,"NA") -> 9.0651098
A11: Taxes on goods and services (current LCU) | B11: GC.TAX.GSRV.CN | C11: Aruba | D11: ABW | E11: .. | F11: .. | G11: .. | H11: .. | I11: .. | J11: .. | K11: .. | L11: .. | M11: .. | N11: .. | O11: .. | P11: .. | Q11: .. | R11: .. | S11: .. | T11: .. | U11: .. | V11: .. | W11: .. | X11: .. | Y11: .. | Z11: .. | AA11: .. | AB11: .. | AC11: .. | AD11: .. | AE11: .. | AF11: .. | AG11: =IFERROR(AVERAGE(E11:AF11),"NA") -> NA | AI11: =IFERROR(AG11*100/AG231,"NA") -> NA | AK11: =IFERROR(AG452*100/AG231,"NA") -> NA | AM11: =IFERROR(AG673*100/AG231,"NA") -> NA
A12: Taxes on goods and services (current LCU) | B12: GC.TAX.GSRV.CN | C12: Australia | D12: AUS | E12: 24648000000 | F12: 26882000000 | G12: 27613000000 | H12: 28752000000 | I12: 30132000000 | J12: 30736000000 | K12: 46516000000 | L12: 50037000000 | M12: 55207000000 | N12: 58176000000 | O12: 60523000000 | P12: 63722000000 | Q12: 66728000000 | R12: 70880000000 | S12: 70121000000 | T12: 74182000000 | U12: 77407000000 | V12: 78152000000 | W12: 86713000000 | X12: 91660000000 | Y12: 84991000000 | Z12: 89412000000 | AA12: 92606000000 | AB12: 98174000000 | AC12: 100093000000 | AD12: 98478000000 | AE12: 109351000000 | AF12: 110605000000 | AG12: =IFERROR(AVERAGE(E12:AF12),"NA") -> 6.7946321e+10 | AI12: =IFERROR(AG12*100/AG232,"NA") -> 5.4911305 | AK12: =IFERROR(AG453*100/AG232,"NA") -> 0.67024513 | AM12: =IFERROR(AG674*100/AG232,"NA") -> 16.434395
A13: Taxes on goods and services (current LCU) | B13: GC.TAX.GSRV.CN | C13: Austria | D13: AUT | E13: 20702610000 | F13: 22196210000 | G13: 23388870000 | H13: 24271110000 | I13: 25476350000 | J13: 26328330000 | K13: 27440420000 | L13: 28532860000 | M13: 28814700000 | N13: 29955780000 | O13: 30799860000 | P13: 31403050000 | Q13: 32944000000 | R13: 34114870000 | S13: 34362710000 | T13: 35246410000 | U13: 37160460000 | V13: 38741900000 | W13: 39041190000 | X13: 39843080000 | Y13: 41215020000 | Z13: 42686270000 | AA13: 44022710000 | AB13: 45211970000 | AC13: 46718660000 | AD13: 43670950000 | AE13: 47573970000 | AF13: .. | AG13: =IFERROR(AVERAGE(E13:AF13),"NA") -> 3.4143123e+10 | AI13: =IFERROR(AG13*100/AG233,"NA") -> 11.745178 | AK13: =IFERROR(AG454*100/AG233,"NA") -> -0.0027464446 | AM13: =IFERROR(AG675*100/AG233,"NA") -> 11.93604
A14: Taxes on goods and services (current LCU) | B14: GC.TAX.GSRV.CN | C14: Azerbaijan | D14: AZE | E14: 130276600 | F14: 105032200 | G14: 193523200 | H14: 234531400 | I14: 264754200 | J14: .. | K14: .. | L14: .. | M14: .. | N14: .. | O14: .. | P14: .. | Q14: .. | R14: 2502800000 | S14: 2593000000 | T14: 2695600000 | U14: 2865100000 | V14: 3080200000 | W14: 3493800000 | X14: 4145800000 | Y14: 4404200000 | Z14: 4727000000 | AA14: 4808400000 | AB14: 5600004000 | AC14: 6541000000 | AD14: 6130300000 | AE14: 6739100000 | AF14: .. | AG14: =IFERROR(AVERAGE(E14:AF14),"NA") -> 3.2239169e+09 | AI14: =IFERROR(AG14*100/AG234,"NA") -> 8.2392438 | AK14: =IFERROR(AG455*100/AG234,"NA") -> 1.4743464 | AM14: =IFERROR(AG676*100/AG234,"NA") -> 6.0267988
A15: Taxes on goods and services (current LCU) | B15: GC.TAX.GSRV.CN | C15: Bahamas, The | D15: BHS | E15: 57800000 | F15: 35900000 | G15: 40911000 | H15: 50328000 | I15: 46930000 | J15: 119100000 | K15: 94000000 | L15: 102100000 | M15: 86300000 | N15: 117130000 | O15: 180285000 | P15: 334525000 | Q15: 388734000 | R15: 158400000 | S15: 373774000 | T15: 5.1574553e+08 | U15: 6.8342112e+08 | V15: 6.6521177e+08 | W15: 5.6438677e+08 | X15: 6.2878554e+08 | Y15: 9.0168065e+08 | Z15: 1.1545712e+09 | AA15: 1.2819658e+09 | AB15: 1275736000 | AC15: 1634363000 | AD15: 1346816646 | AE15: 1166624454 | AF15: 1488588337 | AG15: =IFERROR(AVERAGE(E15:AF15),"NA") -> 5.5336121e+08 | AI15: =IFERROR(AG15*100/AG235,"NA") -> 5.7376246 | AK15: =IFERROR(AG456*100/AG235,"NA") -> 5.172775 | AM15: =IFERROR(AG677*100/AG235,"NA") -> NA
A16: Taxes on goods and services (current LCU) | B16: GC.TAX.GSRV.CN | C16: Bahrain | D16: BHR | E16: 30200000 | F16: 28400000 | G16: 23800000 | H16: 22300000 | I16: 23100000 | J16: 25300000 | K16: 24300000 | L16: 26200000 | M16: 30700000 | N16: 32800000 | O16: .. | P16: .. | Q16: .. | R16: .. | S16: .. | T16: .. | U16: .. | V16: .. | W16: .. | X16: .. | Y16: .. | Z16: .. | AA16: .. | AB16: .. | AC16: .. | AD16: .. | AE16: .. | AF16: .. | AG16: =IFERROR(AVERAGE(E16:AF16),"NA") -> 26710000 | AI16: =IFERROR(AG16*100/AG236,"NA") -> 0.31447793 | AK16: =IFERROR(AG457*100/AG236,"NA") -> 0.63554918 | AM16: =IFERROR(AG678*100/AG236,"NA") -> 0.43292226
A17: Taxes on goods and services (current LCU) | B17: GC.TAX.GSRV.CN | C17: Bangladesh | D17: BGD | E17: .. | F17: .. | G17: .. | H17: .. | I17: .. | J17: .. | K17: 66568780000 | L17: 75228380000 | M17: 108949240000 | N17: 100539870000 | O17: 109990725000 | P17: 125517335000 | Q17: 140969068000 | R17: 171902957000 | S17: 200555946000 | T17: 240716688000 | U17: 304282400000 | V17: 352579400000 | W17: 402282200000 | X17: 428603900000 | Y17: 474400070000 | Z17: 577640000000 | AA17: 928708500000 | AB17: 1151751000000 | AC17: 1284988059000 | AD17: 1184613000000 | AE17: 1.4652468e+12 | AF17: .. | AG17: =IFERROR(AVERAGE(E17:AF17),"NA") -> 4.7123973e+11 | AI17: =IFERROR(AG17*100/AG237,"NA") -> 4.0092421 | AK17: =IFERROR(AG458*100/AG237,"NA") -> 1.8015978 | AM17: =IFERROR(AG679*100/AG237,"NA") -> 2.5116353
A18: Taxes on goods and services (current LCU) | B18: GC.TAX.GSRV.CN | C18: Barbados | D18: BRB | E18: .. | F18: .. | G18: .. | H18: .. | I18: .. | J18: .. | K18: .. | L18: .. | M18: 744568000 | N18: 878600000 | O18: 980641000 | P18: 9.8838044e+08 | Q18: 1090205310 | R18: 1100267475 | S18: 1002793628 | T18: 1077151137 | U18: 1284253544 | V18: 1144666163 | W18: 1151577522 | X18: 1063462232 | Y18: 1226930233 | Z18: 1317590062 | AA18: .. | AB18: .. | AC18: .. | AD18: .. | AE18: .. | AF18: .. | AG18: =IFERROR(AVERAGE(E18:AF18),"NA") -> 1.0750776e+09 | AI18: =IFERROR(AG18*100/AG238,"NA") -> 13.164133 | AK18: =IFERROR(AG459*100/AG238,"NA") -> 2.5135495 | AM18: =IFERROR(AG680*100/AG238,"NA") -> 9.2873308
A19: Taxes on goods and services (current LCU) | B19: GC.TAX.GSRV.CN | C19: Belarus | D19: BLR | E19: 1209560 | F19: 2193460 | G19: 4802210 | H19: 7757750 | I19: 32942470 | J19: 101656000 | K19: 178242000 | L19: 251079000 | M19: 370189400 | N19: 543991000 | O19: 738047400 | P19: 1128617900 | Q19: 1270861800 | R19: 1.5231464e+09 | S19: 1397172200 | T19: 1.6701819e+09 | U19: 2495000000 | V19: 4610280000 | W19: 5994690000 | X19: 7529064110 | Y19: 7.8650167e+09 | Z19: 8.7935673e+09 | AA19: 9068217958 | AB19: 1.1020978e+10 | AC19: 1.1753309e+10 | AD19: 1.3111921e+10 | AE19: 1.558478e+10 | AF19: .. | AG19: =IFERROR(AVERAGE(E19:AF19),"NA") -> 3.9647746e+09 | AI19: =IFERROR(AG19*100/AG239,"NA") -> 8.0357778 | AK19: =IFERROR(AG460*100/AG239,"NA") -> 3.1923354 | AM19: =IFERROR(AG681*100/AG239,"NA") -> 0.85928337
A20: Taxes on goods and services (current LCU) | B20: GC.TAX.GSRV.CN | C20: Belgium | D20: BEL | E20: 22240700000 | F20: 23569900000 | G20: 24950500000 | H20: 25830000000 | I20: 27821200000 | J20: 29187000000 | K20: 28825800000 | L20: 27505000000 | M20: 28103900000 | N20: 30307300000 | O20: 31743900000 | P20: 33226400000 | Q20: 34746600000 | R20: 35193500000 | S20: 34745900000 | T20: 37261900000 | U20: 38381900000 | V20: 40884700000 | W20: 40994500000 | X20: 41445400000 | Y20: 41974800000 | Z20: 43855200000 | AA20: 45144600000 | AB20: 47340800000 | AC20: 48519500000 | AD20: 45222600000 | AE20: 51766700000 | AF20: .. | AG20: =IFERROR(AVERAGE(E20:AF20),"NA") -> 3.5584822e+10 | AI20: =IFERROR(AG20*100/AG240,"NA") -> 10.118285 | AK20: =IFERROR(AG461*100/AG240,"NA") -> NA | AM20: =IFERROR(AG682*100/AG240,"NA") -> 13.953597
A21: Taxes on goods and services (current LCU) | B21: GC.TAX.GSRV.CN | C21: Belize | D21: BLZ | E21: 41749000 | F21: 104340000 | G21: 98047000 | H21: 97921000 | I21: 81974000 | J21: 101849000 | K21: 107947000 | L21: 113526000 | M21: 120033000 | N21: 140997000 | O21: 181834000 | P21: 217027000 | Q21: 235974000 | R21: 236703000 | S21: 217097000 | T21: 251105000 | U21: 230251000 | V21: 2.7727404e+08 | W21: 3.0502895e+08 | X21: 3.4557191e+08 | Y21: 3.5445857e+08 | Z21: 4.893467e+08 | AA21: 5.3302942e+08 | AB21: .. | AC21: .. | AD21: .. | AE21: .. | AF21: .. | AG21: =IFERROR(AVERAGE(E21:AF21),"NA") -> 2.1230798e+08 | AI21: =IFERROR(AG21*100/AG241,"NA") -> 6.3035175 | AK21: =IFERROR(AG462*100/AG241,"NA") -> 4.6893769 | AM21: =IFERROR(AG683*100/AG241,"NA") -> 4.6216683
A22: Taxes on goods and services (current LCU) | B22: GC.TAX.GSRV.CN | C22: Benin | D22: BEN | E22: .. | F22: .. | G22: .. | H22: .. | I22: .. | J22: .. | K22: .. | L22: .. | M22: .. | N22: .. | O22: .. | P22: .. | Q22: .. | R22: .. | S22: .. | T22: .. | U22: .. | V22: .. | W22: .. | X22: .. | Y22: .. | Z22: .. | AA22: .. | AB22: .. | AC22: .. | AD22: .. | AE22: .. | AF22: .. | AG22: =IFERROR(AVERAGE(E22:AF22),"NA") -> NA | AI22: =IFERROR(AG22*100/AG242,"NA") -> NA | AK22: =IFERROR(AG463*100/AG242,"NA") -> NA | AM22: =IFERROR(AG684*100/AG242,"NA") -> NA
A23: Taxes on goods and services (current LCU) | B23: GC.TAX.GSRV.CN | C23: Bermuda | D23: BMU | E23: .. | F23: .. | G23: .. | H23: .. | I23: .. | J23: .. | K23: .. | L23: .. | M23: .. | N23: .. | O23: .. | P23: .. | Q23: .. | R23: .. | S23: .. | T23: .. | U23: .. | V23: .. | W23: .. | X23: .. | Y23: .. | Z23: .. | AA23: .. | AB23: .. | AC23: .. | AD23: .. | AE23: .. | AF23: .. | AG23: =IFERROR(AVERAGE(E23:AF23),"NA") -> NA | AI23: =IFERROR(AG23*100/AG243,"NA") -> NA | AK23: =IFERROR(AG464*100/AG243,"NA") -> NA | AM23: =IFERROR(AG685*100/AG243,"NA") -> NA
A24: Taxes on goods and services (current LCU) | B24: GC.TAX.GSRV.CN | C24: Bhutan | D24: BTN | E24: 338600000 | F24: 381600000 | G24: 319700000 | H24: 519130000 | I24: 466300000 | J24: 842500000 | K24: 546100000 | L24: 915009000 | M24: 1219493000 | N24: 750092000 | O24: 1230259000 | P24: 1653204000 | Q24: 1423833000 | R24: 1869554000 | S24: 2141890000 | T24: 3271565345 | U24: 4161423239 | V24: 6405340491 | W24: 7051661111 | X24: 6285523000 | Y24: 6.7784898e+09 | Z24: 7.6089783e+09 | AA24: 8817876000 | AB24: 1.2571699e+10 | AC24: 11848028000 | AD24: 9835763000 | AE24: .. | AF24: .. | AG24: =IFERROR(AVERAGE(E24:AF24),"NA") -> 3.8174466e+09 | AI24: =IFERROR(AG24*100/AG244,"NA") -> 4.9238723 | AK24: =IFERROR(AG465*100/AG244,"NA") -> 0.79130598 | AM24: =IFERROR(AG686*100/AG244,"NA") -> 6.2481379
A25: Taxes on goods and services (current LCU) | B25: GC.TAX.GSRV.CN | C25: Bolivia | D25: BOL | E25: 2611100000 | F25: 3784100000 | G25: 4237600000 | H25: 4752100000 | I25: 4200900000 | J25: 5145000000 | K25: 5088700000 | L25: 5.9804539e+09 | M25: 6.434651e+09 | N25: 7705600000 | O25: 9.6817418e+09 | P25: 1.1833077e+10 | Q25: 1.3213266e+10 | R25: .. | S25: .. | T25: .. | U25: .. | V25: .. | W25: .. | X25: .. | Y25: .. | Z25: .. | AA25: .. | AB25: .. | AC25: .. | AD25: .. | AE25: .. | AF25: .. | AG25: =IFERROR(AVERAGE(E25:AF25),"NA") -> 6.5129454e+09 | AI25: =IFERROR(AG25*100/AG245,"NA") -> 4.4863966 | AK25: =IFERROR(AG466*100/AG245,"NA") -> 0.37027745 | AM25: =IFERROR(AG687*100/AG245,"NA") -> 0.70856584
A26: Taxes on goods and services (current LCU) | B26: GC.TAX.GSRV.CN | C26: Bosnia and Herzegovina | D26: BIH | E26: .. | F26: .. | G26: .. | H26: .. | I26: .. | J26: .. | K26: .. | L26: .. | M26: .. | N26: .. | O26: 1.4355779e+09 | P26: 3.8758704e+09 | Q26: 4.3208227e+09 | R26: 4.494651e+09 | S26: 4.052924e+09 | T26: 4.3855818e+09 | U26: 4600028053 | V26: 4634988510 | W26: 4543595047 | X26: 4.6649467e+09 | Y26: 4.911459e+09 | Z26: 5.0590284e+09 | AA26: 5.3044318e+09 | AB26: 5.6858156e+09 | AC26: 5.9221021e+09 | AD26: 5.3888613e+09 | AE26: 6.2584587e+09 | AF26: 7.1216557e+09 | AG26: =IFERROR(AVERAGE(E26:AF26),"NA") -> 4.8144888e+09 | AI26: =IFERROR(AG26*100/AG246,"NA") -> 21.712007 | AK26: =IFERROR(AG467*100/AG246,"NA") -> 0.54791374 | AM26: =IFERROR(AG688*100/AG246,"NA") -> 3.3420054
A27: Taxes on goods and services (current LCU) | B27: GC.TAX.GSRV.CN | C27: Botswana | D27: BWA | E27: 241700000 | F27: 276800000 | G27: .. | H27: .. | I27: .. | J27: .. | K27: .. | L27: .. | M27: .. | N27: .. | O27: .. | P27: 2416000000 | Q27: 3056870000 | R27: 4617050000 | S27: 4165830000 | T27: 4899330000 | U27: 5106980000 | V27: 5535880000 | W27: 5165780000 | X27: 5993110000 | Y27: 6379780000 | Z27: 6947860000 | AA27: 8182332000 | AB27: 7831390000 | AC27: 8565670000 | AD27: 8235650000 | AE27: 11566200000 | AF27: .. | AG27: =IFERROR(AVERAGE(E27:AF27),"NA") -> 5510234000 | AI27: =IFERROR(AG27*100/AG247,"NA") -> 5.947078 | AK27: =IFERROR(AG468*100/AG247,"NA") -> 11.65696 | AM27: =IFERROR(AG689*100/AG247,"NA") -> 12.011415
A28: Taxes on goods and services (current LCU) | B28: GC.TAX.GSRV.CN | C28: Brazil | D28: BRA | E28: .. | F28: .. | G28: .. | H28: .. | I28: .. | J28: .. | K28: .. | L28: .. | M28: .. | N28: .. | O28: .. | P28: .. | Q28: .. | R28: .. | S28: .. | T28: 2.6090588e+11 | U28: 2.9352672e+11 | V28: 3.1711196e+11 | W28: 3.3528224e+11 | X28: 3.3905181e+11 | Y28: 3.5488536e+11 | Z28: 3.5155679e+11 | AA28: 3.8089238e+11 | AB28: 4.1909054e+11 | AC28: 4.1069164e+11 | AD28: 3.7055036e+11 | AE28: 4.8545087e+11 | AF28: 4.838324e+11 | AG28: =IFERROR(AVERAGE(E28:AF28),"NA") -> 3.6944838e+11 | AI28: =IFERROR(AG28*100/AG248,"NA") -> 9.4143723 | AK28: =IFERROR(AG469*100/AG248,"NA") -> 0.99148007 | AM28: =IFERROR(AG690*100/AG248,"NA") -> 11.983306
A29: Taxes on goods and services (current LCU) | B29: GC.TAX.GSRV.CN | C29: British Virgin Islands | D29: VGB | E29: .. | F29: .. | G29: .. | H29: .. | I29: .. | J29: .. | K29: .. | L29: .. | M29: .. | N29: .. | O29: .. | P29: .. | Q29: .. | R29: .. | S29: .. | T29: .. | U29: .. | V29: .. | W29: .. | X29: .. | Y29: .. | Z29: .. | AA29: .. | AB29: .. | AC29: .. | AD29: .. | AE29: .. | AF29: .. | AG29: =IFERROR(AVERAGE(E29:AF29),"NA") -> NA | AI29: =IFERROR(AG29*100/AG249,"NA") -> NA | AK29: =IFERROR(AG470*100/AG249,"NA") -> NA | AM29: =IFERROR(AG691*100/AG249,"NA") -> NA
A30: Taxes on goods and services (current LCU) | B30: GC.TAX.GSRV.CN | C30: Brunei Darussalam | D30: BRN | E30: .. | F30: .. | G30: .. | H30: .. | I30: .. | J30: .. | K30: .. | L30: .. | M30: .. | N30: .. | O30: .. | P30: .. | Q30: .. | R30: .. | S30: .. | T30: .. | U30: .. | V30: .. | W30: .. | X30: .. | Y30: .. | Z30: .. | AA30: .. | AB30: .. | AC30: .. | AD30: .. | AE30: .. | AF30: .. | AG30: =IFERROR(AVERAGE(E30:AF30),"NA") -> NA | AI30: =IFERROR(AG30*100/AG250,"NA") -> NA | AK30: =IFERROR(AG471*100/AG250,"NA") -> NA | AM30: =IFERROR(AG692*100/AG250,"NA") -> NA
A31: Taxes on goods and services (current LCU) | B31: GC.TAX.GSRV.CN | C31: Bulgaria | D31: BGR | E31: 84295000 | F31: 155413000 | G31: 1436061000 | H31: 2813001000 | I31: 2873137000 | J31: 3482281000 | K31: 3734318000 | L31: 3848061000 | M31: 4766176000 | N31: 5980097000 | O31: 6979256000 | P31: 8229181000 | Q31: 9905665000 | R31: 11906712000 | S31: 10027516000 | T31: 9974193000 | U31: 10851832000 | V31: 11468262000 | W31: 12179246000 | X31: 12150530000 | Y31: 13252710000 | Z31: 14206394000 | AA31: 15210352000 | AB31: 15676626000 | AC31: 17839112000 | AD31: 17593419000 | AE31: 20021022000 | AF31: .. | AG31: =IFERROR(AVERAGE(E31:AF31),"NA") -> 9.1349951e+09 | AI31: =IFERROR(AG31*100/AG251,"NA") -> 13.424183 | AK31: =IFERROR(AG472*100/AG251,"NA") -> 0.18066 | AM31: =IFERROR(AG693*100/AG251,"NA") -> 5.219091
A32: Taxes on goods and services (current LCU) | B32: GC.TAX.GSRV.CN | C32: Burkina Faso | D32: BFA | E32: .. | F32: .. | G32: .. | H32: .. | I32: .. | J32: .. | K32: .. | L32: 130176282334 | M32: 1.4720929e+11 | N32: 177266962809 | O32: 185811088412 | P32: 194347024416 | Q32: 217313127652 | R32: 243815710870 | S32: 282942741937 | T32: 318436000000 | U32: 366763000000 | V32: 467465000000 | W32: 523444000000 | X32: 509613853289 | Y32: 5.287926e+11 | Z32: 601600000000 | AA32: 670207854137 | AB32: 7.5648209e+11 | AC32: 8.0569624e+11 | AD32: 7.0510547e+11 | AE32: 8.9842197e+11 | AF32: .. | AG32: =IFERROR(AVERAGE(E32:AF32),"NA") -> 4.3654552e+11 | AI32: =IFERROR(AG32*100/AG252,"NA") -> 8.5054231 | AK32: =IFERROR(AG473*100/AG252,"NA") -> 2.460246 | AM32: =IFERROR(AG694*100/AG252,"NA") -> 4.3564671
A33: Taxes on goods and services (current LCU) | B33: GC.TAX.GSRV.CN | C33: Burundi | D33: BDI | E33: 19512000000 | F33: 16316000000 | G33: 20744000000 | H33: 25304700000 | I33: 31640150000 | J33: .. | K33: .. | L33: .. | M33: .. | N33: .. | O33: .. | P33: .. | Q33: .. | R33: .. | S33: .. | T33: .. | U33: .. | V33: .. | W33: .. | X33: .. | Y33: .. | Z33: .. | AA33: .. | AB33: .. | AC33: .. | AD33: .. | AE33: .. | AF33: .. | AG33: =IFERROR(AVERAGE(E33:AF33),"NA") -> 22703370000 | AI33: =IFERROR(AG33*100/AG253,"NA") -> 0.82351818 | AK33: =IFERROR(AG474*100/AG253,"NA") -> 0.44399098 | AM33: =IFERROR(AG695*100/AG253,"NA") -> 0.41593262
A34: Taxes on goods and services (current LCU) | B34: GC.TAX.GSRV.CN | C34: Cabo Verde | D34: CPV | E34: .. | F34: .. | G34: .. | H34: .. | I34: .. | J34: .. | K34: .. | L34: .. | M34: .. | N34: .. | O34: 12539719163 | P34: 10612186419 | Q34: 12608527482 | R34: 14400328061 | S34: 11900628095 | T34: 12474668878 | U34: 14280767215 | V34: 12505077492 | W34: 13277051690 | X34: 12846075494 | Y34: 14236916226 | Z34: 14380605426 | AA34: 16592330072 | AB34: .. | AC34: .. | AD34: .. | AE34: .. | AF34: .. | AG34: =IFERROR(AVERAGE(E34:AF34),"NA") -> 1.3281145e+10 | AI34: =IFERROR(AG34*100/AG254,"NA") -> 10.288915 | AK34: =IFERROR(AG475*100/AG254,"NA") -> 4.1933458 | AM34: =IFERROR(AG696*100/AG254,"NA") -> 6.3904353
A35: Taxes on goods and services (current LCU) | B35: GC.TAX.GSRV.CN | C35: Cambodia | D35: KHM | E35: .. | F35: .. | G35: .. | H35: .. | I35: .. | J35: .. | K35: .. | L35: 703506430000 | M35: 689434530556 | N35: 941779628481 | O35: 1156725464334 | P35: 1368782937887 | Q35: 1889158000000 | R35: 2583454485900 | S35: 2317084365325 | T35: 2742246684797 | U35: 3093235600520 | V35: 3680680500000 | W35: 4174470300000 | X35: 5426488868518 | Y35: 6238464008082 | Z35: 7097514489320 | AA35: 8410736795545 | AB35: 10550116900000 | AC35: 13749754824212 | AD35: 10961572577726 | AE35: 10016364272406 | AF35: .. | AG35: =IFERROR(AVERAGE(E35:AF35),"NA") -> 4.8895786e+12 | AI35: =IFERROR(AG35*100/AG255,"NA") -> 9.8419962 | AK35: =IFERROR(AG476*100/AG255,"NA") -> 2.995123 | AM35: =IFERROR(AG697*100/AG255,"NA") -> 3.9723906
A36: Taxes on goods and services (current LCU) | B36: GC.TAX.GSRV.CN | C36: Cameroon | D36: CMR | E36: 138320000000 | F36: .. | G36: .. | H36: 187640000000 | I36: 230990000000 | J36: .. | K36: .. | L36: .. | M36: .. | N36: .. | O36: .. | P36: .. | Q36: .. | R36: .. | S36: .. | T36: .. | U36: .. | V36: 747453200000 | W36: 873151000000 | X36: 998600000000 | Y36: 1023100000000 | Z36: 1144800000000 | AA36: 1292000000000 | AB36: 1472441311897 | AC36: 1498911619273 | AD36: 1320841801794 | AE36: 1532897136597 | AF36: .. | AG36: =IFERROR(AVERAGE(E36:AF36),"NA") -> 9.585497e+11 | AI36: =IFERROR(AG36*100/AG256,"NA") -> 6.8490888 | AK36: =IFERROR(AG477*100/AG256,"NA") -> 2.322554 | AM36: =IFERROR(AG698*100/AG256,"NA") -> 4.1975948
A37: Taxes on goods and services (current LCU) | B37: GC.TAX.GSRV.CN | C37: Canada | D37: CAN | E37: 28373000000 | F37: 29721000000 | G37: 32223000000 | H37: 32750000000 | I37: 33934000000 | J37: 35874000000 | K37: 36886000000 | L37: 40122000000 | M37: 42169000000 | N37: 43701000000 | O37: 45281000000 | P37: 44772000000 | Q37: 44268000000 | R37: 39730000000 | S37: 40809000000 | T37: 43103000000 | U37: 43547000000 | V37: 43800000000 | W37: 45041000000 | X37: 47416000000 | Y37: 49051000000 | Z37: 50428000000 | AA37: 53913000000 | AB37: 55967000000 | AC37: 58114000000 | AD37: 56506000000 | AE37: 64606000000 | AF37: 72107000000 | AG37: =IFERROR(AVERAGE(E37:AF37),"NA") -> 4.4793286e+10 | AI37: =IFERROR(AG37*100/AG257,"NA") -> 2.7428267 | AK37: =IFERROR(AG478*100/AG257,"NA") -> 0.24116831 | AM37: =IFERROR(AG699*100/AG257,"NA") -> 9.9209642
A38: Taxes on goods and services (current LCU) | B38: GC.TAX.GSRV.CN | C38: Cayman Islands | D38: CYM | E38: .. | F38: .. | G38: .. | H38: .. | I38: .. | J38: .. | K38: .. | L38: .. | M38: .. | N38: .. | O38: .. | P38: .. | Q38: .. | R38: .. | S38: .. | T38: .. | U38: .. | V38: .. | W38: .. | X38: .. | Y38: .. | Z38: .. | AA38: .. | AB38: .. | AC38: .. | AD38: .. | AE38: .. | AF38: .. | AG38: =IFERROR(AVERAGE(E38:AF38),"NA") -> NA | AI38: =IFERROR(AG38*100/AG258,"NA") -> NA | AK38: =IFERROR(AG479*100/AG258,"NA") -> NA | AM38: =IFERROR(AG700*100/AG258,"NA") -> NA
A39: Taxes on goods and services (current LCU) | B39: GC.TAX.GSRV.CN | C39: Central African Republic | D39: CAF | E39: .. | F39: .. | G39: .. | H39: .. | I39: .. | J39: .. | K39: .. | L39: .. | M39: .. | N39: 17241489275 | O39: .. | P39: .. | Q39: .. | R39: .. | S39: .. | T39: .. | U39: .. | V39: .. | W39: .. | X39: .. | Y39: .. | Z39: .. | AA39: .. | AB39: .. | AC39: 46617690698 | AD39: 6.5594805e+10 | AE39: 60260364173 | AF39: .. | AG39: =IFERROR(AVERAGE(E39:AF39),"NA") -> 4.7428587e+10 | AI39: =IFERROR(AG39*100/AG259,"NA") -> 5.1847997 | AK39: =IFERROR(AG480*100/AG259,"NA") -> 2.7669079 | AM39: =IFERROR(AG701*100/AG259,"NA") -> 2.3348734
A40: Taxes on goods and services (current LCU) | B40: GC.TAX.GSRV.CN | C40: Chad | D40: TCD | E40: .. | F40: .. | G40: .. | H40: .. | I40: .. | J40: .. | K40: .. | L40: .. | M40: .. | N40: .. | O40: .. | P40: .. | Q40: .. | R40: .. | S40: .. | T40: .. | U40: .. | V40: .. | W40: .. | X40: .. | Y40: .. | Z40: .. | AA40: .. | AB40: .. | AC40: .. | AD40: .. | AE40: .. | AF40: .. | AG40: =IFERROR(AVERAGE(E40:AF40),"NA") -> NA | AI40: =IFERROR(AG40*100/AG260,"NA") -> NA | AK40: =IFERROR(AG481*100/AG260,"NA") -> NA | AM40: =IFERROR(AG702*100/AG260,"NA") -> NA
A41: Taxes on goods and services (current LCU) | B41: GC.TAX.GSRV.CN | C41: Channel Islands | D41: CHI | E41: .. | F41: .. | G41: .. | H41: .. | I41: .. | J41: .. | K41: .. | L41: .. | M41: .. | N41: .. | O41: .. | P41: .. | Q41: .. | R41: .. | S41: .. | T41: .. | U41: .. | V41: .. | W41: .. | X41: .. | Y41: .. | Z41: .. | AA41: .. | AB41: .. | AC41: .. | AD41: .. | AE41: .. | AF41: .. | AG41: =IFERROR(AVERAGE(E41:AF41),"NA") -> NA | AI41: =IFERROR(AG41*100/AG261,"NA") -> NA | AK41: =IFERROR(AG482*100/AG261,"NA") -> NA | AM41: =IFERROR(AG703*100/AG261,"NA") -> NA
A42: Taxes on goods and services (current LCU) | B42: GC.TAX.GSRV.CN | C42: Chile | D42: CHL | E42: 2604820000000 | F42: 3066430000000 | G42: 3395780000000 | H42: 3585480000000 | I42: 3629350000000 | J42: 4133360000000 | K42: 4438730000000 | L42: 4803990000000 | M42: 5191940000000 | N42: 5807570000000 | O42: 6499000000000 | P42: 6894000000000 | Q42: 8081956000000 | R42: 8987497000000 | S42: 8424530000000 | T42: 10759883000000 | U42: 12109275514000 | V42: 12436769000000 | W42: 14089800000000 | X42: 15048086065920 | Y42: 16281146774000 | Z42: 17498066663000 | AA42: 19047205000000 | AB42: 19705850892630 | AC42: 18888751432350 | AD42: 19740091747900 | AE42: 26985427586430 | AF42: .. | AG42: =IFERROR(AVERAGE(E42:AF42),"NA") -> 1.0449437e+13 | AI42: =IFERROR(AG42*100/AG262,"NA") -> 9.4472125 | AK42: =IFERROR(AG483*100/AG262,"NA") -> 0.34229696 | AM42: =IFERROR(AG704*100/AG262,"NA") -> 6.3054997
A43: Taxes on goods and services (current LCU) | B43: GC.TAX.GSRV.CN | C43: China | D43: CHN | E43: .. | F43: .. | G43: .. | H43: .. | I43: .. | J43: .. | K43: .. | L43: .. | M43: .. | N43: .. | O43: 1455981640000 | P43: 1306490000000 | Q43: 1738222520000 | R43: 2105028000000 | S43: 2443669999800 | T43: 2.9333192e+12 | U43: 3407197000000 | V43: 3679180000000 | W43: 3766687010000 | X43: 3911535720000 | Y43: 3902294220000 | Z43: 4.0535399e+12 | AA43: 4.7508655e+12 | AB43: 4961410558200 | AC43: 5071370380000 | AD43: 4910425350000 | AE43: 5361119640000 | AF43: .. | AG43: =IFERROR(AVERAGE(E43:AF43),"NA") -> 3.5151963e+12 | AI43: =IFERROR(AG43*100/AG263,"NA") -> 7.8198475 | AK43: =IFERROR(AG484*100/AG263,"NA") -> 0.46575801 | AM43: =IFERROR(AG705*100/AG263,"NA") -> 4.1425574
A44: Taxes on goods and services (current LCU) | B44: GC.TAX.GSRV.CN | C44: Colombia | D44: COL | E44: .. | F44: .. | G44: .. | H44: 7048245000000 | I44: .. | J44: .. | K44: .. | L44: .. | M44: 1.5126816e+13 | N44: .. | O44: .. | P44: .. | Q44: .. | R44: 30832966000000 | S44: 29454028000000 | T44: 33010918000000 | U44: 38826137000000 | V44: 41420911000000 | W44: 46076455000000 | X44: 5.21462e+13 | Y44: 5.5441002e+13 | Z44: 5.6456011e+13 | AA44: 5.8722469e+13 | AB44: 6.4140593e+13 | AC44: 7.8141065e+13 | AD44: 6.7921581e+13 | AE44: 8.641552e+13 | AF44: 113253757652851 | AG44: =IFERROR(AVERAGE(E44:AF44),"NA") -> 5.1437334e+13 | AI44: =IFERROR(AG44*100/AG264,"NA") -> 9.2435084 | AK44: =IFERROR(AG485*100/AG264,"NA") -> 0.72767808 | AM44: =IFERROR(AG706*100/AG264,"NA") -> 7.4433927
A45: Taxes on goods and services (current LCU) | B45: GC.TAX.GSRV.CN | C45: Comoros | D45: COM | E45: .. | F45: .. | G45: .. | H45: .. | I45: .. | J45: .. | K45: .. | L45: .. | M45: .. | N45: .. | O45: .. | P45: .. | Q45: .. | R45: .. | S45: .. | T45: .. | U45: .. | V45: .. | W45: .. | X45: .. | Y45: .. | Z45: .. | AA45: .. | AB45: .. | AC45: .. | AD45: .. | AE45: .. | AF45: .. | AG45: =IFERROR(AVERAGE(E45:AF45),"NA") -> NA | AI45: =IFERROR(AG45*100/AG265,"NA") -> NA | AK45: =IFERROR(AG486*100/AG265,"NA") -> NA | AM45: =IFERROR(AG707*100/AG265,"NA") -> NA
A46: Taxes on goods and services (current LCU) | B46: GC.TAX.GSRV.CN | C46: Congo, Dem. Rep. | D46: COD | E46: .. | F46: .. | G46: .. | H46: .. | I46: .. | J46: .. | K46: .. | L46: .. | M46: .. | N46: .. | O46: .. | P46: .. | Q46: .. | R46: .. | S46: .. | T46: .. | U46: .. | V46: .. | W46: .. | X46: .. | Y46: .. | Z46: .. | AA46: .. | AB46: .. | AC46: .. | AD46: .. | AE46: .. | AF46: .. | AG46: =IFERROR(AVERAGE(E46:AF46),"NA") -> NA | AI46: =IFERROR(AG46*100/AG266,"NA") -> NA | AK46: =IFERROR(AG487*100/AG266,"NA") -> NA | AM46: =IFERROR(AG708*100/AG266,"NA") -> NA
A47: Taxes on goods and services (current LCU) | B47: GC.TAX.GSRV.CN | C47: Congo, Rep. | D47: COG | E47: .. | F47: .. | G47: .. | H47: .. | I47: .. | J47: .. | K47: 142500000000 | L47: 135300000000 | M47: 102400000000 | N47: 87100098179 | O47: 92148533157 | P47: 94900000000 | Q47: 111798000000 | R47: 124221000000 | S47: 175417000000 | T47: 197860000000 | U47: 280306065756 | V47: 293264902491 | W47: 309941523413 | X47: 356374746685 | Y47: 345302700000 | Z47: 346189900000 | AA47: 255779723659 | AB47: 212512828108 | AC47: 228304084143 | AD47: 220251384974 | AE47: .. | AF47: .. | AG47: =IFERROR(AVERAGE(E47:AF47),"NA") -> 2.0559362e+11 | AI47: =IFERROR(AG47*100/AG267,"NA") -> 4.0723337 | AK47: =IFERROR(AG488*100/AG267,"NA") -> 1.6156457 | AM47: =IFERROR(AG709*100/AG267,"NA") -> 3.858738
A48: Taxes on goods and services (current LCU) | B48: GC.TAX.GSRV.CN | C48: Costa Rica | D48: CRI | E48: 138690000000 | F48: 200250000000 | G48: 241690000000 | H48: 296580000000 | I48: 348800000000 | J48: 408100000000 | K48: 479700000000 | L48: .. | M48: .. | N48: 692346000000 | O48: 827846000000 | P48: 1.0218445e+12 | Q48: 1.2874984e+12 | R48: 1.4854127e+12 | S48: 1.3615626e+12 | T48: 1.4983291e+12 | U48: 1.6951004e+12 | V48: 1.8280961e+12 | W48: 1962940000000 | X48: 2.0786479e+12 | Y48: 2.2462697e+12 | Z48: 2.3783663e+12 | AA48: 2.4338757e+12 | AB48: 2.4799129e+12 | AC48: 2.6277407e+12 | AD48: 2.4408373e+12 | AE48: 3.0174531e+12 | AF48: .. | AG48: =IFERROR(AVERAGE(E48:AF48),"NA") -> 1.4191156e+12 | AI48: =IFERROR(AG48*100/AG268,"NA") -> 7.5611045 | AK48: =IFERROR(AG489*100/AG268,"NA") -> 1.1445494 | AM48: =IFERROR(AG710*100/AG268,"NA") -> 3.6775853
A49: Taxes on goods and services (current LCU) | B49: GC.TAX.GSRV.CN | C49: Cote d'Ivoire | D49: CIV | E49: 163700000000 | F49: .. | G49: .. | H49: .. | I49: .. | J49: .. | K49: 295500000000 | L49: 296400000000 | M49: 254100000000 | N49: 255900000000 | O49: 282400000000 | P49: 275000000000 | Q49: 270800000000 | R49: 348460000000 | S49: 494228000000 | T49: 444782000000 | U49: 329545000000 | V49: 549899000000 | W49: 556858000000 | X49: 6.0549425e+11 | Y49: 1.206346e+12 | Z49: 1333894502983 | AA49: 1.4262273e+12 | AB49: 1.5379982e+12 | AC49: 1.6814547e+12 | AD49: 1.8789978e+12 | AE49: 2.1555424e+12 | AF49: .. | AG49: =IFERROR(AVERAGE(E49:AF49),"NA") -> 7.5652396e+11 | AI49: =IFERROR(AG49*100/AG269,"NA") -> 3.8336937 | AK49: =IFERROR(AG490*100/AG269,"NA") -> 4.3561805 | AM49: =IFERROR(AG711*100/AG269,"NA") -> 2.8785341
A50: Taxes on goods and services (current LCU) | B50: GC.TAX.GSRV.CN | C50: Croatia | D50: HRV | E50: 2438171000 | F50: 2610312000 | G50: 2840045000 | H50: 3586609000 | I50: 3568007000 | J50: 4043511000 | K50: 4330759000 | L50: 5000553000 | M50: 5434487000 | N50: 5706543000 | O50: 6100087000 | P50: 6647152000 | Q50: 7079213000 | R50: 7590647000 | S50: 6914721000 | T50: 7122193000 | U50: 7022725000 | V50: 7388767000 | W50: 7690652000 | X50: 7774790000 | Y50: 8225355000 | Z50: 8585611000 | AA50: 9076298000 | AB50: 9676364000 | AC50: 10261628000 | AD50: 8963027000 | AE50: 10506875000 | AF50: .. | AG50: =IFERROR(AVERAGE(E50:AF50),"NA") -> 6.5253741e+09 | AI50: =IFERROR(AG50*100/AG270,"NA") -> 16.609942 | AK50: =IFERROR(AG491*100/AG270,"NA") -> 0.67552121 | AM50: =IFERROR(AG712*100/AG270,"NA") -> 2.8075053
A51: Taxes on goods and services (current LCU) | B51: GC.TAX.GSRV.CN | C51: Cuba | D51: CUB | E51: .. | F51: .. | G51: .. | H51: .. | I51: .. | J51: .. | K51: .. | L51: .. | M51: .. | N51: .. | O51: .. | P51: .. | Q51: .. | R51: .. | S51: .. | T51: .. | U51: .. | V51: .. | W51: .. | X51: .. | Y51: .. | Z51: .. | AA51: .. | AB51: .. | AC51: .. | AD51: .. | AE51: .. | AF51: .. | AG51: =IFERROR(AVERAGE(E51:AF51),"NA") -> NA | AI51: =IFERROR(AG51*100/AG271,"NA") -> NA | AK51: =IFERROR(AG492*100/AG271,"NA") -> NA | AM51: =IFERROR(AG713*100/AG271,"NA") -> NA
A52: Taxes on goods and services (current LCU) | B52: GC.TAX.GSRV.CN | C52: Curacao | D52: CUW | E52: .. | F52: .. | G52: .. | H52: .. | I52: .. | J52: .. | K52: .. | L52: .. | M52: .. | N52: .. | O52: .. | P52: .. | Q52: .. | R52: .. | S52: .. | T52: .. | U52: .. | V52: .. | W52: .. | X52: .. | Y52: .. | Z52: .. | AA52: .. | AB52: .. | AC52: .. | AD52: .. | AE52: .. | AF52: .. | AG52: =IFERROR(AVERAGE(E52:AF52),"NA") -> NA | AI52: =IFERROR(AG52*100/AG272,"NA") -> NA | AK52: =IFERROR(AG493*100/AG272,"NA") -> NA | AM52: =IFERROR(AG714*100/AG272,"NA") -> NA
A53: Taxes on goods and services (current LCU) | B53: GC.TAX.GSRV.CN | C53: Cyprus | D53: CYP | E53: 1.0723183e+09 | F53: 1.1064903e+09 | G53: 1.1148624e+09 | H53: 1.3175026e+09 | I53: 1.3795248e+09 | J53: 1.748241e+09 | K53: 1.965746e+09 | L53: 2.0788554e+09 | M53: 2.6256078e+09 | N53: 3.0717237e+09 | O53: 3.3832017e+09 | P53: 3.6787898e+09 | Q53: 4.194104e+09 | R53: 4.5430004e+09 | S53: 2319600000 | T53: 2401300000 | U53: 2362100000 | V53: 2415900000 | W53: 2210500000 | X53: 2364800000 | Y53: 2366700000 | Z53: 2515500000 | AA53: 2653600000 | AB53: 2895149000 | AC53: 2977400000 | AD53: 2589800000 | AE53: 3028600000 | AF53: .. | AG53: =IFERROR(AVERAGE(E53:AF53),"NA") -> 2.4585525e+09 | AI53: =IFERROR(AG53*100/AG273,"NA") -> 14.960181 | AK53: =IFERROR(AG494*100/AG273,"NA") -> 0.49656062 | AM53: =IFERROR(AG715*100/AG273,"NA") -> 11.159525
A54: Taxes on goods and services (current LCU) | B54: GC.TAX.GSRV.CN | C54: Czechia | D54: CZE | E54: 161054000000 | F54: 182868000000 | G54: 193252000000 | H54: 204846000000 | I54: 229057000000 | J54: 234141000000 | K54: 218103000000 | L54: 221493000000 | M54: 235090000000 | N54: 277981000000 | O54: 284990000000 | P54: 296428000000 | Q54: 334931000000 | R54: 337210000000 | S54: 345044000000 | T54: 358195000000 | U54: 393960000000 | V54: 412824000000 | W54: 425882000000 | X54: 413466000000 | Y54: 457326000000 | Z54: 470801000000 | AA54: 498064000000 | AB54: 506248000000 | AC54: 536677000000 | AD54: 505581000000 | AE54: 528342000000 | AF54: .. | AG54: =IFERROR(AVERAGE(E54:AF54),"NA") -> 3.431057e+11 | AI54: =IFERROR(AG54*100/AG274,"NA") -> 8.9775468 | AK54: =IFERROR(AG495*100/AG274,"NA") -> 0.32758997 | AM54: =IFERROR(AG716*100/AG274,"NA") -> 4.9918554
A55: Taxes on goods and services (current LCU) | B55: GC.TAX.GSRV.CN | C55: Denmark | D55: DNK | E55: 153731000000 | F55: 165823000000 | G55: 175411000000 | H55: 190970000000 | I55: 199946000000 | J55: 202909000000 | K55: 209354000000 | L55: 218153000000 | M55: 219494000000 | N55: 232863000000 | O55: 249502000000 | P55: 263096000000 | Q55: 277904000000 | R55: 268968000000 | S55: 255277000000 | T55: 264440000000 | U55: 270457000000 | V55: 278525000000 | W55: 279880000000 | X55: 281603000000 | Y55: 289320000000 | Z55: 299951000000 | AA55: 307953000000 | AB55: 318695000000 | AC55: 316302000000 | AD55: 324118000000 | AE55: 336382000000 | AF55: .. | AG55: =IFERROR(AVERAGE(E55:AF55),"NA") -> 2.5374174e+11 | AI55: =IFERROR(AG55*100/AG275,"NA") -> 14.397136 | AK55: =IFERROR(AG496*100/AG275,"NA") -> 0.020085722 | AM55: =IFERROR(AG717*100/AG275,"NA") -> 16.243639
A56: Taxes on goods and services (current LCU) | B56: GC.TAX.GSRV.CN | C56: Djibouti | D56: DJI | E56: .. | F56: .. | G56: .. | H56: .. | I56: .. | J56: .. | K56: .. | L56: .. | M56: .. | N56: .. | O56: .. | P56: .. | Q56: .. | R56: .. | S56: .. | T56: .. | U56: .. | V56: .. | W56: .. | X56: .. | Y56: .. | Z56: .. | AA56: .. | AB56: .. | AC56: .. | AD56: .. | AE56: .. | AF56: .. | AG56: =IFERROR(AVERAGE(E56:AF56),"NA") -> NA | AI56: =IFERROR(AG56*100/AG276,"NA") -> NA | AK56: =IFERROR(AG497*100/AG276,"NA") -> NA | AM56: =IFERROR(AG718*100/AG276,"NA") -> NA
A57: Taxes on goods and services (current LCU) | B57: GC.TAX.GSRV.CN | C57: Dominica | D57: DMA | E57: .. | F57: .. | G57: .. | H57: .. | I57: .. | J57: .. | K57: .. | L57: .. | M57: .. | N57: .. | O57: .. | P57: .. | Q57: .. | R57: .. | S57: .. | T57: .. | U57: .. | V57: .. | W57: .. | X57: .. | Y57: .. | Z57: .. | AA57: .. | AB57: .. | AC57: .. | AD57: .. | AE57: .. | AF57: .. | AG57: =IFERROR(AVERAGE(E57:AF57),"NA") -> NA | AI57: =IFERROR(AG57*100/AG277,"NA") -> NA | AK57: =IFERROR(AG498*100/AG277,"NA") -> NA | AM57: =IFERROR(AG719*100/AG277,"NA") -> NA
A58: Taxes on goods and services (current LCU) | B58: GC.TAX.GSRV.CN | C58: Dominican Republic | D58: DOM | E58: 8949100000 | F58: 9480000000 | G58: 12717900000 | H58: 14550600000 | I58: 13832900000 | J58: 14037800000 | K58: 2.2450057e+10 | L58: 2.498578e+10 | M58: 3.5292878e+10 | N58: 5.4785167e+10 | O58: 7.8843889e+10 | P58: 1.0590892e+11 | Q58: 137442908353 | R58: 1.5074953e+11 | S58: 1.4194505e+11 | T58: 1.6347404e+11 | U58: 1.8184566e+11 | V58: 193340000000 | W58: 2.1917121e+11 | X58: 2.335148e+11 | Y58: 2.4165894e+11 | Z58: 2.6138231e+11 | AA58: 2.8408784e+11 | AB58: 3.3589059e+11 | AC58: 3.6628591e+11 | AD58: 3.2420726e+11 | AE58: 4.4963881e+11 | AF58: .. | AG58: =IFERROR(AVERAGE(E58:AF58),"NA") -> 1.5112851e+11 | AI58: =IFERROR(AG58*100/AG278,"NA") -> 7.1732966 | AK58: =IFERROR(AG499*100/AG278,"NA") -> 1.2330208 | AM58: =IFERROR(AG720*100/AG278,"NA") -> 3.5359233
A59: Taxes on goods and services (current LCU) | B59: GC.TAX.GSRV.CN | C59: Ecuador | D59: ECU | E59: .. | F59: .. | G59: .. | H59: .. | I59: .. | J59: .. | K59: .. | L59: .. | M59: .. | N59: .. | O59: .. | P59: .. | Q59: .. | R59: .. | S59: .. | T59: .. | U59: .. | V59: .. | W59: 7.1818387e+09 | X59: 7.6018046e+09 | Y59: 7.7260318e+09 | Z59: 6.8127601e+09 | AA59: 7.5346814e+09 | AB59: 7.751074e+09 | AC59: 7.5715227e+09 | AD59: 6.1875834e+09 | AE59: 7.0904426e+09 | AF59: 7.5760486e+09 | AG59: =IFERROR(AVERAGE(E59:AF59),"NA") -> 7.3033788e+09 | AI59: =IFERROR(AG59*100/AG279,"NA") -> 11.344058 | AK59: =IFERROR(AG500*100/AG279,"NA") -> 3.9043972 | AM59: =IFERROR(AG721*100/AG279,"NA") -> 6.5308069
A60: Taxes on goods and services (current LCU) | B60: GC.TAX.GSRV.CN | C60: Egypt, Arab Rep. | D60: EGY | E60: 9738000000 | F60: 10901000000 | G60: 11862000000 | H60: .. | I60: .. | J60: .. | K60: .. | L60: 21273000000 | M60: 23443000000 | N60: 26834000000 | O60: 31743000000 | P60: 35026500000 | Q60: 39896700000 | R60: 50281300000 | S60: 63196000000 | T60: 73509500000 | U60: 83390300000 | V60: 95169000000 | W60: 106829000000 | X60: 106719000000 | Y60: 140559000000 | Z60: .. | AA60: .. | AB60: .. | AC60: .. | AD60: .. | AE60: .. | AF60: .. | AG60: =IFERROR(AVERAGE(E60:AF60),"NA") -> 5.4727665e+10 | AI60: =IFERROR(AG60*100/AG280,"NA") -> 2.781791 | AK60: =IFERROR(AG501*100/AG280,"NA") -> 0.61105856 | AM60: =IFERROR(AG722*100/AG280,"NA") -> 3.0492563
A61: Taxes on goods and services (current LCU) | B61: GC.TAX.GSRV.CN | C61: El Salvador | D61: SLV | E61: .. | F61: .. | G61: .. | H61: 635560000 | I61: 632810000 | J61: 744210000 | K61: 859500000 | L61: 904300000 | M61: 1000500000 | N61: 1037500000 | O61: 1221900000 | P61: 1490800000 | Q61: 1678800000 | R61: 1802200000 | S61: 1440300000 | T61: 1660800000 | U61: 1692850000 | V61: 2092300000 | W61: 2179600000 | X61: 2.2097163e+09 | Y61: 2.3265326e+09 | Z61: 2.3185936e+09 | AA61: 2.4766919e+09 | AB61: 2656300000 | AC61: 2717600000 | AD61: 2513100000 | AE61: 3202500000 | AF61: .. | AG61: =IFERROR(AVERAGE(E61:AF61),"NA") -> 1.7289569e+09 | AI61: =IFERROR(AG61*100/AG281,"NA") -> 9.3995602 | AK61: =IFERROR(AG502*100/AG281,"NA") -> 1.0412718 | AM61: =IFERROR(AG723*100/AG281,"NA") -> 5.8650945
A62: Taxes on goods and services (current LCU) | B62: GC.TAX.GSRV.CN | C62: Equatorial Guinea | D62: GNQ | E62: .. | F62: .. | G62: .. | H62: .. | I62: .. | J62: .. | K62: .. | L62: .. | M62: .. | N62: .. | O62: .. | P62: 28847000000 | Q62: 30267000000 | R62: 30251000000 | S62: 44000000000 | T62: 45608000000 | U62: 54279488191 | V62: 95679658509 | W62: 56629709183 | X62: 63157939488 | Y62: 97488000810 | Z62: 79513208976 | AA62: 75245419477 | AB62: 93660497268 | AC62: 9.6991502e+10 | AD62: 8.4856362e+10 | AE62: 6.2236142e+10 | AF62: .. | AG62: =IFERROR(AVERAGE(E62:AF62),"NA") -> 6.4919433e+10 | AI62: =IFERROR(AG62*100/AG282,"NA") -> 1.2428859 | AK62: =IFERROR(AG503*100/AG282,"NA") -> 0.32792287 | AM62: =IFERROR(AG724*100/AG282,"NA") -> 10.531205
A63: Taxes on goods and services (current LCU) | B63: GC.TAX.GSRV.CN | C63: Eritrea | D63: ERI | E63: .. | F63: .. | G63: .. | H63: .. | I63: .. | J63: .. | K63: .. | L63: .. | M63: .. | N63: .. | O63: .. | P63: .. | Q63: .. | R63: .. | S63: .. | T63: .. | U63: .. | V63: .. | W63: .. | X63: .. | Y63: .. | Z63: .. | AA63: .. | AB63: .. | AC63: .. | AD63: .. | AE63: .. | AF63: .. | AG63: =IFERROR(AVERAGE(E63:AF63),"NA") -> NA | AI63: =IFERROR(AG63*100/AG283,"NA") -> NA | AK63: =IFERROR(AG504*100/AG283,"NA") -> NA | AM63: =IFERROR(AG725*100/AG283,"NA") -> NA
A64: Taxes on goods and services (current LCU) | B64: GC.TAX.GSRV.CN | C64: Estonia | D64: EST | E64: 349340000 | F64: 468810000 | G64: 591100000 | H64: 606850000 | I64: 609420000 | J64: 736630000 | K64: 838890000 | L64: 948380000 | M64: 1029130000 | N64: 1208140000 | O64: 1384820000 | P64: 1762170000 | Q64: 2120140000 | R64: 1930540000 | S64: 1996450000 | T64: 1952070000 | U64: 2162440000 | V64: 2391070000 | W64: 2456610000 | X64: 2680860000 | Y64: 2857870000 | Z64: 3107670000 | AA64: 3281220000 | AB64: 3506130000 | AC64: 3871240000 | AD64: 3580910000 | AE64: 4109660000 | AF64: .. | AG64: =IFERROR(AVERAGE(E64:AF64),"NA") -> 1.9458726e+09 | AI64: =IFERROR(AG64*100/AG284,"NA") -> 12.48258 | AK64: =IFERROR(AG505*100/AG284,"NA") -> 0.0085888398 | AM64: =IFERROR(AG726*100/AG284,"NA") -> 7.1400819
A65: Taxes on goods and services (current LCU) | B65: GC.TAX.GSRV.CN | C65: Eswatini | D65: SWZ | E65: .. | F65: .. | G65: .. | H65: .. | I65: .. | J65: .. | K65: .. | L65: .. | M65: .. | N65: .. | O65: .. | P65: .. | Q65: .. | R65: .. | S65: .. | T65: .. | U65: .. | V65: .. | W65: .. | X65: .. | Y65: .. | Z65: .. | AA65: .. | AB65: .. | AC65: .. | AD65: .. | AE65: .. | AF65: .. | AG65: =IFERROR(AVERAGE(E65:AF65),"NA") -> NA | AI65: =IFERROR(AG65*100/AG285,"NA") -> NA | AK65: =IFERROR(AG506*100/AG285,"NA") -> NA | AM65: =IFERROR(AG727*100/AG285,"NA") -> NA
A66: Taxes on goods and services (current LCU) | B66: GC.TAX.GSRV.CN | C66: Ethiopia | D66: ETH | E66: 859100000 | F66: 1053000000 | G66: 1487800000 | H66: 1586500000 | I66: 1561200000 | J66: .. | K66: 1077500000 | L66: 1247503522 | M66: 1397500000 | N66: 1625800000 | O66: 1817200000 | P66: 2326400000 | Q66: 2657300000 | R66: 4631600000 | S66: 5199600000 | T66: 5582400000 | U66: 12048730000 | V66: 1.8982385e+10 | W66: 1.9245715e+10 | X66: 4.3707217e+10 | Y66: 5.0160467e+10 | Z66: 5.7297646e+10 | AA66: 6.2648025e+10 | AB66: 6.8139392e+10 | AC66: 8.1033081e+10 | AD66: 9.1304668e+10 | AE66: .. | AF66: .. | AG66: =IFERROR(AVERAGE(E66:AF66),"NA") -> 2.1547109e+10 | AI66: =IFERROR(AG66*100/AG286,"NA") -> 2.1040664 | AK66: =IFERROR(AG507*100/AG286,"NA") -> 1.7302257 | AM66: =IFERROR(AG728*100/AG286,"NA") -> 1.5365523
A67: Taxes on goods and services (current LCU) | B67: GC.TAX.GSRV.CN | C67: Faroe Islands | D67: FRO | E67: .. | F67: .. | G67: .. | H67: .. | I67: .. | J67: .. | K67: .. | L67: .. | M67: .. | N67: .. | O67: .. | P67: .. | Q67: .. | R67: .. | S67: .. | T67: .. | U67: .. | V67: .. | W67: .. | X67: .. | Y67: .. | Z67: .. | AA67: .. | AB67: .. | AC67: .. | AD67: .. | AE67: .. | AF67: .. | AG67: =IFERROR(AVERAGE(E67:AF67),"NA") -> NA | AI67: =IFERROR(AG67*100/AG287,"NA") -> NA | AK67: =IFERROR(AG508*100/AG287,"NA") -> NA | AM67: =IFERROR(AG729*100/AG287,"NA") -> NA
A68: Taxes on goods and services (current LCU) | B68: GC.TAX.GSRV.CN | C68: Fiji | D68: FJI | E68: 222600000 | F68: 238250000 | G68: .. | H68: .. | I68: .. | J68: .. | K68: .. | L68: .. | M68: .. | N68: 498170000 | O68: 511060000 | P68: 579764321 | Q68: 3.5285495e+08 | R68: 5.5395729e+08 | S68: 4.885955e+08 | T68: 5.9915351e+08 | U68: 7.6735102e+08 | V68: 7.8787394e+08 | W68: 9.6127602e+08 | X68: 1.0650053e+09 | Y68: 1.1829715e+09 | Z68: 1.1513579e+09 | AA68: 1.3117541e+09 | AB68: 1.4313258e+09 | AC68: 1.3972222e+09 | AD68: 8.9288511e+08 | AE68: 6.891001e+08 | AF68: .. | AG68: =IFERROR(AVERAGE(E68:AF68),"NA") -> 7.8412643e+08 | AI68: =IFERROR(AG68*100/AG288,"NA") -> 11.9188 | AK68: =IFERROR(AG509*100/AG288,"NA") -> 5.4103898 | AM68: =IFERROR(AG730*100/AG288,"NA") -> 7.5930787
A69: Taxes on goods and services (current LCU) | B69: GC.TAX.GSRV.CN | C69: Finland | D69: FIN | E69: 13206000000 | F69: 13813000000 | G69: 15878000000 | H69: 16975000000 | I69: 17808000000 | J69: 18494000000 | K69: 18804000000 | L69: 19801000000 | M69: 20893000000 | N69: 21514000000 | O69: 22329000000 | P69: 23307000000 | Q69: 24129000000 | R69: 24585000000 | S69: 23912000000 | T69: 24791000000 | U69: 27789000000 | V69: 28773000000 | W69: 30025000000 | X69: 30285000000 | Y69: 30441000000 | Z69: 31994000000 | AA69: 32547000000 | AB69: 34032000000 | AC69: 34610000000 | AD69: 34105000000 | AE69: 35655000000 | AF69: .. | AG69: =IFERROR(AVERAGE(E69:AF69),"NA") -> 2.4833148e+10 | AI69: =IFERROR(AG69*100/AG289,"NA") -> 13.677888 | AK69: =IFERROR(AG510*100/AG289,"NA") -> 0.0022031661 | AM69: =IFERROR(AG731*100/AG289,"NA") -> 6.5911387
A70: Taxes on goods and services (current LCU) | B70: GC.TAX.GSRV.CN | C70: France | D70: FRA | E70: 136605000000 | F70: 145319000000 | G70: 149933000000 | H70: 155170000000 | I70: 161383000000 | J70: 163450000000 | K70: 165495000000 | L70: 170737000000 | M70: 173773000000 | N70: 178072000000 | O70: 182603000000 | P70: 189088000000 | Q70: 191535000000 | R70: 189998000000 | S70: 182689000000 | T70: 189329000000 | U70: 195945000000 | V70: 200466000000 | W70: 205806000000 | X70: 210648000000 | Y70: 216894000000 | Z70: 221278000000 | AA70: 232445000000 | AB70: 239562000000 | AC70: 247091000000 | AD70: 231614000000 | AE70: 225647000000 | AF70: .. | AG70: =IFERROR(AVERAGE(E70:AF70),"NA") -> 1.9083611e+11 | AI70: =IFERROR(AG70*100/AG290,"NA") -> 10.017845 | AK70: =IFERROR(AG511*100/AG290,"NA") -> -0.0024789065 | AM70: =IFERROR(AG732*100/AG290,"NA") -> 10.592644
A71: Taxes on goods and services (current LCU) | B71: GC.TAX.GSRV.CN | C71: French Polynesia | D71: PYF | E71: .. | F71: .. | G71: .. | H71: .. | I71: .. | J71: .. | K71: .. | L71: .. | M71: .. | N71: .. | O71: .. | P71: .. | Q71: .. | R71: .. | S71: .. | T71: .. | U71: .. | V71: .. | W71: .. | X71: .. | Y71: .. | Z71: .. | AA71: .. | AB71: .. | AC71: .. | AD71: .. | AE71: .. | AF71: .. | AG71: =IFERROR(AVERAGE(E71:AF71),"NA") -> NA | AI71: =IFERROR(AG71*100/AG291,"NA") -> NA | AK71: =IFERROR(AG512*100/AG291,"NA") -> NA | AM71: =IFERROR(AG733*100/AG291,"NA") -> NA
A72: Taxes on goods and services (current LCU) | B72: GC.TAX.GSRV.CN | C72: Gabon | D72: GAB | E72: .. | F72: .. | G72: .. | H72: .. | I72: .. | J72: .. | K72: .. | L72: .. | M72: .. | N72: .. | O72: .. | P72: .. | Q72: .. | R72: .. | S72: .. | T72: .. | U72: .. | V72: 194850000000 | W72: 291471000000 | X72: 298931000000 | Y72: 181697000000 | Z72: 229170510960 | AA72: 2.2768714e+11 | AB72: 160393022541 | AC72: 203738833384 | AD72: .. | AE72: .. | AF72: .. | AG72: =IFERROR(AVERAGE(E72:AF72),"NA") -> 2.2349231e+11 | AI72: =IFERROR(AG72*100/AG292,"NA") -> 3.4388341 | AK72: =IFERROR(AG513*100/AG292,"NA") -> 4.9747319 | AM72: =IFERROR(AG734*100/AG292,"NA") -> 7.5982255
A73: Taxes on goods and services (current LCU) | B73: GC.TAX.GSRV.CN | C73: Gambia, The | D73: GMB | E73: .. | F73: .. | G73: .. | H73: .. | I73: .. | J73: .. | K73: .. | L73: .. | M73: .. | N73: .. | O73: .. | P73: .. | Q73: .. | R73: .. | S73: .. | T73: .. | U73: .. | V73: .. | W73: .. | X73: .. | Y73: .. | Z73: .. | AA73: .. | AB73: .. | AC73: .. | AD73: .. | AE73: .. | AF73: .. | AG73: =IFERROR(AVERAGE(E73:AF73),"NA") -> NA | AI73: =IFERROR(AG73*100/AG293,"NA") -> NA | AK73: =IFERROR(AG514*100/AG293,"NA") -> NA | AM73: =IFERROR(AG735*100/AG293,"NA") -> NA
A74: Taxes on goods and services (current LCU) | B74: GC.TAX.GSRV.CN | C74: Georgia | D74: GEO | E74: 61300000 | F74: 156100000 | G74: 284200000 | H74: 268000000 | I74: 386800000 | J74: 407400000 | K74: 477265000 | L74: 561900000 | M74: 586500000 | N74: 889600000 | O74: 1294200000 | P74: 1679200000 | Q74: 2402300000 | R74: 2587500000 | S74: 2494900000 | T74: 2763900000 | U74: 3399500000 | V74: 3699900000 | W74: 3570100000 | X74: 4108700000 | Y74: 4376200000 | Z74: 4356100000 | AA74: 5573500000 | AB74: 5892600000 | AC74: 6745700000 | AD74: 6152400000 | AE74: 8041800000 | AF74: 9443300000 | AG74: =IFERROR(AVERAGE(E74:AF74),"NA") -> 2952173750 | AI74: =IFERROR(AG74*100/AG294,"NA") -> 12.529337 | AK74: =IFERROR(AG515*100/AG294,"NA") -> 0.31263581 | AM74: =IFERROR(AG736*100/AG294,"NA") -> 8.2897838
A75: Taxes on goods and services (current LCU) | B75: GC.TAX.GSRV.CN | C75: Germany | D75: DEU | E75: 125618000000 | F75: 118486000000 | G75: 118779000000 | H75: 122702000000 | I75: 134076000000 | J75: 137775000000 | K75: 141207000000 | L75: 143405000000 | M75: 147802000000 | N75: 142872000000 | O75: 148024000000 | P75: 152393000000 | Q75: 166970000000 | R75: 170432000000 | S75: 174437000000 | T75: 178610000000 | U75: 190797000000 | V75: 191875000000 | W75: 193302000000 | X75: 197587000000 | Y75: 201422000000 | Z75: 198174000000 | AA75: 206524000000 | AB75: 209301000000 | AC75: 214336000000 | AD75: 187488000000 | AE75: 217415000000 | AF75: .. | AG75: =IFERROR(AVERAGE(E75:AF75),"NA") -> 1.6784478e+11 | AI75: =IFERROR(AG75*100/AG295,"NA") -> 6.3613953 | AK75: =IFERROR(AG516*100/AG295,"NA") -> NA | AM75: =IFERROR(AG737*100/AG295,"NA") -> 4.6653677
A76: Taxes on goods and services (current LCU) | B76: GC.TAX.GSRV.CN | C76: Ghana | D76: GHA | E76: .. | F76: .. | G76: .. | H76: .. | I76: .. | J76: .. | K76: 140928800 | L76: 215883900 | M76: 549683073 | N76: 871089714 | O76: 1053166888 | P76: 1195599344 | Q76: 1548573031 | R76: 1863799358 | S76: 1996424536 | T76: 2436751418 | U76: 3548884820 | V76: 4.2120379e+09 | W76: 4.8329518e+09 | X76: 6.434284e+09 | Y76: 9.9268323e+09 | Z76: 1.2231319e+10 | AA76: 1.3344835e+10 | AB76: 1.5030378e+10 | AC76: 1.7151665e+10 | AD76: 1.7792087e+10 | AE76: .. | AF76: .. | AG76: =IFERROR(AVERAGE(E76:AF76),"NA") -> 5.8188587e+09 | AI76: =IFERROR(AG76*100/AG296,"NA") -> 4.7763616 | AK76: =IFERROR(AG517*100/AG296,"NA") -> 1.9223913 | AM76: =IFERROR(AG738*100/AG296,"NA") -> 5.2634084
A77: Taxes on goods and services (current LCU) | B77: GC.TAX.GSRV.CN | C77: Gibraltar | D77: GIB | E77: .. | F77: .. | G77: .. | H77: .. | I77: .. | J77: .. | K77: .. | L77: .. | M77: .. | N77: .. | O77: .. | P77: .. | Q77: .. | R77: .. | S77: .. | T77: .. | U77: .. | V77: .. | W77: .. | X77: .. | Y77: .. | Z77: .. | AA77: .. | AB77: .. | AC77: .. | AD77: .. | AE77: .. | AF77: .. | AG77: =IFERROR(AVERAGE(E77:AF77),"NA") -> NA | AI77: =IFERROR(AG77*100/AG297,"NA") -> NA | AK77: =IFERROR(AG518*100/AG297,"NA") -> NA | AM77: =IFERROR(AG739*100/AG297,"NA") -> NA
A78: Taxes on goods and services (current LCU) | B78: GC.TAX.GSRV.CN | C78: Greece | D78: GRC | E78: 10975000000 | F78: 12415000000 | G78: 13944000000 | H78: 14790000000 | I78: 16621000000 | J78: 17694000000 | K78: 18618000000 | L78: 20409000000 | M78: 20976000000 | N78: 21784000000 | O78: 22855000000 | P78: 25754000000 | Q78: 28264000000 | R78: 29322000000 | S78: 27326000000 | T78: 28233000000 | U78: 27616000000 | V78: 26243000000 | W78: 25524000000 | X78: 25391000000 | Y78: 25535000000 | Z78: 27165000000 | AA78: 27451000000 | AB78: 28257000000 | AC78: 28785000000 | AD78: 24651000000 | AE78: 27942000000 | AF78: .. | AG78: =IFERROR(AVERAGE(E78:AF78),"NA") -> 2.3131111e+10 | AI78: =IFERROR(AG78*100/AG298,"NA") -> 13.096301 | AK78: =IFERROR(AG519*100/AG298,"NA") -> 0.004852945 | AM78: =IFERROR(AG740*100/AG298,"NA") -> 7.7698136
A79: Taxes on goods and services (current LCU) | B79: GC.TAX.GSRV.CN | C79: Greenland | D79: GRL | E79: .. | F79: .. | G79: .. | H79: .. | I79: .. | J79: .. | K79: .. | L79: .. | M79: .. | N79: .. | O79: .. | P79: .. | Q79: .. | R79: .. | S79: .. | T79: .. | U79: .. | V79: .. | W79: .. | X79: .. | Y79: .. | Z79: .. | AA79: .. | AB79: .. | AC79: .. | AD79: .. | AE79: .. | AF79: .. | AG79: =IFERROR(AVERAGE(E79:AF79),"NA") -> NA | AI79: =IFERROR(AG79*100/AG299,"NA") -> NA | AK79: =IFERROR(AG520*100/AG299,"NA") -> NA | AM79: =IFERROR(AG741*100/AG299,"NA") -> NA
A80: Taxes on goods and services (current LCU) | B80: GC.TAX.GSRV.CN | C80: Grenada | D80: GRD | E80: .. | F80: .. | G80: .. | H80: .. | I80: .. | J80: .. | K80: .. | L80: .. | M80: .. | N80: .. | O80: .. | P80: .. | Q80: .. | R80: .. | S80: .. | T80: .. | U80: .. | V80: .. | W80: .. | X80: .. | Y80: .. | Z80: .. | AA80: .. | AB80: .. | AC80: .. | AD80: .. | AE80: .. | AF80: .. | AG80: =IFERROR(AVERAGE(E80:AF80),"NA") -> NA | AI80: =IFERROR(AG80*100/AG300,"NA") -> NA | AK80: =IFERROR(AG521*100/AG300,"NA") -> NA | AM80: =IFERROR(AG742*100/AG300,"NA") -> NA
A81: Taxes on goods and services (current LCU) | B81: GC.TAX.GSRV.CN | C81: Guam | D81: GUM | E81: .. | F81: .. | G81: .. | H81: .. | I81: .. | J81: .. | K81: .. | L81: .. | M81: .. | N81: .. | O81: .. | P81: .. | Q81: .. | R81: .. | S81: .. | T81: .. | U81: .. | V81: .. | W81: .. | X81: .. | Y81: .. | Z81: .. | AA81: .. | AB81: .. | AC81: .. | AD81: .. | AE81: .. | AF81: .. | AG81: =IFERROR(AVERAGE(E81:AF81),"NA") -> NA | AI81: =IFERROR(AG81*100/AG301,"NA") -> NA | AK81: =IFERROR(AG522*100/AG301,"NA") -> NA | AM81: =IFERROR(AG743*100/AG301,"NA") -> NA
A82: Taxes on goods and services (current LCU) | B82: GC.TAX.GSRV.CN | C82: Guatemala | D82: GTM | E82: 3308040000 | F82: 4429500000 | G82: 5365230000 | H82: 7311630000 | I82: 8885700000 | J82: 9376130000 | K82: 9679220000 | L82: 11435170000 | M82: 12146070000 | N82: 13535950000 | O82: 12800230000 | P82: 16398300000 | Q82: 19623400000 | R82: 20610200000 | S82: 1.9155423e+10 | T82: 2.1265738e+10 | U82: 2.4109314e+10 | V82: 2.5901051e+10 | W82: 27540796114 | X82: 2.7924855e+10 | Y82: 2.9151745e+10 | Z82: 3.0012045e+10 | AA82: 3.2242729e+10 | AB82: 3.41083e+10 | AC82: 3.6749349e+10 | AD82: 3.5146368e+10 | AE82: 4.4666889e+10 | AF82: .. | AG82: =IFERROR(AVERAGE(E82:AF82),"NA") -> 2.0106643e+10 | AI82: =IFERROR(AG82*100/AG302,"NA") -> 6.093166 | AK82: =IFERROR(AG523*100/AG302,"NA") -> 0.73815269 | AM82: =IFERROR(AG744*100/AG302,"NA") -> 3.3392862
A83: Taxes on goods and services (current LCU) | B83: GC.TAX.GSRV.CN | C83: Guinea | D83: GIN | E83: .. | F83: .. | G83: .. | H83: .. | I83: .. | J83: .. | K83: .. | L83: .. | M83: .. | N83: .. | O83: .. | P83: .. | Q83: .. | R83: .. | S83: .. | T83: .. | U83: .. | V83: .. | W83: .. | X83: .. | Y83: .. | Z83: .. | AA83: .. | AB83: .. | AC83: .. | AD83: .. | AE83: .. | AF83: .. | AG83: =IFERROR(AVERAGE(E83:AF83),"NA") -> NA | AI83: =IFERROR(AG83*100/AG303,"NA") -> NA | AK83: =IFERROR(AG524*100/AG303,"NA") -> NA | AM83: =IFERROR(AG745*100/AG303,"NA") -> NA
A84: Taxes on goods and services (current LCU) | B84: GC.TAX.GSRV.CN | C84: Guinea-Bissau | D84: GNB | E84: .. | F84: .. | G84: .. | H84: .. | I84: .. | J84: .. | K84: .. | L84: .. | M84: .. | N84: .. | O84: .. | P84: .. | Q84: .. | R84: .. | S84: .. | T84: .. | U84: .. | V84: .. | W84: .. | X84: .. | Y84: .. | Z84: .. | AA84: 33721498281 | AB84: .. | AC84: 30212009841 | AD84: .. | AE84: .. | AF84: .. | AG84: =IFERROR(AVERAGE(E84:AF84),"NA") -> 31966754061 | AI84: =IFERROR(AG84*100/AG304,"NA") -> 7.0254755 | AK84: =IFERROR(AG525*100/AG304,"NA") -> 5.3992392 | AM84: =IFERROR(AG746*100/AG304,"NA") -> 4.8062079
A85: Taxes on goods and services (current LCU) | B85: GC.TAX.GSRV.CN | C85: Guyana | D85: GUY | E85: .. | F85: .. | G85: .. | H85: .. | I85: .. | J85: .. | K85: .. | L85: .. | M85: .. | N85: .. | O85: .. | P85: .. | Q85: .. | R85: .. | S85: .. | T85: .. | U85: .. | V85: .. | W85: .. | X85: .. | Y85: .. | Z85: .. | AA85: .. | AB85: .. | AC85: .. | AD85: .. | AE85: .. | AF85: .. | AG85: =IFERROR(AVERAGE(E85:AF85),"NA") -> NA | AI85: =IFERROR(AG85*100/AG305,"NA") -> NA | AK85: =IFERROR(AG526*100/AG305,"NA") -> NA | AM85: =IFERROR(AG747*100/AG305,"NA") -> NA
A86: Taxes on goods and services (current LCU) | B86: GC.TAX.GSRV.CN | C86: Haiti | D86: HTI | E86: .. | F86: .. | G86: .. | H86: .. | I86: .. | J86: .. | K86: .. | L86: .. | M86: .. | N86: .. | O86: .. | P86: .. | Q86: .. | R86: .. | S86: .. | T86: .. | U86: .. | V86: .. | W86: .. | X86: .. | Y86: .. | Z86: .. | AA86: .. | AB86: .. | AC86: .. | AD86: .. | AE86: .. | AF86: .. | AG86: =IFERROR(AVERAGE(E86:AF86),"NA") -> NA | AI86: =IFERROR(AG86*100/AG306,"NA") -> NA | AK86: =IFERROR(AG527*100/AG306,"NA") -> NA | AM86: =IFERROR(AG748*100/AG306,"NA") -> NA
A87: Taxes on goods and services (current LCU) | B87: GC.TAX.GSRV.CN | C87: Honduras | D87: HND | E87: .. | F87: .. | G87: .. | H87: .. | I87: .. | J87: .. | K87: .. | L87: .. | M87: 13357700000 | N87: 15262800000 | O87: 17008400000 | P87: 19687700000 | Q87: 23384475000 | R87: 25911400000 | S87: 24299850000 | T87: 26686150000 | U87: 29929640000 | V87: 32825970000 | W87: 34470971446 | X87: 4.3895244e+10 | Y87: 5.0989917e+10 | Z87: .. | AA87: .. | AB87: .. | AC87: .. | AD87: 5.6864648e+10 | AE87: .. | AF87: .. | AG87: =IFERROR(AVERAGE(E87:AF87),"NA") -> 2.961249e+10 | AI87: =IFERROR(AG87*100/AG307,"NA") -> 9.5192155 | AK87: =IFERROR(AG528*100/AG307,"NA") -> 0.84730634 | AM87: =IFERROR(AG749*100/AG307,"NA") -> 4.6517992
A88: Taxes on goods and services (current LCU) | B88: GC.TAX.GSRV.CN | C88: Hong Kong SAR, China | D88: HKG | E88: .. | F88: .. | G88: .. | H88: .. | I88: .. | J88: .. | K88: .. | L88: .. | M88: .. | N88: .. | O88: .. | P88: .. | Q88: .. | R88: .. | S88: .. | T88: .. | U88: .. | V88: .. | W88: .. | X88: .. | Y88: .. | Z88: .. | AA88: .. | AB88: .. | AC88: .. | AD88: .. | AE88: .. | AF88: .. | AG88: =IFERROR(AVERAGE(E88:AF88),"NA") -> NA | AI88: =IFERROR(AG88*100/AG308,"NA") -> NA | AK88: =IFERROR(AG529*100/AG308,"NA") -> NA | AM88: =IFERROR(AG750*100/AG308,"NA") -> NA
A89: Taxes on goods and services (current LCU) | B89: GC.TAX.GSRV.CN | C89: Hungary | D89: HUN | E89: 709170000000 | F89: 851827000000 | G89: 1060478000000 | H89: 1318474000000 | I89: 1523111000000 | J89: 1814330000000 | K89: 1940379000000 | L89: 2129841000000 | M89: 2456599000000 | N89: 2878030000000 | O89: 2969404000000 | P89: 3072181000000 | Q89: 3407992000000 | R89: 3536270000000 | S89: 3625297000000 | T89: 4025486000000 | U89: 4165808000000 | V89: 4586919000000 | W89: 4766934000000 | X89: 5145100000000 | Y89: 5515904000000 | Z89: 5474777000000 | AA89: 5847636000000 | AB89: 6523046000000 | AC89: 7058851000000 | AD89: 7337883000000 | AE89: 8178701000000 | AF89: .. | AG89: =IFERROR(AVERAGE(E89:AF89),"NA") -> 3.7748307e+12 | AI89: =IFERROR(AG89*100/AG309,"NA") -> 13.618645 | AK89: =IFERROR(AG530*100/AG309,"NA") -> 0.33540372 | AM89: =IFERROR(AG751*100/AG309,"NA") -> 6.5424893
A90: Taxes on goods and services (current LCU) | B90: GC.TAX.GSRV.CN | C90: Iceland | D90: ISL | E90: 67508000000 | F90: 74255800000 | G90: 78787500000 | H90: 95357400000 | I90: 107810600000 | J90: 110561000000 | K90: 107397262000 | L90: 115451773580 | M90: 125534126091 | N90: 147628670464 | O90: 173826680831 | P90: 193447754217 | Q90: 205506232508 | R90: 1.9284262e+11 | S90: 175552237342 | T90: 1.8535831e+11 | U90: 197005002049 | V90: 213576295760 | W90: 222835698133 | X90: 2.3589367e+11 | Y90: 2.5933421e+11 | Z90: 2.874053e+11 | AA90: 322961437613 | AB90: 3.3732606e+11 | AC90: 337640971442 | AD90: 327192896824 | AE90: 369511536077 | AF90: 430147296189 | AG90: =IFERROR(AVERAGE(E90:AF90),"NA") -> 2.0348773e+11 | AI90: =IFERROR(AG90*100/AG310,"NA") -> 12.253587 | AK90: =IFERROR(AG531*100/AG310,"NA") -> 0.24965063 | AM90: =IFERROR(AG752*100/AG310,"NA") -> 9.1961187
A91: Taxes on goods and services (current LCU) | B91: GC.TAX.GSRV.CN | C91: India | D91: IND | E91: 419050000000 | F91: 470140000000 | G91: 507460000000 | H91: 565270000000 | I91: 653730000000 | J91: 726790000000 | K91: 775930000000 | L91: 883260000000 | M91: 1006270000000 | N91: 1151640000000 | O91: 1387530000000 | P91: 1621410000000 | Q91: 1768090000000 | R91: 1855250000000 | S91: 1736160000000 | T91: 2187440000000 | U91: 2516400000000 | V91: 3265750000000 | W91: 3870900000000 | X91: 3684626200000 | Y91: 5106480000000 | Z91: 6517900000000 | AA91: 8136460000000 | AB91: 10197450000000 | AC91: .. | AD91: .. | AE91: .. | AF91: .. | AG91: =IFERROR(AVERAGE(E91:AF91),"NA") -> 2.5421411e+12 | AI91: =IFERROR(AG91*100/AG311,"NA") -> 2.8323156 | AK91: =IFERROR(AG532*100/AG311,"NA") -> 1.1207294 | AM91: =IFERROR(AG753*100/AG311,"NA") -> 3.9932093
A92: Taxes on goods and services (current LCU) | B92: GC.TAX.GSRV.CN | C92: Indonesia | D92: IDN | E92: 27183000000000 | F92: 27342000000000 | G92: 32119400000000 | H92: 39305000000000 | I92: 55952300000000 | J92: .. | K92: 79781000000000 | L92: 95128800000000 | M92: 112300273021133 | N92: 135167200000000 | O92: .. | P92: .. | Q92: .. | R92: 266472000000000 | S92: 256251000000000 | T92: 304797000000000 | U92: 354809000000000 | V92: 432612000000000 | W92: 493166000000000 | X92: 527655429222292 | Y92: 568928959372087 | Z92: 556820527274173 | AA92: 634995332475415 | AB92: 697512871633752 | AC92: 704537914447775 | AD92: 627122541837655 | AE92: 747807437528937 | AF92: .. | AG92: =IFERROR(AVERAGE(E92:AF92),"NA") -> 3.3816378e+14 | AI92: =IFERROR(AG92*100/AG312,"NA") -> 4.804385 | AK92: =IFERROR(AG533*100/AG312,"NA") -> 0.3995512 | AM92: =IFERROR(AG754*100/AG312,"NA") -> 5.2330342
A93: Taxes on goods and services (current LCU) | B93: GC.TAX.GSRV.CN | C93: Iran, Islamic Rep. | D93: IRN | E93: 2708000000000 | F93: 3691000000000 | G93: 6463000000000 | H93: 7459000000000 | I93: 17997527000000 | J93: 10192062000000 | K93: 9027225000000 | L93: 10480100000000 | M93: 1.3200452e+13 | N93: 1.34534e+13 | O93: 1.8981505e+13 | P93: 1.9521456e+13 | Q93: 2.4369826e+13 | R93: 2.3640531e+13 | S93: 36640900000000 | T93: .. | U93: .. | V93: .. | W93: .. | X93: .. | Y93: .. | Z93: .. | AA93: .. | AB93: .. | AC93: .. | AD93: .. | AE93: .. | AF93: .. | AG93: =IFERROR(AVERAGE(E93:AF93),"NA") -> 1.4521732e+13 | AI93: =IFERROR(AG93*100/AG313,"NA") -> 0.11004703 | AK93: =IFERROR(AG534*100/AG313,"NA") -> 0.1925528 | AM93: =IFERROR(AG755*100/AG313,"NA") -> 0.42137896
A94: Taxes on goods and services (current LCU) | B94: GC.TAX.GSRV.CN | C94: Iraq | D94: IRQ | E94: .. | F94: .. | G94: .. | H94: .. | I94: .. | J94: .. | K94: .. | L94: .. | M94: .. | N94: .. | O94: .. | P94: .. | Q94: .. | R94: .. | S94: .. | T94: .. | U94: .. | V94: .. | W94: .. | X94: 264431000000 | Y94: 3.2942932e+11 | Z94: 7.9829247e+11 | AA94: 2.9565449e+11 | AB94: 3.1199317e+11 | AC94: 374431257275 | AD94: .. | AE94: .. | AF94: .. | AG94: =IFERROR(AVERAGE(E94:AF94),"NA") -> 3.9570528e+11 | AI94: =IFERROR(AG94*100/AG314,"NA") -> 0.27055042 | AK94: =IFERROR(AG535*100/AG314,"NA") -> 0.63816572 | AM94: =IFERROR(AG756*100/AG314,"NA") -> 1.6997815
A95: Taxes on goods and services (current LCU) | B95: GC.TAX.GSRV.CN | C95: Ireland | D95: IRL | E95: 6886984000 | F95: 7652192000 | G95: 8539758000 | H95: 9727321000 | I95: 11042869000 | J95: 13626870000 | K95: 13937170000 | L95: 15450335000 | M95: 16747254000 | N95: 18749527000 | O95: 21430111000 | P95: 24176944000 | Q95: 24769644000 | R95: 21463799000 | S95: 17314576000 | T95: 16962954000 | U95: 16621732000 | V95: 17011464000 | W95: 18091820000 | X95: 20042862000 | Y95: 21249984000 | Z95: 22187994000 | AA95: 23300004000 | AB95: 24129168000 | AC95: 25678637000 | AD95: 22598502000 | AE95: 27442710000 | AF95: .. | AG95: =IFERROR(AVERAGE(E95:AF95),"NA") -> 1.8030859e+10 | AI95: =IFERROR(AG95*100/AG315,"NA") -> 8.9271272 | AK95: =IFERROR(AG536*100/AG315,"NA") -> NA | AM95: =IFERROR(AG757*100/AG315,"NA") -> 10.630055
A96: Taxes on goods and services (current LCU) | B96: GC.TAX.GSRV.CN | C96: Isle of Man | D96: IMN | E96: .. | F96: .. | G96: .. | H96: .. | I96: .. | J96: .. | K96: .. | L96: .. | M96: .. | N96: .. | O96: .. | P96: .. | Q96: .. | R96: .. | S96: .. | T96: .. | U96: .. | V96: .. | W96: .. | X96: .. | Y96: .. | Z96: .. | AA96: .. | AB96: .. | AC96: .. | AD96: .. | AE96: .. | AF96: .. | AG96: =IFERROR(AVERAGE(E96:AF96),"NA") -> NA | AI96: =IFERROR(AG96*100/AG316,"NA") -> NA | AK96: =IFERROR(AG537*100/AG316,"NA") -> NA | AM96: =IFERROR(AG758*100/AG316,"NA") -> NA
A97: Taxes on goods and services (current LCU) | B97: GC.TAX.GSRV.CN | C97: Israel | D97: ISR | E97: 35915000000 | F97: 41523000000 | G97: 45970000000 | H97: 49164000000 | I97: 54153000000 | J97: 60881001000 | K97: 61056140000 | L97: 66865300000 | M97: 6.7362584e+10 | N97: 7.0743666e+10 | O97: 7.4723302e+10 | P97: 78555400000 | Q97: 8.5312228e+10 | R97: 8.8500786e+10 | S97: 9.1675812e+10 | T97: 1.030712e+11 | U97: 1.0965184e+11 | V97: 1.124967e+11 | W97: 1.233425e+11 | X97: 1.3284945e+11 | Y97: 1.375681e+11 | Z97: 1.4308293e+11 | AA97: 1.4275892e+11 | AB97: 148660505714 | AC97: 1.5312259e+11 | AD97: 1.4871624e+11 | AE97: 1.7753559e+11 | AF97: .. | AG97: =IFERROR(AVERAGE(E97:AF97),"NA") -> 9.6491029e+10 | AI97: =IFERROR(AG97*100/AG317,"NA") -> 10.785749 | AK97: =IFERROR(AG538*100/AG317,"NA") -> 0.23948948 | AM97: =IFERROR(AG759*100/AG317,"NA") -> 10.418939
A98: Taxes on goods and services (current LCU) | B98: GC.TAX.GSRV.CN | C98: Italy | D98: ITA | E98: 90225000000 | F98: 90631000000 | G98: 98781000000 | H98: 107783000000 | I98: 114046000000 | J98: 113727000000 | K98: 113826000000 | L98: 117741000000 | M98: 116775000000 | N98: 122741000000 | O98: 127098000000 | P98: 136104000000 | Q98: 139407000000 | R98: 135424000000 | S98: 130994000000 | T98: 142841000000 | U98: 148537000000 | V98: 153534000000 | W98: 152599000000 | X98: 158345000000 | Y98: 159878000000 | Z98: 166473000000 | AA98: 170349000000 | AB98: 173197000000 | AC98: 176603000000 | AD98: 154309000000 | AE98: 178020000000 | AF98: .. | AG98: =IFERROR(AVERAGE(E98:AF98),"NA") -> 1.3666622e+11 | AI98: =IFERROR(AG98*100/AG318,"NA") -> 9.0529046 | AK98: =IFERROR(AG539*100/AG318,"NA") -> NA | AM98: =IFERROR(AG760*100/AG318,"NA") -> 12.877966
A99: Taxes on goods and services (current LCU) | B99: GC.TAX.GSRV.CN | C99: Jamaica | D99: JAM | E99: 2.1813173e+10 | F99: 2.3044094e+10 | G99: 2.4463683e+10 | H99: 2.844271e+10 | I99: 3.3106374e+10 | J99: 3.65694e+10 | K99: 39089942291 | L99: 44826778315 | M99: 57006371500 | N99: 65017303900 | O99: 70226143000 | P99: 82792997500 | Q99: 92286990983 | R99: 1.0108748e+11 | S99: 110993518706 | T99: 1.3380733e+11 | U99: 1.3881848e+11 | V99: 1.5524445e+11 | W99: 174308539291 | X99: 189900857222 | Y99: 2.1561101e+11 | Z99: 2.4346868e+11 | AA99: 2.7642472e+11 | AB99: 3.006519e+11 | AC99: 313438600000 | AD99: 2.6360201e+11 | AE99: .. | AF99: .. | AG99: =IFERROR(AVERAGE(E99:AF99),"NA") -> 1.2446321e+11 | AI99: =IFERROR(AG99*100/AG319,"NA") -> 11.138618 | AK99: =IFERROR(AG540*100/AG319,"NA") -> 2.5754469 | AM99: =IFERROR(AG761*100/AG319,"NA") -> 8.8365627
A100: Taxes on goods and services (current LCU) | B100: GC.TAX.GSRV.CN | C100: Japan | D100: JPN | E100: .. | F100: .. | G100: .. | H100: .. | I100: .. | J100: .. | K100: .. | L100: .. | M100: .. | N100: .. | O100: .. | P100: .. | Q100: .. | R100: .. | S100: .. | T100: .. | U100: .. | V100: .. | W100: .. | X100: .. | Y100: .. | Z100: .. | AA100: .. | AB100: .. | AC100: .. | AD100: .. | AE100: .. | AF100: .. | AG100: =IFERROR(AVERAGE(E100:AF100),"NA") -> NA | AI100: =IFERROR(AG100*100/AG320,"NA") -> NA | AK100: =IFERROR(AG541*100/AG320,"NA") -> NA | AM100: =IFERROR(AG762*100/AG320,"NA") -> NA
...

Sheet vérification des erreurs 
B3: verif erreurs
A4: Afghanistan | B4: NA | C4: NA | D4: 12.221166 | E4: 3.4954979 | F4: -1.5282862 | G4: 59.095889 | H4: -2.4809625 | I4: 115.7132 | J4: 100.72019 | K4: 29.139934 | L4: -1.4200903 | M4: -1.4936953 | N4: -1.7212338 | O4: -1.3154747
A5: Albania | B5: 4.7096771 | C5: 7.3052022 | D5: 28.234992 | E5: -0.51387055 | F5: -0.30570641 | G5: 76.962704 | H5: -0.07743383 | I5: 87.204486 | J5: 39.967874 | K5: 5.6691786 | L5: -0.6724434 | M5: 0.020878915 | N5: -0.53877781 | O5: 0.034698074
A6: Algeria | B6: 1.2472527 | C6: 7.9593136 | D6: 30.722778 | E6: 1.694848 | F6: -0.57214574 | G6: 72.826667 | H6: -1.2189323 | I6: 107.48072 | J6: 22.097866 | K6: 5.4010473 | L6: -0.64930455 | M6: -0.96427201 | N6: -0.84774298 | O6: -0.97832619
A7: American Samoa | B7: NA | C7: NA | D7: NA | E7: -0.59425675 | F7: 0.45066375 | G7: NA | H7: 0.99981607 | I7: 107.93092 | J7: 86.952467 | K7: 38.056991 | L7: 0.88248917 | M7: 0.26575818 | N7: 1.1612325 | O7: 0.91652832
A8: Andorra | B8: 1.2707207 | C8: 10.241794 | D8: NA | E8: 0.95837133 | F8: 1.572452 | G8: NA | H8: 1.3621018 | I8: 89.527079 | J8: 89.524159 | K8: 13.653441 | L8: 1.252925 | M8: 1.3059024 | N8: 1.3283595 | O8: 1.3110088
A9: Angola | B9: 1.3160424 | C9: 7.4239911 | D9: 26.839838 | E9: 3.4720108 | F9: -1.0962019 | G9: 54.111889 | H9: -0.76937486 | I9: 110.11878 | J9: 90.954865 | K9: 49.593525 | L9: -1.2330975 | M9: -1.0589671 | N9: -1.2683666 | O9: -1.1383518
A10: Antigua and Barbuda | B10: 0.90711749 | C10: 9.516668 | D10: NA | E10: 1.1964416 | F10: 1.2284783 | G10: 76.391519 | H10: 0.86728527 | I10: 114.70298 | J10: 98.955017 | K10: 74.241269 | L10: 0.80119645 | M10: 0.54966119 | N10: 0.71992285 | O10: 0.55544067
A11: Argentina | B11: 0.97085591 | C11: 9.2072688 | D11: 16.526854 | E11: 1.0467921 | F11: 0.309166 | G11: 75.272593 | H11: -0.062694981 | I11: 99.739047 | J11: 89.30783 | K11: 41.944904 | L11: -0.34692161 | M11: -0.52550969 | N11: -0.51334566 | O11: 0.40665429
A12: Armenia | B12: 6.5264997 | C12: 6.8331314 | D12: 24.927534 | E12: -0.69069393 | F12: -0.07553162 | G12: 72.329667 | H12: -0.27584209 | I12: NA | J12: NA | K12: NA | L12: -0.55545039 | M12: 0.15242438 | N12: -0.35538289 | O12: -0.47553955
A13: Aruba | B13: 0.35870917 | C13: 10.292076 | D13: NA | E13: 1.2643374 | F13: -0.22971242 | G13: 74.586444 | H13: 1.2768626 | I13: 115.11915 | J13: 113.40096 | K13: NA | L13: 1.1393865 | M13: 1.0875311 | N13: 1.1622112 | O13: 1.1683587
A14: Australia | B14: 1.6403108 | C14: 10.579234 | D14: 25.514464 | E14: 1.3528714 | F14: 1.1339919 | G14: 81.006775 | H14: 0.98132158 | I14: 102.78112 | J14: 146.69508 | K14: 101.18495 | L14: 1.8690129 | M14: 1.7265004 | N14: 1.7302952 | O14: 1.3990897
A15: Austria | B15: 1.205426 | C15: 10.427935 | D15: 23.921077 | E15: 0.46585597 | F15: 1.6610913 | G15: 79.828726 | H15: 1.0967106 | I15: 101.698 | J15: 100.66312 | K15: 73.446607 | L15: 1.6486806 | M15: 1.4838394 | N15: 1.8280325 | O15: 1.3867748
A16: Azerbaijan | B16: 6.1970333 | C16: 7.0053337 | D16: 26.805767 | E16: 1.0320249 | F16: 1.6619661 | G16: 68.094741 | H16: -0.74111291 | I16: 98.485199 | J16: 84.919172 | K16: 25.63076 | L16: -1.0847096 | M16: -0.47731127 | N16: -0.82028031 | O16: -1.3069318
A17: Bahamas, The | B17: 0.2367812 | C17: 10.254516 | D17: 26.505855 | E17: 1.1876735 | F17: -0.55437021 | G17: 72.391037 | H17: 0.94337777 | I17: 96.945866 | J17: 29.503661 | K17: 3.1290701 | L17: 1.2644203 | M17: 0.58671984 | N17: 0.75484677 | O17: 0.98894457
A18: Bahrain | B18: 0.66403743 | C18: 9.9234554 | D18: 23.467916 | E18: 3.2461176 | F18: 0.91198128 | G18: 77.508111 | H18: -0.45629006 | I18: 102.61714 | J18: 155.73887 | K18: 67.336749 | L18: 0.20715693 | M18: 0.68849758 | N18: 0.42452549 | O18: -1.0894483
A19: Bangladesh | B19: 4.3885534 | C19: 6.3273817 | D19: 26.658804 | E19: 1.4017432 | F19: 0.45139074 | G19: 67.719222 | H19: -1.1891145 | I19: 103.30039 | J19: 39.306518 | K19: 8.4604723 | L19: -1.0820966 | M19: -0.93982781 | N19: -0.82140678 | O19: -0.48791288
A20: Barbados | B20: 0.57238029 | C20: 9.5623417 | D20: 16.778978 | E20: 0.26202587 | F20: -0.75506117 | G20: 75.431556 | H20: 1.0822522 | I20: 67.930978 | J20: 24.278902 | K20: 3.9475652 | L20: 1.4049004 | M20: 0.75509913 | N20: 0.98860834 | O20: 1.1252438
A21: Belarus | B21: 4.507885 | C21: 7.542472 | D21: 27.849921 | E21: -0.36706017 | F21: 1.1357789 | G21: 70.638432 | H21: 0.078517446 | I21: 105.78866 | J21: 55.475698 | K21: 12.775785 | L21: -0.43211972 | M21: -1.1852769 | N21: -1.0220175 | O21: -1.4641737
A22: Belgium | B22: 1.2814957 | C22: 10.352328 | D22: 22.601563 | E22: 0.5153448 | F22: -0.83133648 | G22: 79.565086 | H22: 0.7702138 | I22: 101.35388 | J22: 92.131931 | K22: 55.878957 | L22: 1.437862 | M22: 1.2696099 | N22: 1.3549161 | O22: 1.3580424
A23: Belize | B23: 0.81824313 | C23: 8.5109323 | D23: 17.747519 | E23: 2.5506879 | F23: 1.5396026 | G23: 71.090037 | H23: 0.21959279 | I23: 96.8926 | J23: 90.5701 | K23: 40.954326 | L23: -0.15975439 | M23: -0.28267077 | N23: -0.39967279 | O23: 0.65727731
A24: Benin | B24: 1.6630842 | C24: 6.6900349 | D24: 19.800557 | E24: 2.9029332 | F24: -0.2037761 | G24: 57.924815 | H24: 0.25150338 | I24: NA | J24: 83.060659 | K24: 14.33432 | L24: -0.54896374 | M24: -0.45623376 | N24: -0.50650971 | O24: 0.18884809
A25: Bermuda | B25: 0.64051094 | C25: 11.402198 | D25: 12.636803 | E25: 0.24499 | F25: -0.50903461 | G25: 79.759667 | H25: 0.8931456 | I25: 93.126175 | J25: 84.573198 | K25: 35.584385 | L25: 1.2607275 | M25: 1.2075273 | N25: 0.90820859 | O25: 1.0565776
A26: Bhutan | B26: NA | C26: 6.8505578 | D26: 50.534339 | E26: 1.4506695 | F26: 1.1320169 | G26: 66.759296 | H26: 0.89031048 | I26: 100.13653 | J26: 98.674237 | K26: 71.284453 | L26: 1.0714155 | M26: -0.63584256 | N26: 0.33951693 | O26: -0.47107942
A27: Bolivia | B27: 1.9385795 | C27: 7.5319022 | D27: 17.404931 | E27: 1.6535913 | F27: 0.4656296 | G27: 64.634926 | H27: -0.45960037 | I27: 115.03735 | J27: 78.156679 | K27: 21.133021 | L27: -0.68099136 | M27: -0.71039483 | N27: -0.90665773 | O27: -0.014136566
A28: Bosnia and Herzegovina | B28: 7.9975228 | C28: 6.6651979 | D28: 24.760237 | E28: -0.54094737 | F28: -0.51303612 | G28: 75.672074 | H28: -0.45036886 | I28: 104.79967 | J28: 88.698727 | K28: 33.22389 | L28: -0.42206778 | M28: -0.2956734 | N28: -0.36336778 | O28: -0.075485842
A29: Botswana | B29: 1.6572815 | C29: 8.3597135 | D29: 26.430882 | E29: 1.9973979 | F29: -0.78058553 | G29: 57.751111 | H29: 1.0226195 | I29: NA | J29: 76.921761 | K29: NA | L29: 0.85730213 | M29: 0.66657609 | N29: 0.52307551 | O29: 0.53779007
A30: Brazil | B30: 1.1274772 | C30: 8.7833225 | D30: 18.155147 | E30: 1.0386144 | F30: 0.4347906 | G30: 72.110111 | H30: -0.22298419 | I30: 114.16318 | J30: 102.71184 | K30: 41.292828 | L30: -0.18316958 | M30: 0.037600805 | N30: -0.22986735 | O30: 0.41737558
A31: British Virgin Islands | B31: NA | C31: NA | D31: NA | E31: 2.1274138 | F31: -0.220761 | G31: 74.936481 | H31: NA | I31: 99.755564 | J31: 107.51422 | K31: 55.078339 | L31: NA | M31: NA | N31: 0.58958852 | O31: NA
A32: Brunei Darussalam | B32: -0.75369466 | C32: 10.477734 | D32: 26.477194 | E32: 1.5374863 | F32: 0.96167488 | G32: 74.443963 | H32: 1.1823548 | I32: 102.4183 | J32: 87.681696 | K32: 20.312394 | L32: 0.60866668 | M32: 0.95820407 | N32: -0.12190507 | O32: -0.79594648
A33: Bulgaria | B33: 3.2515765 | C33: 8.3004406 | D33: 19.762658 | E33: -0.95353456 | F33: -0.021032884 | G33: 72.952647 | H33: 0.28493553 | I33: 94.839586 | J33: 62.908112 | K33: 10.062492 | L33: -0.21097233 | M33: 0.52859139 | N33: -0.51396338 | O33: 0.45300526
A34: Burkina Faso | B34: 2.7088643 | C34: 5.8748969 | D34: 18.681561 | E34: 2.891211 | F34: -0.71028564 | G34: 54.921556 | H34: -0.52705767 | I34: 102.91694 | J34: 73.603632 | K34: 15.048078 | L34: -0.19425634 | M34: -0.32293118 | N34: -1.2744365 | O34: -0.27706748
A35: Burundi | B35: -1.1070687 | C35: 5.8696251 | D35: 11.193935 | E35: 2.9860086 | F35: -1.3055631 | G35: 54.540593 | H35: -1.7116444 | I35: 72.826495 | J35: 13.562921 | K35: 2.1412545 | L35: -1.1802308 | M35: -1.0978512 | N35: 0.49301043 | O35: -1.1844699
A36: Cabo Verde | B36: 3.8240248 | C36: 7.1457307 | D36: NA | E36: 1.392329 | F36: 0.015781369 | G36: 72.108037 | H36: 0.86119937 | I36: 99.134542 | J36: 106.40359 | K36: 68.096208 | L36: 0.85061409 | M36: -0.14638214 | N36: -1.0834278 | O36: 0.86588946
A37: Cambodia | B37: 5.1987922 | C37: 5.9373314 | D37: 18.689547 | E37: 1.6256615 | F37: -0.78932999 | G37: 64.998222 | H37: -0.32878124 | I37: 102.53375 | J37: 98.211111 | K37: 50.570209 | L37: -1.1679486 | M37: -0.4676546 | N37: -1.1248985 | O37: -1.0185148
A38: Cameroon | B38: 1.1824101 | C38: 6.956266 | D38: 18.571178 | E38: 2.771044 | F38: -0.88050299 | G38: 56.344259 | H38: -0.81236008 | I38: NA | J38: NA | K38: NA | L38: -1.1602667 | M38: -0.8756812 | N38: 1.7256276 | O38: -1.0582847
A39: Canada | B39: 1.1936863 | C39: 10.392443 | D39: 22.067825 | E39: 1.0515855 | F39: 1.7686003 | G39: 80.547309 | H39: 1.050072 | I39: 101.98573 | J39: 94.32557 | K39: 61.490332 | L39: 1.8909337 | M39: 1.6459304 | N39: 0.97377473 | O39: 1.4662967
A40: Cayman Islands | B40: NA | C40: NA | D40: NA | E40: 2.7944841 | F40: 1.3340247 | G40: 82.190244 | H40: 1.116959 | I40: 103.89109 | J40: 77.333903 | K40: 29.060357 | L40: 0.9968462 | M40: 1.1143373 | N40: -1.5203608 | O40: 0.79565808
A41: Central African Republic | B41: -0.99971073 | C41: 6.1703299 | D41: 12.95163 | E41: 1.9988948 | F41: -1.5470561 | G41: 49.143667 | H41: -1.8363351 | I41: 78.425447 | J41: 46.217832 | K41: 7.670532 | L41: -1.1691322 | M41: -1.2455818 | N41: -1.3720946 | O41: -1.1112256
A42: Chad | B42: 1.4518322 | C42: 5.9914633 | D42: 25.112545 | E42: 3.5316887 | F42: -1.3283807 | G42: 49.56537 | H42: -1.4087013 | I42: 102.10665 | J42: 39.452959 | K42: 9.6269121 | L42: -1.4089354 | M42: -1.1191018 | N42: 1.1240322 | O42: -1.3026839
A43: Channel Islands | B43: NA | C43: NA | D43: NA | E43: 0.71573516 | F43: 1.0032518 | G43: 80.382519 | H43: NA | I43: 93.56225 | J43: 39.913814 | K43: 5.3561082 | L43: NA | M43: NA | N43: -0.41876498 | O43: NA
A44: Chile | B44: 2.548012 | C44: 8.8925512 | D44: 24.151439 | E44: 1.1490237 | F44: 0.16483272 | G44: 78.096704 | H44: 0.45257032 | I44: 100.21441 | J44: 43.993693 | K44: 6.9048595 | L44: 1.2765119 | M44: 1.3410719 | N44: -0.47267379 | O44: 1.0187498
A45: China | B45: 7.8037544 | C45: 7.326485 | D45: 39.149926 | E45: 0.60584619 | F45: -0.14735298 | G45: 74.66763 | H45: -0.44223798 | I45: 118.87128 | J45: 90.810651 | K45: 39.58527 | L45: -0.36800981 | M45: -0.30139017 | N45: -1.0391197 | O45: -1.585438
A46: Colombia | B46: 1.8507405 | C46: 8.3357811 | D46: 20.241807 | E46: 1.3752278 | F46: -1.5955256 | G46: 73.696704 | H46: -1.4401395 | I46: 101.31864 | J46: 48.692416 | K46: 5.6211945 | L46: -0.33412937 | M46: 0.16580784 | N46: -1.6963502 | O46: -0.11648015
A47: Comoros | B47: 0.67923634 | C47: 7.0345068 | D47: 15.834981 | E47: 2.0337449 | F47: -1.655485 | G47: 60.854037 | H47: -0.27499165 | I47: 108.02459 | J47: 79.114567 | K47: 12.535652 | L47: -0.857356 | M47: -1.2677857 | N47: -1.2059673 | O47: -0.48531915
A48: Congo, Dem. Rep. | B48: 0.46729697 | C48: 6.1447129 | D48: 15.714788 | E48: 3.1044315 | F48: -1.2024508 | G48: 55.174519 | H48: -2.1516318 | I48: 109.68691 | J48: 93.568459 | K48: 48.267352 | L48: -1.4495876 | M48: -1.5190175 | O48: -1.4343621
A49: Congo, Rep. | B49: -0.76685751 | C49: 7.648743 | D49: 34.97185 | E49: 2.875113 | F49: -0.32221309 | G49: 58.835074 | H49: -0.67157251 | I49: 102.23934 | J49: 92.254179 | K49: 49.526065 | L49: -1.1947403 | M49: -1.2518737 | N49: 0.50043687 | O49: -1.1353801
A50: Costa Rica | B50: 2.5135083 | C50: 8.8345755 | D50: 19.484288 | E50: 1.4118084 | F50: 0.27578656 | G50: 78.340222 | H50: 0.67705354 | I50: 148.0991 | J50: 107.88845 | K50: 19.283002 | L50: 0.56095784 | M50: 0.573025 | N50: -1.0136226 | O50: 1.0532039
A51: Cote d'Ivoire | B51: 1.3080167 | C51: 7.4448981 | D51: 18.682953 | E51: 2.5467415 | F51: -0.8863061 | G51: 54.350074 | H51: -1.2378577 | I51: 101.50555 | J51: 93.930294 | K51: 31.052102 | L51: -0.77235409 | M51: -0.6173169 | N51: 0.081630565 | O51: -0.77897928
